Workbook

Sheet ENTRADAS
A1: 46752 | E1: SISTEMA SC-6 , SC-10 e SC-14 ORÇAMENTO DADOS DE ENTRADA E CÁLCULOS | M1: DATA: | O1: 45638 | BJ1: J
M2: REVISÃO: | O2: 3 | BJ2: S
E3: CLIENTE: | F3: Passarelli | M3: =IF(H11=0,0,"LOCAL:") -> LOCAL:
E4: OBRA: | F4: 12 tqs Nereda | M4: =H11 -> São Paulo - Tatuapé | P4: =IF(H11=0,0,VLOOKUP(E11,BI1292:BJ1318,2,0)) -> SP
C8: DADOS DE ENTRADA GERAL | BJ8: X
B10: LOCALIZAÇÃO DA OBRA: | E10: ESTADO: | H10: MUNICÍPIO: | M10: DISTÂNCIA RODOVIÁRIA
E11: São Paulo | H11: São Paulo - Tatuapé | M11: 1000 | O11: km
D13: =IF(E15>14,"ALTURA DO PAINEL MAIOR QUE 14,00 m ! PLANILHA NÃO ATENDE !",0) -> 0 | BJ13: Y
C15: ALTURA DO TANQUE (Ht) | E15: 7.15 | F15: m | G15: =IF(G18=0,0,"altura do painel = ") -> altura do painel = | I15: =IF(E15=0,0,E15+G18) -> 7.3 | J15: =IF(E15=0,0,"m") -> m | BJ15: 1
C16: ALTURA DE USO (Hu) | E16: 6.4 | F16: m (de projeto) | BJ16: 2
C17: MUDAR DIMENSÃO (Hu) | F17: m (caso queira alterar o Hu somente nos cálculos)
C18: ALTURA DE ANCORAGEM NA BASE ( h1) | G18: =IF(J18=0,0.15,J18) -> 0.15 | H18: m ( para alterar ) | BJ18: 3
BJ19: 4
F20: 1 | G20: 2 | H20: 3 | BJ20: 5
C21: QUANTIDADE DE TANQUES= | F21: 12 | G21: =IF(F21=1,"unidade","unidades") -> unidades
C22: QUANTIDADE DE TANQUES= | F22: =IF(F21>4,4,F21) -> 4 | G22: =IF(F22=1,"unidade","unidades") -> unidades
C25: DIÂMETRO INTERNO DO TANQUE ( PROJETO ): | G25: 47 | H25: m
G26: =IF(C37+C41+C45=0,0,VLOOKUP(BJ8,D37:O45,11,0)) -> 47.041151 | H26: =IF(G26=0,0,"m ( novo valor do diâmetro )") -> m ( novo valor do diâmetro )
D28: VOLUME ÚTIL DE PROJETO= | G28: =PI()*(G25/2)^2*E16 -> 11103.645 | H28: m³ | Q28: =IF(OR(G25>'TABELA SC-10 e 14'!B83,G25>'TABELA SC-10 e 14'!C83),10,0) -> 0
D30: VOLUME ÚTIL ADEQUADO= | G30: =RELATÓRIO!W10 -> 11132.918 | H30: m³ | I30: =IF(C32<>0,0,IF(I32<>0,"ALERTA !",0)) -> 0 | Q30: =IF(OR(G25>'TABELA SC-10 e 14'!B83,G25>'TABELA SC-10 e 14'!C83),10,0) -> 0
C32: =IF(G25=0,0,IF(ENTRADAS!G25<O32+O33+O35,"O DIÂMETRO MÍNIMO É "&O32+O33+O35&" m",0)) -> 0 | I32: =IF(C32<>0,0,IF(AND(E15<=6,G25<='TABELA SC-10 e 14'!D33),0,IF(AND(E15<=7,G25<='TABELA SC-10 e 14'!B68),0,IF(AND(E15<=8,G25<='TABELA SC-10 e 14'!B83),0,IF(G25=0,0,IF(Q35=110,"OS CÁLCULOS ESTÃO SENDO FEITOS, PORÉM ",IF(AND(E15<=6,G25>'TABELA SC-10 e 14'!D33,G25<='TABELA SC-10 e 14'!C126),0,IF('TABELA SC-10 e 14'!C2>'TABELA SC-10 e 14'!A125,"EXCEDEU O LIMITE MÁXIMO PERMITIDO,",IF(OR('TABELA SC-10 e 14'!H84=0,'TABELA SC-10 e 14'!C2>'TABELA SC-10 e 14'!A83),"OS CÁLCULOS ESTÃO SENDO FEITOS, PORÉM ",0))))))))) -> 0 | O32: =IF('TABELA SC-10 e 14'!A2="SC6",'TABELA SC-10 e 14'!D5,0) -> 0 | Q32: =IF(G25<='TABELA SC-10 e 14'!C125,100,0) -> 100 | BF32: =IF(AND(E15<=8,G25<='TABELA SC-10 e 14'!B83),0,I32) -> 0
I33: =IF('TABELA SC-10 e 14'!C2>'TABELA SC-10 e 14'!A103,"VERIFICAR COM ENGENHARIA",IF('TABELA SC-10 e 14'!C2>'TABELA SC-10 e 14'!A83,"O DIÂMETRO ESTÁ ALÉM DA TABELA PADRÃO, ",0)) -> 0 | O33: =IF('TABELA SC-10 e 14'!A2="SC10",'TABELA SC-10 e 14'!B5,0) -> 8.5142424
C35: DIÂMETRO INTERNO DO TANQUE NO SISTEMA ( marcar "X" ): | I35: =IF(C32<>0,0,IF(AND(E15<=6,G25<='TABELA SC-10 e 14'!D33),0,IF(AND(E15<=7,G25<='TABELA SC-10 e 14'!B68),0,IF(AND(E15<=8,G25<='TABELA SC-10 e 14'!B83),0,IF(G25=0,0,IF(Q35=110,"CONFIRMAR COM ENGENHARIA SE É POSSÍVEL.",IF(AND(E15<=6,G25>'TABELA SC-10 e 14'!D33,G25<='TABELA SC-10 e 14'!C126),0,IF('TABELA SC-10 e 14'!C2>'TABELA SC-10 e 14'!A125,"",IF(OR('TABELA SC-10 e 14'!H84=0,'TABELA SC-10 e 14'!C2>'TABELA SC-10 e 14'!A83),"CONFIRMAR COM ENGENHARIA SE É POSSÍVEL.",0))))))))) -> 0 | O35: =IF('TABELA SC-10 e 14'!A2="SC14",'TABELA SC-10 e 14'!C5,0) -> 0 | Q35: =Q30+Q32 -> 100
C36: as quantidade são para apenas 1 tanque | Q36: =IF(G66="X","SC6",IF(G60="X","SC10",IF(I60="X","SC14",0))) -> 0
C37: =IF(D37="X",1,0) -> 0 | E37: =IF(O42=10,0,IF(G25=0,0,IF(N45=0," OPÇÃO 1 - - - PARA MENOS - - -",0))) -> OPÇÃO 1 - - - PARA MENOS - - - | H37: =IF(O42=10,0,IF('TABELA SC-10 e 14'!D2=11,0,IF(G25=0,0,IF(N45=0,'TABELA SC-10 e 14'!D2,0)))) -> 61 | I37: =IF(O42=10,0,IF(G25=0,0,IF('TABELA SC-10 e 14'!D2=11,0,IF(N45=0,"PAINÉIS E DIÂMETRO PASSA PARA =",0)))) -> PAINÉIS E DIÂMETRO PASSA PARA = | N37: =IF(O42=10,0,IF(N45=0,IF(G25=0,0,'TABELA SC-10 e 14'!K2),0)) -> 46.273356 | O37: =IF(O42=10,0,IF(G25=0,0,IF(N45=0,"m",0))) -> m
I38: =IF(O42=10,0,IF(N37=0,0," O DIÂMETRO DIMINUI =")) -> O DIÂMETRO DIMINUI = | M38: =IF(O42=10,0,IF(N37=0,0,G25-N37)) -> 0.72664384 | N38: =IF(O42=10,0,IF(N37=0,0,"m")) -> m
E39: =IF(E15=0,0,IF(O42=10,"esta não",IF(N37=0,"esta não",IF(M38=0,0,"marque 'X' somente na opção 1 e veja quanto -------")))) -> marque 'X' somente na opção 1 e veja quanto ------- | I39: =IF(O42=10,0,IF(N37=0,0,"--------------- O VOLUME DIMINUI =")) -> --------------- O VOLUME DIMINUI = | M39: =IF(D37="x",IF(O42=10,0,IF(N37=0,0,G28-F131)),0) -> 0 | N39: =IF(O42=10,0,IF(N37=0,0,"m³")) -> m³
C41: =IF(D41="X",1,0) -> 1 | D41: x | E41: =IF(E15=0,0,IF(O42=10," MARCAR ESTA OPÇÃO ---------------",IF(G25=0,0,IF(N45=0," OPÇÃO 2 - - - PARA MAIS - - - - - -"," OPÇÃO 1 - - - PARA MENOS - - - - - -")))) -> OPÇÃO 2 - - - PARA MAIS - - - - - - | H41: =IF(G25=0,0,'TABELA SC-10 e 14'!I2) -> 62 | I41: =IF(G25=0,0,"PAINÉIS E DIÂMETRO PASSA PARA =") -> PAINÉIS E DIÂMETRO PASSA PARA = | N41: =IF(G25=0,0,'TABELA SC-10 e 14'!L2) -> 47.041151 | O41: =IF(G25=0,0,"m") -> m
I42: =IF(G25=0,0,IF(N41=G25,"O DIÂMETRO ZEROU",IF(N41=0,0,IF(G25>N41," O DIÂMETRO DIMINUI ="," O DIÂMETRO AUMENTA =")))) -> O DIÂMETRO AUMENTA = | M42: =IF(N41=0,0,IF(G25-N41<0,(G25-N41)*-1,G25-N41)) -> 0.041150642 | N42: =IF(N41=0,0,"m") -> m | O42: =IF(M42<0.01,10,0) -> 0
E43: =IF(E15=0,0,IF(N45=0,"marque 'X' somente na opção 2 e veja quanto","marque 'X' somente na opção 1 e veja quanto --------")) -> marque 'X' somente na opção 2 e veja quanto | I43: =IF(G25=0,0,IF(N41=G25,"O VOLUME ZEROU",IF(N41=0,0,IF(G25>N41,"--------------- O VOLUME DIMINUI =","--------------- O VOLUME AUMENTA =")))) -> --------------- O VOLUME AUMENTA = | M43: =IF(D41="x",IF(N41=0,0,IF(G25-N41<0,(G28-F131)*-1,G25-N41)),0) -> 29.27304 | N43: =IF(N41=0,0,"m³") -> m³
C45: =IF(D45="X",1,0) -> 0 | E45: =IF(N45=0,0," OPÇÃO 2 - - - PARA MAIS - - - - - -") -> 0 | H45: =IF(O42=10,0,IF(G25=0,0,'TABELA SC-10 e 14'!J2)) -> 0 | I45: =IF(O42=10,0,IF(N45=0,0,"PAINÉIS E DIÂMETRO PASSA PARA =")) -> 0 | N45: =IF(O42=10,0,IF(G25=0,0,'TABELA SC-10 e 14'!M2)) -> 0 | O45: =IF(O42=10,0,IF(H45=0,0,"m")) -> 0
I46: =IF(O42=10,0,IF(N45=0,0," O DIÂMETRO AUMENTA =")) -> 0 | M46: =IF(O42=10,0,IF(N45=0,0,N45-G25)) -> 0 | N46: =IF(O42=10,0,IF(N45=0,0,"m")) -> 0
E47: =IF(E15=0,0,IF(M46=0,"esta não","marque 'X' somente na opção 2 e veja quanto")) -> esta não | I47: =IF(O42=10,0,IF(N45=0,0," O VOLUME AUMENTA =")) -> 0 | M47: =IF(D45="x",IF(O42=10,0,IF(N45=0,0,(G28-F131)*-1)),0) -> 0 | N47: =IF(O42=10,0,IF(N45=0,0,"m³")) -> 0
C50: =IF(F21<>4,"PAREDES DO TANQUE --------- AS QUANTIDADES NA PLANILHA INSUMOS SÃO PARA 4 TANQUES","PAREDES DO TANQUE") -> PAREDES DO TANQUE --------- AS QUANTIDADES NA PLANILHA INSUMOS SÃO PARA 4 TANQUES
L52: observações ( caso necessário ): | BJ52: 6
C53: TIPO DE SISTEMA ( analisado apenas 1 tanque )
C54: =IF(I15=0,0,IF(AND(E15<=4,G25>'TABELA SC-10 e 14'!B83,G25<='TABELA SC-10 e 14'!B89),0,IF(OR('TABELA SC-10 e 14'!AB12<>0,'TABELA SC-10 e 14'!AB13<>0,'TABELA SC-10 e 14'!AC13<>0),"X",0))) -> 0 | D54: =IF(AND(E15<=4,G25>'TABELA SC-10 e 14'!B83,G25<='TABELA SC-10 e 14'!B89),0,IF('TABELA SC-10 e 14'!AB12="SC10","PELA TABELA SOPLACAS ESTE DÂMETRO E ESSA ALTURA NÃO PERMITEM O SC-6 !",IF('TABELA SC-10 e 14'!AB13="SC14","PELA TABELA SOPLACAS ESTE DÂMETRO E ESSA ALTURA NÃO PERMITEM O SC-10 !",IF('TABELA SC-10 e 14'!AC13="SC14","PELA TABELA SOPLACAS ESTE DÂMETRO E ESSA ALTURA NÃO PERMITEM O SC-10 !",0)))) -> 0
D55: =IF(AND(E15<=4,G25>'TABELA SC-10 e 14'!B83,G25<='TABELA SC-10 e 14'!B89),0,IF('TABELA SC-10 e 14'!AB12="SC10","LOGO, MARQUE 'X' NA CAIXA À DIREITA ( SC-10)",IF('TABELA SC-10 e 14'!AB13="SC14","LOGO, MARQUE 'X' NA CAIXA À DIREITA ( SC-14)",IF('TABELA SC-10 e 14'!AC13="SC14","LOGO, MARQUE 'X' NA CAIXA À DIREITA ( SC-14)",0)))) -> 0
D56: =IF(AND(E15<=4,G25>'TABELA SC-10 e 14'!B83,G25<='TABELA SC-10 e 14'!B89),0,IF('TABELA SC-10 e 14'!AB12="SC10","MAS, SE QUISER CONTINUAR COM O SISTEMA DA REGRA AUTOMÁTICA, ",IF('TABELA SC-10 e 14'!AB13="SC14","MAS, SE QUISER CONTINUAR COM O SISTEMA DA REGRA AUTOMÁTICA, ",IF('TABELA SC-10 e 14'!AC13="SC14","MAS, SE QUISER CONTINUAR COM O SISTEMA DA REGRA AUTOMÁTICA, ",0)))) -> 0
D57: =IF(AND(E15<=4,G25>'TABELA SC-10 e 14'!B83,G25<='TABELA SC-10 e 14'!B89),0,IF('TABELA SC-10 e 14'!AB12="SC10"," ENTÃO MARQUE 'X' NA CAIXA À DIREITA ( SC-10) CONFIRMANDO ESTE SISTEMA",IF('TABELA SC-10 e 14'!AB13="SC14"," ENTÃO MARQUE 'X' NA CAIXA À DIREITA ( SC-10) CONFIRMANDO ESTE SISTEMA",IF('TABELA SC-10 e 14'!AC13="SC14"," ENTÃO MARQUE 'X' NA CAIXA À DIREITA ( SC-10) CONFIRMANDO ESTE SISTEMA",0)))) -> 0
G58: TIPO DE SISTEMA ( marcar "X") | BJ58: 7
C59: (REGRA AUTOMÁTICA EM FUNÇÃO DA ALTURA h2): | G59: (MUDANÇA MANUAL SE NECESSÁRIO): | BJ59: 8
C60: =IF(I15=0,0,IF(G66="X",0,IF(I60="X",0,IF(G65="X",0,IF(G60="X","X",IF(E15<=10,"X",0)))))) -> X | D60: SC-10 | E60: =IF(I15=0,0,IF(G60="X",0,IF(G65="X",0,IF(I60="X","X",IF(E15>10,"X",0))))) -> 0 | F60: SC-14 | H60: SC-10 | J60: SC-14 | BJ60: 9
BJ61: 10
C65: =IF(I15=0,0,IF(G60="X",0,IF(I60="X",0,IF(G65="X","X",IF(AND(E15<=6,G25<='TABELA SC-10 e 14'!D33),"X",0))))) -> 0 | D65: SC-6 | H65: SC-6
G66: =IF(G65="X","X",C65) -> 0 | H66: =IF(I15<=6,"SIM",0) -> 0 | I66: =IF(M23=0,0,IF(K66="X",0,IF(M66="X","X",IF(M23>10,"X",0)))) -> 0 | J66: =IF(I15<=6,"NÃO",0) -> 0
G67: SC-10 | BJ67: 11
BJ68: 12
BJ69: 13
BJ73: 14
BJ74: 15
BJ75: 16
C87: =IF(I15=0,0,"O DIÂMETRO ATUAL ESTÁ NO SISTEMA "&'TABELA SC-10 e 14'!A2&" SE NÃO FOR ESTE MARQUE X E MUDE") -> O DIÂMETRO ATUAL ESTÁ NO SISTEMA SC10 SE NÃO FOR ESTE MARQUE X E MUDE
C90: PAINEL FECHO ( marcar "X"): apenas para 1 tanque
D91: JÁ HÁ PROJETO. -------- QUANTIDADE= | H91: unid.
C93: X | D93: NÃO HÁ PROJETO.------ QUANTIDADE= | G93: =CÁLCULOS!G46 -> 2 | H93: unid.
C97: PAINÉIS NORNAIS ( para 1 tanque) -- QUANTIDADE= | G97: =IF(G25=0,0,(VLOOKUP(BJ8,D37:H45,5,0))-(G91+G93)) -> 60 | H97: unid.
C101: Alerta: Canaletas com dimensões internas maior que 100x100 cm devem ser analisadas!
C103: CANALETA - interligada ao painel ( marcar "X" ): | G103: DIMENSÕES DA CANALETA:
D104: SIM | E104: X | F104: NÃO | G104: A (m)= | H104: B (m)= | I104: L (m)= | J104: M (m)=
C105: =IF(F248="X",1000,0) -> 0
C109: BEIRAL DE APOIO - interligado ao painel ( marcar "X" ): | H109: DIMENSÕES DO BEIRAL :
D110: SIM | E110: X | F110: NÃO | H110: R (m)= | I110: S (m)= | J110: T (m)=
C111: =IF(C110="X",1000,0) -> 0
C115: PESO DA CANALETA POR UNID.: | F115: =((G105*H105)+(I105*J105))*2.4*2500 -> 0 | G115: kg
C117: PESO DO BEIRAL POR UNID.: | F117: =((H111*I111)+(H111*J111/2))*2.4*2500 -> 0 | G117: kg
C121: EXECUÇÃO DA BASE INCLUÍDA (marcar "X":
D122: SIM | F122: NÃO
J123: SC10 | L123: SC14
C125: RESULTADOS 1 | I125: quant= | J125: =IF(C60="x",(VLOOKUP(BJ8,D37:H45,5,0)),0) -> 62 | L125: =IF(E60="x",VLOOKUP(BJ8,D37:H45,5,0),0) -> 0
C126: RAIO NA JUNTA ENTRE PAINÉIS (Rj)= | F126: =CÁLCULOS!F77 -> 23.551111 | H126: m | I126: raio na junta | J126: =IF(C60="x",1.205/SIN(PI()/(VLOOKUP(BJ8,D37:H45,5,0)))-0.24,0) -> 23.551111 | L126: =IF(E60="x",1.205/SIN(PI()/(VLOOKUP(BJ8,D37:H45,5,0)))-0.3,0) -> 0
C127: RAIO NO CENTRO DO PAINEL (Rc)= | F127: =CÁLCULOS!F78 -> 23.520883 | H127: m | I127: raio no centro | J127: =IF(C60="x",J126*COS(PI()/J125),0) -> 23.520883 | L127: =IF(E60="x",L126*COS(PI()/L125),0) -> 0
C128: DISTÂNCIA INT. ENTRE PAINÉIS (d)= | F128: =CÁLCULOS!F79 -> 2.3856884 | H128: m | I128: d | J128: =IF(C60="X",2*J127*TAN(PI()/J125),0) -> 2.3856884 | L128: =IF(E60="X",2*L127*TAN(PI()/L125),0) -> 0
C129: ÁREA DE PISO INTERNO = | F129: =CÁLCULOS!F80 -> 1739.5185 | H129: m² | I129: área piso | J129: =J125*J128*J127/2 -> 1739.5185 | L129: =L125*L128*L127/2 -> 0
C130: VOLUME TOTAL DO TANQUE= | F130: =CÁLCULOS!F81 -> 12437.557 | H130: m³ | I130: vol total | J130: =J129*E15 -> 12437.557 | L130: =L129*E15 -> 0
C131: VOLUME ÚTIL ( USO) DO TANQUE= | F131: =CÁLCULOS!F82 -> 11132.918 | H131: m³ | I131: vol útil | J131: =J129*E16 -> 11132.918 | L131: =L129*E16 -> 0
C132: ÁREA DE PAINEL FABRICADO= | F132: =CÁLCULOS!F83 -> 4344.96 | H132: m² | I132: área de painel | J132: =J125*I15*2.4 -> 1086.24 | L132: =L125*I15*2.4 -> 0
J137: somente | L137: incluindo
C138: INSUMOS de M.O. ( PRODUTIVA ) MONTAGEM COMPLETA | J138: H normais | L138: H a mais
C139: ENCARREGADO | J139: =C738*9*(L878) -> 1545.3 | L139: =J139+(C738*9*(L878)*L797/100) -> 1931.625 | M139: h
C140: TECNICO DE EDIFICAÇÕES | J140: =C739*9*(L878) -> 909 | L140: =J140+(C739*9*(L878)*L797/100) -> 1136.25 | M140: h
C141: TÉCNICO DE SEGURANÇA | J141: =C740*9*(L878) -> 0 | L141: =J141+(C740*9*(L878)*L797/100) -> 0 | M141: h
C142: OFICIAL POLIVALENTE | J142: =C741*9*C734*(L878) -> 7272 | L142: =J142+(C741*9*(L878)*L797/100) -> 9090 | M142: h
C143: AUXILIAR DE OBRAS | J143: =C742*C734*9*C734*(L878) -> 909 | L143: =J143+(C742*9*(L878)*L797/100) -> 1136.25 | M143: h
C145: ÍNDICE de M.O. ( PRODUTIVA) MONTAGEM COMPLETA ( horas / m² de painel) | J145: somente | L145: incluindo
J146: H normais | L146: H a mais
C147: ENCARREGADO | J147: =IF(I15=0,0,J139/($F$132)) -> 0.35565345 | L147: =IF(I15=0,0,L139/$F$132) -> 0.44456681 | M147: h/m² de painel
C148: TECNICO DE EDIFICAÇÕES | J148: =J140/($F$132) -> 0.20920791 | L148: =L140/$F$132 -> 0.26150989 | M148: h/m² de painel
C149: TÉCNICO DE SEGURANÇA | J149: =J141/($F$132) -> 0 | L149: =L141/$F$132 -> 0 | M149: h/m² de painel
C150: OFICIAL POLIVALENTE | J150: =IF(I15=0,0,J142/($F$132)) -> 1.6736633 | L150: =IF(I15=0,0,L142/$F$132) -> 2.0920791 | M150: h/m² de painel
C151: AUXILIAR DE OBRAS | J151: =IF(I15=0,0,J143/($F$132)) -> 0.20920791 | L151: =IF(I15=0,0,L143/$F$132) -> 0.26150989 | M151: h/m² de painel
I152: SOMA= | J152: =IF(I15=0,0,SUM(J148:J151)) -> 2.0920791 | L152: =IF(I15=0,0,SUM(L148:L151)) -> 2.6150989 | M152: h/m² de painel
C154: INSUMOS DE M.O. ( MONTAGEM - TOTAL COM MOBILIZAÇÃO - PARA CUSTO ) | L154: dias
L155: corridos
C156: ENCARREGADO | L156: =$L$885*$C$734*C738 -> 193.8 | M156: dias corridos
C157: TECNICO DE EDIFICAÇÕES | L157: =$L$885*$C$734*C739 -> 114 | M157: dias corridos
C158: TÉCNICO DE SEGURANÇA | L158: =$L$885*$C$734*C740 -> 0 | M158: dias corridos
C159: OFICIAL POLIVALENTE | L159: =$L$885*$C$734*C741 -> 912 | M159: dias corridos
C160: AUXILIAR DE OBRAS | L160: =$L$885*$C$734*C742 -> 114 | M160: dias corridos
C162: MONTAGEM COMPLETA - MATERIAIS E EQUIPAMENTOS DE SEGURANÇA
...

Sheet TABELA SC-10 e 14
A1: SISTEMA | B1: diâmentro de projeto | C1: quant. painéis real | D1: quant. painéis para baixo | I1: quant. painéis para cima | J1: quant. painéis extra | K1: diâmentro para baixo | L1: diâmentro para cima | M1: diâmentro extra | O1: maior diâmetro possível | T1: 0.03939 | V1: ANTES ERA =ENTRADAS!G59
A2: =IF(AND(ENTRADAS!Q35=110,ENTRADAS!Q36<>0),IF(ENTRADAS!G66="X","SC6",IF(CÁLCULOS!C19="X","SC10",IF(CÁLCULOS!E19="X","SC14",0))),IF(ENTRADAS!Q35=110,"SC14",IF(ENTRADAS!G66="X","SC6",IF(CÁLCULOS!C19="X","SC10",IF(CÁLCULOS!E19="X","SC14",0))))) -> SC10 | B2: =CÁLCULOS!G23 -> 47 | C2: =IF(B2=0,0,IF(A2="SC6",PI()*(B2+0.09)/2.1,IF(A2="SC10",PI()*(B2+0.24)/2.4,IF(A2="SC14",PI()*(B2+0.3)/2.4,0)))) -> 61.837015 | D2: =ROUNDDOWN(IF(B2=0,0,IF(A2="SC6",PI()*(B2+0.09)/2.1,IF(A2="SC10",PI()*(B2+0.24)/2.4,IF(A2="SC14",PI()*(B2+0.3)/2.4,0)))),0) -> 61 | I2: =ROUNDUP(IF(B2=0,0,IF(A2="SC6",PI()*(B2+0.09)/2.1,IF(A2="SC10",PI()*(B2+0.24)/2.4,IF(A2="SC14",PI()*(B2+0.3)/2.4,0)))),0) -> 62 | J2: =IF(L2=0,0,IF(L2<B2,I2+1,0)) -> 0 | K2: =IF(D2<A5,0,IF(D2>A125,0,IF(B2=0,0,IF(A2="SC6",VLOOKUP(D2,A5:D125,4,0),IF(A2="SC10",VLOOKUP(D2,A5:B125,2,0),IF(A2="SC14",VLOOKUP(D2,A5:C125,3,0),0)))))) -> 46.273356 | L2: =IF(I2>A125,0,IF(B2=0,0,IF(A2="SC6",VLOOKUP(I2,A5:D125,4,0),IF(A2="SC10",VLOOKUP(I2,A5:B125,2,0),IF(A2="SC14",VLOOKUP(I2,A5:C125,3,0),0))))) -> 47.041151 | M2: =IF(J2=0,0,IF(J2>A125,0,IF(L2<B2,N2,0))) -> 0 | N2: =IF(A2="SC6",VLOOKUP(I2+1,A5:D125,4,0),IF(A2="SC10",VLOOKUP(I2+1,A5:D125,2,0),IF(A2="SC14",VLOOKUP(I2+1,A5:D125,3,0),0))) -> 47.808924 | O2: =LARGE(B5:D189,1) -> 101.52889
B3: Diâm. Interno no meio do painel | C3: Diâm. Interno no meio do painel | D3: Diâm. Interno no meio do painel | I3: Ângulo teta p/ confecção | J3: área à 90° | K3: altura h à 90° | L3: a= | M3: c= | N3: b= | O3: distância superior entre formas | P3: desconto dos triangulos | Q3: desconto da parte superior | R3: área desconto lateral(2X) | S3: área do miolo inferior | T3: área Real final da secção SEM miolo inferior | U3: % redução
A4: Nº PAINÉIS | B4: SC10 | C4: SC14 | D4: SC6 | E4: altura max | F4: diâm min | G4: diâm max | AB4: Como a capacidade de carga de carretas é definida pelo semi-reboque acoplado ao cavalo mecânico, os tipos diferentes são:
A5: 12 | B5: =(1.205/TAN(PI()/A5)-0.24)*2 -> 8.5142424 | C5: =(1.205/TAN(PI()/A5)-0.295)*2 -> 8.4042424 | D5: =((2.1+0.006-0.005)/2/TAN(PI()/A5)-0.07)*2 -> 7.7010387 | E5: =IF(AND(ENTRADAS!$E$15>13,ENTRADAS!$E$15<=14),14,0) -> 0 | F5: =IF(E5>0,$C$5,0) -> 0 | G5: =IF(E5>0,$C$63,0) -> 0 | H5: =IF(E5=0,0,IF(AND(ENTRADAS!$G$25>=F5,ENTRADAS!$G$25<=G5),1,0)) -> 0 | I5: =180/A5 -> 15 | J5: 0.479 | K5: 0.24328 | L5: =K5*TAN(PI()*I5/180) -> 0.06518668 | M5: =L5*SIN(PI()*(I5/2)/180) -> 0.0085085691 | N5: =M5*COS(PI()*(I5)/180) -> 0.0082186466 | O5: =CÁLCULOS!$F$79 -> 2.3856884 | P5: =L5*K5 -> 0.015858615 | Q5: =(O5-(2*L5))*N5 -> 0.018535637 | R5: =P5+Q5 -> 0.034394253 | S5: =$T$1 -> 0.03939 | T5: =IF($U$1="X",J5-R5-S5,J5-R5) -> 0.44460575 | U5: =(J5-T5)/J5*100 -> 7.1804285 | W5: nº painéis | X5: diâmetro | Y5: lógica | Z5: tipo sistema | AB5: Carreta 2 eixos: semi reboque com 2 eixos. Comprimento máximo de 18,15 metros. Capacidade de carga: 23 toneladas. Peso bruto máximo de 33 toneladas. Peso máximo permitido por eixo: 6 no eixo dianteiro, 10 no eixo central, 17 no eixo traseiro.
A6: 13 | B6: =(1.205/TAN(PI()/A6)-0.24)*2 -> 9.2977544 | C6: =(1.205/TAN(PI()/A6)-0.295)*2 -> 9.1877544 | D6: =((2.1+0.006-0.005)/2/TAN(PI()/A6)-0.07)*2 -> 8.3840921 | E6: =IF(AND(ENTRADAS!$E$15>13,ENTRADAS!$E$15<=14),14,0) -> 0 | F6: =IF(E6>0,$C$5,0) -> 0 | G6: =IF(E6>0,$C$63,0) -> 0 | H6: =IF(E6=0,0,IF(AND(ENTRADAS!$G$25>=F6,ENTRADAS!$G$25<=G6),1,0)) -> 0 | I6: =180/A6 -> 13.846154 | J6: 0.479 | K6: 0.24328 | L6: =K6*TAN(PI()*I6/180) -> 0.059963135 | M6: =L6*SIN(PI()*(I6/2)/180) -> 0.0072277572 | N6: =M6*COS(PI()*(I6)/180) -> 0.0070177317 | O6: =CÁLCULOS!$F$79 -> 2.3856884 | P6: =L6*K6 -> 0.014587831 | Q6: =(O6-(2*L6))*N6 -> 0.015900511 | R6: =P6+Q6 -> 0.030488342 | S6: =$T$1 -> 0.03939 | T6: =IF($U$1="X",J6-R6-S6,J6-R6) -> 0.44851166 | U6: =(J6-T6)/J6*100 -> 6.3649983 | W6: =IF(ENTRADAS!D37="X",'TABELA SC-10 e 14'!D2,IF(ENTRADAS!D41="X",'TABELA SC-10 e 14'!I2,IF(ENTRADAS!D45="X",'TABELA SC-10 e 14'!J2,0))) -> 62 | X6: =IF(W6=0,0,VLOOKUP(W6,$A$5:$B$126,2,0)) -> 47.041151 | Y6: =IF(AND(ENTRADAS!E15<=6,X6<=B75),100,IF(AND(ENTRADAS!E15>6,ENTRADAS!E15<7,X6>=B68,X6<=B76),1000,IF(AND(ENTRADAS!E15>=6,ENTRADAS!E15<7,X6>=B68),1000,100))) -> 100 | Z6: =IF(ENTRADAS!E15>10,"SC14",IF(ENTRADAS!Q35=110,"SC14",IF(AND(Y11>=100,Y11<=500),"SC10",IF(AND(Y11>=1000,Y11<=5000),"SC14",0)))) -> SC10 | AB6: Carreta 3 eixos: semi reboque com 3 eixos. Comprimento máximo: 18,15 metros. Capacidade de carga: até 25 toneladas. Peso bruto máximo: 41,5 toneladas. Peso máximo permitido por eixo: 6 toneladas no eixo dianteiro, 10 no eixo central, 25,5 no eixo traseiro.
A7: 14 | B7: =(1.205/TAN(PI()/A7)-0.24)*2 -> 10.0789 | C7: =(1.205/TAN(PI()/A7)-0.295)*2 -> 9.9688999 | D7: =((2.1+0.006-0.005)/2/TAN(PI()/A7)-0.07)*2 -> 9.0650824 | E7: =IF(AND(ENTRADAS!$E$15>13,ENTRADAS!$E$15<=14),14,0) -> 0 | F7: =IF(E7>0,$C$5,0) -> 0 | G7: =IF(E7>0,$C$63,0) -> 0 | H7: =IF(E7=0,0,IF(AND(ENTRADAS!$G$25>=F7,ENTRADAS!$G$25<=G7),1,0)) -> 0 | I7: =180/A7 -> 12.857143 | J7: 0.479 | K7: 0.24328 | L7: =K7*TAN(PI()*I7/180) -> 0.055527072 | M7: =L7*SIN(PI()*(I7/2)/180) -> 0.0062170596 | N7: =M7*COS(PI()*(I7)/180) -> 0.0060611849 | O7: =CÁLCULOS!$F$79 -> 2.3856884 | P7: =L7*K7 -> 0.013508626 | Q7: =(O7-(2*L7))*N7 -> 0.013786979 | R7: =P7+Q7 -> 0.027295605 | S7: =$T$1 -> 0.03939 | T7: =IF($U$1="X",J7-R7-S7,J7-R7) -> 0.45170439 | U7: =(J7-T7)/J7*100 -> 5.6984562 | Y7: =IF(AND(ENTRADAS!E15<=7,X6<=B67),100,IF(AND(ENTRADAS!E15>7,ENTRADAS!E15<8,X6>=B61,X6<=B68),1000,IF(AND(ENTRADAS!E15>=7,ENTRADAS!E15<8,X6>=B61),1000,100))) -> 100 | AB7: Carreta cavalo trucado: um cavalo mecânico trucado e semi reboque com 3 eixos. Comprimento máximo: 18,15 metros. Capacidade de carga: até 30,50 toneladas. Peso bruto máximo: 45 a 46 toneladas. Peso máximo permitido por eixo: 6 toneladas no eixo dianteiro, 10 no primeiro eixo, 10 no segundo eixo, 17 no eixo traseiro.
A8: 15 | B8: =(1.205/TAN(PI()/A8)-0.24)*2 -> 10.858159 | C8: =(1.205/TAN(PI()/A8)-0.295)*2 -> 10.748159 | D8: =((2.1+0.006-0.005)/2/TAN(PI()/A8)-0.07)*2 -> 9.7444279 | E8: =IF(AND(ENTRADAS!$E$15>13,ENTRADAS!$E$15<=14),14,0) -> 0 | F8: =IF(E8>0,$C$5,0) -> 0 | G8: =IF(E8>0,$C$63,0) -> 0 | H8: =IF(E8=0,0,IF(AND(ENTRADAS!$G$25>=F8,ENTRADAS!$G$25<=G8),1,0)) -> 0 | I8: =180/A8 -> 12 | J8: 0.479 | K8: 0.24328 | L8: =K8*TAN(PI()*I8/180) -> 0.05171076 | M8: =L8*SIN(PI()*(I8/2)/180) -> 0.0054052463 | N8: =M8*COS(PI()*(I8)/180) -> 0.0052871287 | O8: =CÁLCULOS!$F$79 -> 2.3856884 | P8: =L8*K8 -> 0.012580194 | Q8: =(O8-(2*L8))*N8 -> 0.012066639 | R8: =P8+Q8 -> 0.024646833 | S8: =$T$1 -> 0.03939 | T8: =IF($U$1="X",J8-R8-S8,J8-R8) -> 0.45435317 | U8: =(J8-T8)/J8*100 -> 5.1454765 | Y8: =IF(AND(ENTRADAS!E15<=8,X6<=B60),100,IF(AND(ENTRADAS!E15>8,ENTRADAS!E15<9,X6>=B55,X6<=B61),1000,IF(AND(ENTRADAS!E15>=8,ENTRADAS!E15<9,X6>=B55),1000,100))) -> 100
A9: 16 | B9: =(1.205/TAN(PI()/A9)-0.24)*2 -> 11.635888 | C9: =(1.205/TAN(PI()/A9)-0.295)*2 -> 11.525888 | D9: =((2.1+0.006-0.005)/2/TAN(PI()/A9)-0.07)*2 -> 10.42244 | E9: =IF(AND(ENTRADAS!$E$15>13,ENTRADAS!$E$15<=14),14,0) -> 0 | F9: =IF(E9>0,$C$5,0) -> 0 | G9: =IF(E9>0,$C$63,0) -> 0 | H9: =IF(E9=0,0,IF(AND(ENTRADAS!$G$25>=F9,ENTRADAS!$G$25<=G9),1,0)) -> 0 | I9: =180/A9 -> 11.25 | J9: 0.479 | K9: 0.24328 | L9: =K9*TAN(PI()*I9/180) -> 0.048391401 | M9: =L9*SIN(PI()*(I9/2)/180) -> 0.0047431867 | N9: =M9*COS(PI()*(I9)/180) -> 0.0046520477 | O9: =CÁLCULOS!$F$79 -> 2.3856884 | P9: =L9*K9 -> 0.01177266 | Q9: =(O9-(2*L9))*N9 -> 0.010648098 | R9: =P9+Q9 -> 0.022420758 | S9: =$T$1 -> 0.03939 | T9: =IF($U$1="X",J9-R9-S9,J9-R9) -> 0.45657924 | U9: =(J9-T9)/J9*100 -> 4.6807428 | Y9: =IF(AND(ENTRADAS!E15<=9,X6<=B54),100,IF(AND(ENTRADAS!E15>9,ENTRADAS!E15<10,X6>=B50,X6<=B55),1000,IF(AND(ENTRADAS!E15>=9,ENTRADAS!E15<10,X6>=B50),1000,100))) -> 100 | AA9: =IF(AND(Z6="SC10",Z14="xiii"),500,0) -> 500 | AB9: =IF(AND(A2="SC6",Z6="SC10"),500,0) -> 0 | AC9: =AA9+AB9 -> 500
A10: 17 | B10: =(1.205/TAN(PI()/A10)-0.24)*2 -> 12.412361 | C10: =(1.205/TAN(PI()/A10)-0.295)*2 -> 12.302361 | D10: =((2.1+0.006-0.005)/2/TAN(PI()/A10)-0.07)*2 -> 11.099357 | E10: =IF(AND(ENTRADAS!$E$15>13,ENTRADAS!$E$15<=14),14,0) -> 0 | F10: =IF(E10>0,$C$5,0) -> 0 | G10: =IF(E10>0,$C$63,0) -> 0 | H10: =IF(E10=0,0,IF(AND(ENTRADAS!$G$25>=F10,ENTRADAS!$G$25<=G10),1,0)) -> 0 | I10: =180/A10 -> 10.588235 | J10: 0.479 | K10: 0.24328 | L10: =K10*TAN(PI()*I10/180) -> 0.045476914 | M10: =L10*SIN(PI()*(I10/2)/180) -> 0.0041960802 | N10: =M10*COS(PI()*(I10)/180) -> 0.004124634 | O10: =CÁLCULOS!$F$79 -> 2.3856884 | P10: =L10*K10 -> 0.011063624 | Q10: =(O10-(2*L10))*N10 -> 0.0094649402 | R10: =P10+Q10 -> 0.020528564 | S10: =$T$1 -> 0.03939 | T10: =IF($U$1="X",J10-R10-S10,J10-R10) -> 0.45847144 | U10: =(J10-T10)/J10*100 -> 4.2857127 | Y10: =IF(ENTRADAS!E15>10,1000,IF(AND(ENTRADAS!E15=10,X6>B49),1000,100)) -> 100 | AA10: =IF(AND(Z6="SC14",Z14="xiii"),1000,0) -> 0 | AB10: =IF(AND(A2="SC6",Z6="SC14"),1000,0) -> 0 | AC10: =AA10+AB10 -> 0
A11: 18 | B11: =(1.205/TAN(PI()/A11)-0.24)*2 -> 13.187789 | C11: =(1.205/TAN(PI()/A11)-0.295)*2 -> 13.077789 | D11: =((2.1+0.006-0.005)/2/TAN(PI()/A11)-0.07)*2 -> 11.775363 | E11: =IF(AND(ENTRADAS!$E$15>13,ENTRADAS!$E$15<=14),14,0) -> 0 | F11: =IF(E11>0,$C$5,0) -> 0 | G11: =IF(E11>0,$C$63,0) -> 0 | H11: =IF(E11=0,0,IF(AND(ENTRADAS!$G$25>=F11,ENTRADAS!$G$25<=G11),1,0)) -> 0 | I11: =180/A11 -> 10 | J11: 0.479 | K11: 0.24328 | L11: =K11*TAN(PI()*I11/180) -> 0.042896828 | M11: =L11*SIN(PI()*(I11/2)/180) -> 0.0037387049 | N11: =M11*COS(PI()*(I11)/180) -> 0.0036819056 | O11: =CÁLCULOS!$F$79 -> 2.3856884 | P11: =L11*K11 -> 0.01043594 | Q11: =(O11-(2*L11))*N11 -> 0.0084679953 | R11: =P11+Q11 -> 0.018903936 | S11: =$T$1 -> 0.03939 | T11: =IF($U$1="X",J11-R11-S11,J11-R11) -> 0.46009606 | U11: =(J11-T11)/J11*100 -> 3.9465419 | X11: soma= | Y11: =SUM(Y6:Y10) -> 500
A12: 19 | B12: =(1.205/TAN(PI()/A12)-0.24)*2 -> 13.962338 | C12: =(1.205/TAN(PI()/A12)-0.295)*2 -> 13.852338 | D12: =((2.1+0.006-0.005)/2/TAN(PI()/A12)-0.07)*2 -> 12.450603 | E12: =IF(AND(ENTRADAS!$E$15>13,ENTRADAS!$E$15<=14),14,0) -> 0 | F12: =IF(E12>0,$C$5,0) -> 0 | G12: =IF(E12>0,$C$63,0) -> 0 | H12: =IF(E12=0,0,IF(AND(ENTRADAS!$G$25>=F12,ENTRADAS!$G$25<=G12),1,0)) -> 0 | I12: =180/A12 -> 9.4736842 | J12: 0.479 | K12: 0.24328 | L12: =K12*TAN(PI()*I12/180) -> 0.040596252 | M12: =L12*SIN(PI()*(I12/2)/180) -> 0.0033524119 | N12: =M12*COS(PI()*(I12)/180) -> 0.0033066894 | O12: =CÁLCULOS!$F$79 -> 2.3856884 | P12: =L12*K12 -> 0.0098762562 | Q12: =(O12-(2*L12))*N12 -> 0.0076202521 | R12: =P12+Q12 -> 0.017496508 | S12: =$T$1 -> 0.03939 | T12: =IF($U$1="X",J12-R12-S12,J12-R12) -> 0.46150349 | U12: =(J12-T12)/J12*100 -> 3.6527157 | AB12: =IF(AC9=1000,"SC10",0) -> 0
A13: 20 | B13: =(1.205/TAN(PI()/A13)-0.24)*2 -> 14.736141 | C13: =(1.205/TAN(PI()/A13)-0.295)*2 -> 14.626141 | D13: =((2.1+0.006-0.005)/2/TAN(PI()/A13)-0.07)*2 -> 13.125192 | E13: =IF(AND(ENTRADAS!$E$15>13,ENTRADAS!$E$15<=14),14,0) -> 0 | F13: =IF(E13>0,$C$5,0) -> 0 | G13: =IF(E13>0,$C$63,0) -> 0 | H13: =IF(E13=0,0,IF(AND(ENTRADAS!$G$25>=F13,ENTRADAS!$G$25<=G13),1,0)) -> 0 | I13: =180/A13 -> 9 | J13: 0.479 | K13: 0.24328 | L13: =K13*TAN(PI()*I13/180) -> 0.038531767 | M13: =L13*SIN(PI()*(I13/2)/180) -> 0.0030231676 | N13: =M13*COS(PI()*(I13)/180) -> 0.0029859474 | O13: =CÁLCULOS!$F$79 -> 2.3856884 | P13: =L13*K13 -> 0.0093740082 | Q13: =(O13-(2*L13))*N13 -> 0.0068934323 | R13: =P13+Q13 -> 0.016267441 | S13: =$T$1 -> 0.03939 | T13: =IF($U$1="X",J13-R13-S13,J13-R13) -> 0.46273256 | U13: =(J13-T13)/J13*100 -> 3.3961254 | W13: nº painéis | X13: diâmetro | Y13: lógica | Z13: tipo sistema | AB13: =IF(ENTRADAS!E15>10,0,IF(ENTRADAS!Q35=110,"SC14",IF(AC10=2000,"SC14",0))) -> 0 | AC13: =IF(AND(Z6="SC14",A2="SC10"),"SC14",0) -> 0
A14: 21 | B14: =(1.205/TAN(PI()/A14)-0.24)*2 -> 15.509305 | C14: =(1.205/TAN(PI()/A14)-0.295)*2 -> 15.399305 | D14: =((2.1+0.006-0.005)/2/TAN(PI()/A14)-0.07)*2 -> 13.799224 | E14: =IF(AND(ENTRADAS!$E$15>13,ENTRADAS!$E$15<=14),14,0) -> 0 | F14: =IF(E14>0,$C$5,0) -> 0 | G14: =IF(E14>0,$C$63,0) -> 0 | H14: =IF(E14=0,0,IF(AND(ENTRADAS!$G$25>=F14,ENTRADAS!$G$25<=G14),1,0)) -> 0 | I14: =180/A14 -> 8.5714286 | J14: 0.479 | K14: 0.24328 | L14: =K14*TAN(PI()*I14/180) -> 0.03666856 | M14: =L14*SIN(PI()*(I14/2)/180) -> 0.0027402449 | N14: =M14*COS(PI()*(I14)/180) -> 0.0027096387 | O14: =CÁLCULOS!$F$79 -> 2.3856884 | P14: =L14*K14 -> 0.0089207273 | Q14: =(O14-(2*L14))*N14 -> 0.0062656364 | R14: =P14+Q14 -> 0.015186364 | S14: =$T$1 -> 0.03939 | T14: =IF($U$1="X",J14-R14-S14,J14-R14) -> 0.46381364 | U14: =(J14-T14)/J14*100 -> 3.1704308 | W14: =IF(ENTRADAS!D37="X",'TABELA SC-10 e 14'!D2,IF(ENTRADAS!D41="X",'TABELA SC-10 e 14'!I2,IF(ENTRADAS!D45="X",'TABELA SC-10 e 14'!J2,0))) -> 62 | X14: =IF(W14=0,0,VLOOKUP(W14,$A$5:$D$126,4,0)) -> 0 | Y14: =IF(X14=0,0,IF(AND(ENTRADAS!E15<=6,X14<=D33),1000,100)) -> 0 | Z14: =IF(A2="SC6","SC6",IF(Y14=1000,"SC6","xiii")) -> xiii
A15: 22 | B15: =(1.205/TAN(PI()/A15)-0.24)*2 -> 16.281918 | C15: =(1.205/TAN(PI()/A15)-0.295)*2 -> 16.171918 | D15: =((2.1+0.006-0.005)/2/TAN(PI()/A15)-0.07)*2 -> 14.472776 | E15: =IF(AND(ENTRADAS!$E$15>13,ENTRADAS!$E$15<=14),14,0) -> 0 | F15: =IF(E15>0,$C$5,0) -> 0 | G15: =IF(E15>0,$C$63,0) -> 0 | H15: =IF(E15=0,0,IF(AND(ENTRADAS!$G$25>=F15,ENTRADAS!$G$25<=G15),1,0)) -> 0 | I15: =180/A15 -> 8.1818182 | J15: 0.479 | K15: 0.24328 | L15: =K15*TAN(PI()*I15/180) -> 0.034978383 | M15: =L15*SIN(PI()*(I15/2)/180) -> 0.0024953293 | N15: =M15*COS(PI()*(I15)/180) -> 0.0024699304 | O15: =CÁLCULOS!$F$79 -> 2.3856884 | P15: =L15*K15 -> 0.0085095411 | Q15: =(O15-(2*L15))*N15 -> 0.0057196961 | R15: =P15+Q15 -> 0.014229237 | S15: =$T$1 -> 0.03939 | T15: =IF($U$1="X",J15-R15-S15,J15-R15) -> 0.46477076 | U15: =(J15-T15)/J15*100 -> 2.9706132 | Y15: antigo | Z15: =IF(Y14=1000,"SC6","xiii") -> xiii
A16: 23 | B16: =(1.205/TAN(PI()/A16)-0.24)*2 -> 17.054052 | C16: =(1.205/TAN(PI()/A16)-0.295)*2 -> 16.944052 | D16: =((2.1+0.006-0.005)/2/TAN(PI()/A16)-0.07)*2 -> 15.14591 | E16: =IF(AND(ENTRADAS!$E$15>13,ENTRADAS!$E$15<=14),14,0) -> 0 | F16: =IF(E16>0,$C$5,0) -> 0 | G16: =IF(E16>0,$C$63,0) -> 0 | H16: =IF(E16=0,0,IF(AND(ENTRADAS!$G$25>=F16,ENTRADAS!$G$25<=G16),1,0)) -> 0 | I16: =180/A16 -> 7.826087 | J16: 0.479 | K16: 0.24328 | L16: =K16*TAN(PI()*I16/180) -> 0.033438066 | M16: =L16*SIN(PI()*(I16/2)/180) -> 0.0022818943 | N16: =M16*COS(PI()*(I16)/180) -> 0.0022606407 | O16: =CÁLCULOS!$F$79 -> 2.3856884 | P16: =L16*K16 -> 0.0081348128 | Q16: =(O16-(2*L16))*N16 -> 0.0052420013 | R16: =P16+Q16 -> 0.013376814 | S16: =$T$1 -> 0.03939 | T16: =IF($U$1="X",J16-R16-S16,J16-R16) -> 0.46562319 | U16: =(J16-T16)/J16*100 -> 2.7926543
A17: 24 | B17: =(1.205/TAN(PI()/A17)-0.24)*2 -> 17.825767 | C17: =(1.205/TAN(PI()/A17)-0.295)*2 -> 17.715767 | D17: =((2.1+0.006-0.005)/2/TAN(PI()/A17)-0.07)*2 -> 15.818679 | E17: =IF(AND(ENTRADAS!$E$15>13,ENTRADAS!$E$15<=14),14,0) -> 0 | F17: =IF(E17>0,$C$5,0) -> 0 | G17: =IF(E17>0,$C$63,0) -> 0 | H17: =IF(E17=0,0,IF(AND(ENTRADAS!$G$25>=F17,ENTRADAS!$G$25<=G17),1,0)) -> 0 | I17: =180/A17 -> 7.5 | J17: 0.479 | K17: 0.24328 | L17: =K17*TAN(PI()*I17/180) -> 0.03202842 | M17: =L17*SIN(PI()*(I17/2)/180) -> 0.0020947589 | N17: =M17*COS(PI()*(I17)/180) -> 0.0020768379 | O17: =CÁLCULOS!$F$79 -> 2.3856884 | P17: =L17*K17 -> 0.0077918739 | Q17: =(O17-(2*L17))*N17 -> 0.0048216524 | R17: =P17+Q17 -> 0.012613526 | S17: =$T$1 -> 0.03939 | T17: =IF($U$1="X",J17-R17-S17,J17-R17) -> 0.46638647 | U17: =(J17-T17)/J17*100 -> 2.633304
A18: 25 | B18: =(1.205/TAN(PI()/A18)-0.24)*2 -> 18.597114 | C18: =(1.205/TAN(PI()/A18)-0.295)*2 -> 18.487114 | D18: =((2.1+0.006-0.005)/2/TAN(PI()/A18)-0.07)*2 -> 16.491128 | E18: =IF(AND(ENTRADAS!$E$15>13,ENTRADAS!$E$15<=14),14,0) -> 0 | F18: =IF(E18>0,$C$5,0) -> 0 | G18: =IF(E18>0,$C$63,0) -> 0 | H18: =IF(E18=0,0,IF(AND(ENTRADAS!$G$25>=F18,ENTRADAS!$G$25<=G18),1,0)) -> 0 | I18: =180/A18 -> 7.2 | J18: 0.479 | K18: 0.24328 | L18: =K18*TAN(PI()*I18/180) -> 0.030733411 | M18: =L18*SIN(PI()*(I18/2)/180) -> 0.0019297669 | N18: =M18*COS(PI()*(I18)/180) -> 0.0019145501 | O18: =CÁLCULOS!$F$79 -> 2.3856884 | P18: =L18*K18 -> 0.0074768243 | Q18: =(O18-(2*L18))*N18 -> 0.0044498386 | R18: =P18+Q18 -> 0.011926663 | S18: =$T$1 -> 0.03939 | T18: =IF($U$1="X",J18-R18-S18,J18-R18) -> 0.46707334 | U18: =(J18-T18)/J18*100 -> 2.4899087
A19: 26 | B19: =(1.205/TAN(PI()/A19)-0.24)*2 -> 19.368136 | C19: =(1.205/TAN(PI()/A19)-0.295)*2 -> 19.258136 | D19: =((2.1+0.006-0.005)/2/TAN(PI()/A19)-0.07)*2 -> 17.163292 | E19: =IF(AND(ENTRADAS!$E$15>13,ENTRADAS!$E$15<=14),14,0) -> 0 | F19: =IF(E19>0,$C$5,0) -> 0 | G19: =IF(E19>0,$C$63,0) -> 0 | H19: =IF(E19=0,0,IF(AND(ENTRADAS!$G$25>=F19,ENTRADAS!$G$25<=G19),1,0)) -> 0 | I19: =180/A19 -> 6.9230769 | J19: 0.479 | K19: 0.24328 | L19: =K19*TAN(PI()*I19/180) -> 0.02953954 | M19: =L19*SIN(PI()*(I19/2)/180) -> 0.001783553 | N19: =M19*COS(PI()*(I19)/180) -> 0.0017705489 | O19: =CÁLCULOS!$F$79 -> 2.3856884 | P19: =L19*K19 -> 0.0071863793 | Q19: =(O19-(2*L19))*N19 -> 0.0041193757 | R19: =P19+Q19 -> 0.011305755 | S19: =$T$1 -> 0.03939 | T19: =IF($U$1="X",J19-R19-S19,J19-R19) -> 0.46769425 | U19: =(J19-T19)/J19*100 -> 2.3602829
A20: 27 | B20: =(1.205/TAN(PI()/A20)-0.24)*2 -> 20.138868 | C20: =(1.205/TAN(PI()/A20)-0.295)*2 -> 20.028868 | D20: =((2.1+0.006-0.005)/2/TAN(PI()/A20)-0.07)*2 -> 17.835204 | E20: =IF(AND(ENTRADAS!$E$15>13,ENTRADAS!$E$15<=14),14,0) -> 0 | F20: =IF(E20>0,$C$5,0) -> 0 | G20: =IF(E20>0,$C$63,0) -> 0 | H20: =IF(E20=0,0,IF(AND(ENTRADAS!$G$25>=F20,ENTRADAS!$G$25<=G20),1,0)) -> 0 | I20: =180/A20 -> 6.6666667 | J20: 0.479 | K20: 0.24328 | L20: =K20*TAN(PI()*I20/180) -> 0.028435354 | M20: =L20*SIN(PI()*(I20/2)/180) -> 0.0016533688 | N20: =M20*COS(PI()*(I20)/180) -> 0.0016421893 | O20: =CÁLCULOS!$F$79 -> 2.3856884 | P20: =L20*K20 -> 0.0069177529 | Q20: =(O20-(2*L20))*N20 -> 0.0038243595 | R20: =P20+Q20 -> 0.010742112 | S20: =$T$1 -> 0.03939 | T20: =IF($U$1="X",J20-R20-S20,J20-R20) -> 0.46825789 | U20: =(J20-T20)/J20*100 -> 2.2426122
A21: 28 | B21: =(1.205/TAN(PI()/A21)-0.24)*2 -> 20.909342 | C21: =(1.205/TAN(PI()/A21)-0.295)*2 -> 20.799342 | D21: =((2.1+0.006-0.005)/2/TAN(PI()/A21)-0.07)*2 -> 18.506891 | E21: =IF(AND(ENTRADAS!$E$15>13,ENTRADAS!$E$15<=14),14,0) -> 0 | F21: =IF(E21>0,$C$5,0) -> 0 | G21: =IF(E21>0,$C$63,0) -> 0 | H21: =IF(E21=0,0,IF(AND(ENTRADAS!$G$25>=F21,ENTRADAS!$G$25<=G21),1,0)) -> 0 | I21: =180/A21 -> 6.4285714 | J21: 0.479 | K21: 0.24328 | L21: =K21*TAN(PI()*I21/180) -> 0.027411073 | M21: =L21*SIN(PI()*(I21/2)/180) -> 0.0015369511 | N21: =M21*COS(PI()*(I21)/180) -> 0.0015272871 | O21: =CÁLCULOS!$F$79 -> 2.3856884 | P21: =L21*K21 -> 0.0066685658 | Q21: =(O21-(2*L21))*N21 -> 0.0035599019 | R21: =P21+Q21 -> 0.010228468 | S21: =$T$1 -> 0.03939 | T21: =IF($U$1="X",J21-R21-S21,J21-R21) -> 0.46877153 | U21: =(J21-T21)/J21*100 -> 2.1353795
A22: 29 | B22: =(1.205/TAN(PI()/A22)-0.24)*2 -> 21.679584 | C22: =(1.205/TAN(PI()/A22)-0.295)*2 -> 21.569584 | D22: =((2.1+0.006-0.005)/2/TAN(PI()/A22)-0.07)*2 -> 19.178376 | E22: =IF(AND(ENTRADAS!$E$15>13,ENTRADAS!$E$15<=14),14,0) -> 0 | F22: =IF(E22>0,$C$5,0) -> 0 | G22: =IF(E22>0,$C$63,0) -> 0 | H22: =IF(E22=0,0,IF(AND(ENTRADAS!$G$25>=F22,ENTRADAS!$G$25<=G22),1,0)) -> 0 | I22: =180/A22 -> 6.2068966 | J22: 0.479 | K22: 0.24328 | L22: =K22*TAN(PI()*I22/180) -> 0.026458294 | M22: =L22*SIN(PI()*(I22/2)/180) -> 0.0014324232 | N22: =M22*COS(PI()*(I22)/180) -> 0.0014240263 | O22: =CÁLCULOS!$F$79 -> 2.3856884 | P22: =L22*K22 -> 0.0064367739 | Q22: =(O22-(2*L22))*N22 -> 0.0033219283 | R22: =P22+Q22 -> 0.0097587022 | S22: =$T$1 -> 0.03939 | T22: =IF($U$1="X",J22-R22-S22,J22-R22) -> 0.4692413 | U22: =(J22-T22)/J22*100 -> 2.0373073
A23: 30 | B23: =(1.205/TAN(PI()/A23)-0.24)*2 -> 22.449618 | C23: =(1.205/TAN(PI()/A23)-0.295)*2 -> 22.339618 | D23: =((2.1+0.006-0.005)/2/TAN(PI()/A23)-0.07)*2 -> 19.84968 | E23: =IF(AND(ENTRADAS!$E$15>13,ENTRADAS!$E$15<=14),14,0) -> 0 | F23: =IF(E23>0,$C$5,0) -> 0 | G23: =IF(E23>0,$C$63,0) -> 0 | H23: =IF(E23=0,0,IF(AND(ENTRADAS!$G$25>=F23,ENTRADAS!$G$25<=G23),1,0)) -> 0 | I23: =180/A23 -> 6 | J23: 0.479 | K23: 0.24328 | L23: =K23*TAN(PI()*I23/180) -> 0.025569758 | M23: =L23*SIN(PI()*(I23/2)/180) -> 0.0013382178 | N23: =M23*COS(PI()*(I23)/180) -> 0.0013308869 | O23: =CÁLCULOS!$F$79 -> 2.3856884 | P23: =L23*K23 -> 0.0062206108 | Q23: =(O23-(2*L23))*N23 -> 0.0031070204 | R23: =P23+Q23 -> 0.0093276312 | S23: =$T$1 -> 0.03939 | T23: =IF($U$1="X",J23-R23-S23,J23-R23) -> 0.46967237 | U23: =(J23-T23)/J23*100 -> 1.9473134
A24: 31 | B24: =(1.205/TAN(PI()/A24)-0.24)*2 -> 23.219465 | C24: =(1.205/TAN(PI()/A24)-0.295)*2 -> 23.109465 | D24: =((2.1+0.006-0.005)/2/TAN(PI()/A24)-0.07)*2 -> 20.52082 | E24: =IF(AND(ENTRADAS!$E$15>13,ENTRADAS!$E$15<=14),14,0) -> 0 | F24: =IF(E24>0,$C$5,0) -> 0 | G24: =IF(E24>0,$C$63,0) -> 0 | H24: =IF(E24=0,0,IF(AND(ENTRADAS!$G$25>=F24,ENTRADAS!$G$25<=G24),1,0)) -> 0 | I24: =180/A24 -> 5.8064516 | J24: 0.479 | K24: 0.24328 | L24: =K24*TAN(PI()*I24/180) -> 0.024739158 | M24: =L24*SIN(PI()*(I24/2)/180) -> 0.0012530178 | N24: =M24*COS(PI()*(I24)/180) -> 0.001246589 | O24: =CÁLCULOS!$F$79 -> 2.3856884 | P24: =L24*K24 -> 0.0060185424 | Q24: =(O24-(2*L24))*N24 -> 0.0029122937 | R24: =P24+Q24 -> 0.0089308361 | S24: =$T$1 -> 0.03939 | T24: =IF($U$1="X",J24-R24-S24,J24-R24) -> 0.47006916 | U24: =(J24-T24)/J24*100 -> 1.8644752
A25: 32 | B25: =(1.205/TAN(PI()/A25)-0.24)*2 -> 23.989141 | C25: =(1.205/TAN(PI()/A25)-0.295)*2 -> 23.879141 | D25: =((2.1+0.006-0.005)/2/TAN(PI()/A25)-0.07)*2 -> 21.191811 | E25: =IF(AND(ENTRADAS!$E$15>13,ENTRADAS!$E$15<=14),14,0) -> 0 | F25: =IF(E25>0,$C$5,0) -> 0 | G25: =IF(E25>0,$C$63,0) -> 0 | H25: =IF(E25=0,0,IF(AND(ENTRADAS!$G$25>=F25,ENTRADAS!$G$25<=G25),1,0)) -> 0 | I25: =180/A25 -> 5.625 | J25: 0.479 | K25: 0.24328 | L25: =K25*TAN(PI()*I25/180) -> 0.023960989 | M25: =L25*SIN(PI()*(I25/2)/180) -> 0.00117571 | N25: =M25*COS(PI()*(I25)/180) -> 0.0011700486 | O25: =CÁLCULOS!$F$79 -> 2.3856884 | P25: =L25*K25 -> 0.0058292293 | Q25: =(O25-(2*L25))*N25 -> 0.0027353004 | R25: =P25+Q25 -> 0.0085645297 | S25: =$T$1 -> 0.03939 | T25: =IF($U$1="X",J25-R25-S25,J25-R25) -> 0.47043547 | U25: =(J25-T25)/J25*100 -> 1.788002
A26: 33 | B26: =(1.205/TAN(PI()/A26)-0.24)*2 -> 24.758662 | C26: =(1.205/TAN(PI()/A26)-0.295)*2 -> 24.648662 | D26: =((2.1+0.006-0.005)/2/TAN(PI()/A26)-0.07)*2 -> 21.862667 | E26: =IF(AND(ENTRADAS!$E$15>13,ENTRADAS!$E$15<=14),14,0) -> 0 | F26: =IF(E26>0,$C$5,0) -> 0 | G26: =IF(E26>0,$C$63,0) -> 0 | H26: =IF(E26=0,0,IF(AND(ENTRADAS!$G$25>=F26,ENTRADAS!$G$25<=G26),1,0)) -> 0 | I26: =180/A26 -> 5.4545455 | J26: 0.479 | K26: 0.24328 | L26: =K26*TAN(PI()*I26/180) -> 0.023230423 | M26: =L26*SIN(PI()*(I26/2)/180) -> 0.001105348 | N26: =M26*COS(PI()*(I26)/180) -> 0.0011003429 | O26: =CÁLCULOS!$F$79 -> 2.3856884 | P26: =L26*K26 -> 0.0056514974 | Q26: =(O26-(2*L26))*N26 -> 0.0025739525 | R26: =P26+Q26 -> 0.0082254499 | S26: =$T$1 -> 0.03939 | T26: =IF($U$1="X",J26-R26-S26,J26-R26) -> 0.47077455 | U26: =(J26-T26)/J26*100 -> 1.7172129
A27: 34 | B27: =(1.205/TAN(PI()/A27)-0.24)*2 -> 25.528042 | C27: =(1.205/TAN(PI()/A27)-0.295)*2 -> 25.418042 | D27: =((2.1+0.006-0.005)/2/TAN(PI()/A27)-0.07)*2 -> 22.533401 | E27: =IF(AND(ENTRADAS!$E$15>13,ENTRADAS!$E$15<=14),14,0) -> 0 | F27: =IF(E27>0,$C$5,0) -> 0 | G27: =IF(E27>0,$C$63,0) -> 0 | H27: =IF(E27=0,0,IF(AND(ENTRADAS!$G$25>=F27,ENTRADAS!$G$25<=G27),1,0)) -> 0 | I27: =180/A27 -> 5.2941176 | J27: 0.479 | K27: 0.24328 | L27: =K27*TAN(PI()*I27/180) -> 0.022543212 | M27: =L27*SIN(PI()*(I27/2)/180) -> 0.0010411235 | N27: =M27*COS(PI()*(I27)/180) -> 0.0010366822 | O27: =CÁLCULOS!$F$79 -> 2.3856884 | P27: =L27*K27 -> 0.0054843126 | Q27: =(O27-(2*L27))*N27 -> 0.0024264605 | R27: =P27+Q27 -> 0.0079107731 | S27: =$T$1 -> 0.03939 | T27: =IF($U$1="X",J27-R27-S27,J27-R27) -> 0.47108923 | U27: =(J27-T27)/J27*100 -> 1.6515184
... A33: 40 | B33: =(1.205/TAN(PI()/A33)-0.24)*2 -> 30.141953 | C33: =(1.205/TAN(PI()/A33)-0.295)*2 -> 30.031953 | D33: =((2.1+0.006-0.005)/2/TAN(PI()/A33)-0.07)*2 -> 26.555736 | E33: =IF(AND(ENTRADAS!$E$15>13,ENTRADAS!$E$15<=14),14,0) -> 0 | F33: =IF(E33>0,$C$5,0) -> 0 | G33: =IF(E33>0,$C$63,0) -> 0 | H33: =IF(E33=0,0,IF(AND(ENTRADAS!$G$25>=F33,ENTRADAS!$G$25<=G33),1,0)) -> 0 | I33: =180/A33 -> 4.5 | J33: 0.479 | K33: 0.24328 | L33: =K33*TAN(PI()*I33/180) -> 0.019146551 | M33: =L33*SIN(PI()*(I33/2)/180) -> 0.00075169007 | N33: =M33*COS(PI()*(I33)/180) -> 0.00074937286 | O33: =CÁLCULOS!$F$79 -> 2.3856884 | P33: =L33*K33 -> 0.004657973 | Q33: =(O33-(2*L33))*N33 -> 0.0017590743 | R33: =P33+Q33 -> 0.0064170473 | S33: =$T$1 -> 0.03939 | T33: =IF($U$1="X",J33-R33-S33,J33-R33) -> 0.47258295 | U33: =(J33-T33)/J33*100 -> 1.3396759
A34: 41 | B34: =(1.205/TAN(PI()/A34)-0.24)*2 -> 30.910621 | C34: =(1.205/TAN(PI()/A34)-0.295)*2 -> 30.800621 | E34: =IF(AND(ENTRADAS!$E$15>13,ENTRADAS!$E$15<=14),14,0) -> 0 | F34: =IF(E34>0,$C$5,0) -> 0 | G34: =IF(E34>0,$C$63,0) -> 0 | H34: =IF(E34=0,0,IF(AND(ENTRADAS!$G$25>=F34,ENTRADAS!$G$25<=G34),1,0)) -> 0 | I34: =180/A34 -> 4.3902439 | J34: 0.479 | K34: 0.24328 | L34: =K34*TAN(PI()*I34/180) -> 0.018677706 | M34: =L34*SIN(PI()*(I34/2)/180) -> 0.00071540721 | N34: =M34*COS(PI()*(I34)/180) -> 0.00071330806 | O34: =CÁLCULOS!$F$79 -> 2.3856884 | P34: =L34*K34 -> 0.0045439124 | Q34: =(O34-(2*L34))*N34 -> 0.0016750849 | R34: =P34+Q34 -> 0.0062189973 | S34: =$T$1 -> 0.03939 | T34: =IF($U$1="X",J34-R34-S34,J34-R34) -> 0.472781 | U34: =(J34-T34)/J34*100 -> 1.2983293
A35: 42 | B35: =(1.205/TAN(PI()/A35)-0.24)*2 -> 31.679215 | C35: =(1.205/TAN(PI()/A35)-0.295)*2 -> 31.569215 | E35: =IF(AND(ENTRADAS!$E$15>13,ENTRADAS!$E$15<=14),14,0) -> 0 | F35: =IF(E35>0,$C$5,0) -> 0 | G35: =IF(E35>0,$C$63,0) -> 0 | H35: =IF(E35=0,0,IF(AND(ENTRADAS!$G$25>=F35,ENTRADAS!$G$25<=G35),1,0)) -> 0 | I35: =180/A35 -> 4.2857143 | J35: 0.479 | K35: 0.24328 | L35: =K35*TAN(PI()*I35/180) -> 0.018231316 | M35: =L35*SIN(PI()*(I35/2)/180) -> 0.00068169066 | N35: =M35*COS(PI()*(I35)/180) -> 0.00067978452 | O35: =CÁLCULOS!$F$79 -> 2.3856884 | P35: =L35*K35 -> 0.0044353145 | Q35: =(O35-(2*L35))*N35 -> 0.0015969673 | R35: =P35+Q35 -> 0.0060322818 | S35: =$T$1 -> 0.03939 | T35: =IF($U$1="X",J35-R35-S35,J35-R35) -> 0.47296772 | U35: =(J35-T35)/J35*100 -> 1.259349
A36: 43 | B36: =(1.205/TAN(PI()/A36)-0.24)*2 -> 32.447741 | C36: =(1.205/TAN(PI()/A36)-0.295)*2 -> 32.337741 | E36: =IF(AND(ENTRADAS!$E$15>13,ENTRADAS!$E$15<=14),14,0) -> 0 | F36: =IF(E36>0,$C$5,0) -> 0 | G36: =IF(E36>0,$C$63,0) -> 0 | H36: =IF(E36=0,0,IF(AND(ENTRADAS!$G$25>=F36,ENTRADAS!$G$25<=G36),1,0)) -> 0 | I36: =180/A36 -> 4.1860465 | J36: 0.479 | K36: 0.24328 | L36: =K36*TAN(PI()*I36/180) -> 0.017805801 | M36: =L36*SIN(PI()*(I36/2)/180) -> 0.00065030387 | N36: =M36*COS(PI()*(I36)/180) -> 0.00064856905 | O36: =CÁLCULOS!$F$79 -> 2.3856884 | P36: =L36*K36 -> 0.0043317953 | Q36: =(O36-(2*L36))*N36 -> 0.0015241871 | R36: =P36+Q36 -> 0.0058559823 | S36: =$T$1 -> 0.03939 | T36: =IF($U$1="X",J36-R36-S36,J36-R36) -> 0.47314402 | U36: =(J36-T36)/J36*100 -> 1.2225433
A37: 44 | B37: =(1.205/TAN(PI()/A37)-0.24)*2 -> 33.216203 | C37: =(1.205/TAN(PI()/A37)-0.295)*2 -> 33.106203 | E37: =IF(AND(ENTRADAS!$E$15>13,ENTRADAS!$E$15<=14),14,0) -> 0 | F37: =IF(E37>0,$C$5,0) -> 0 | G37: =IF(E37>0,$C$63,0) -> 0 | H37: =IF(E37=0,0,IF(AND(ENTRADAS!$G$25>=F37,ENTRADAS!$G$25<=G37),1,0)) -> 0 | I37: =180/A37 -> 4.0909091 | J37: 0.479 | K37: 0.24328 | L37: =K37*TAN(PI()*I37/180) -> 0.017399729 | M37: =L37*SIN(PI()*(I37/2)/180) -> 0.00062103694 | N37: =M37*COS(PI()*(I37)/180) -> 0.00061945461 | O37: =CÁLCULOS!$F$79 -> 2.3856884 | P37: =L37*K37 -> 0.0042330061 | Q37: =(O37-(2*L37))*N37 -> 0.001456269 | R37: =P37+Q37 -> 0.0056892751 | S37: =$T$1 -> 0.03939 | T37: =IF($U$1="X",J37-R37-S37,J37-R37) -> 0.47331072 | U37: =(J37-T37)/J37*100 -> 1.1877401
A38: 45 | B38: =(1.205/TAN(PI()/A38)-0.24)*2 -> 33.984606 | C38: =(1.205/TAN(PI()/A38)-0.295)*2 -> 33.874606 | E38: =IF(AND(ENTRADAS!$E$15>13,ENTRADAS!$E$15<=14),14,0) -> 0 | F38: =IF(E38>0,$C$5,0) -> 0 | G38: =IF(E38>0,$C$63,0) -> 0 | H38: =IF(E38=0,0,IF(AND(ENTRADAS!$G$25>=F38,ENTRADAS!$G$25<=G38),1,0)) -> 0 | I38: =180/A38 -> 4 | J38: 0.479 | K38: 0.24328 | L38: =K38*TAN(PI()*I38/180) -> 0.017011795 | M38: =L38*SIN(PI()*(I38/2)/180) -> 0.00059370308 | N38: =M38*COS(PI()*(I38)/180) -> 0.00059225685 | O38: =CÁLCULOS!$F$79 -> 2.3856884 | P38: =L38*K38 -> 0.0041386294 | Q38: =(O38-(2*L38))*N38 -> 0.0013927896 | R38: =P38+Q38 -> 0.005531419 | S38: =$T$1 -> 0.03939 | T38: =IF($U$1="X",J38-R38-S38,J38-R38) -> 0.47346858 | U38: =(J38-T38)/J38*100 -> 1.1547848
A39: 46 | B39: =(1.205/TAN(PI()/A39)-0.24)*2 -> 34.752953 | C39: =(1.205/TAN(PI()/A39)-0.295)*2 -> 34.642953 | E39: =IF(AND(ENTRADAS!$E$15>13,ENTRADAS!$E$15<=14),14,0) -> 0 | F39: =IF(E39>0,$C$5,0) -> 0 | G39: =IF(E39>0,$C$63,0) -> 0 | H39: =IF(E39=0,0,IF(AND(ENTRADAS!$G$25>=F39,ENTRADAS!$G$25<=G39),1,0)) -> 0 | I39: =180/A39 -> 3.9130435 | J39: 0.479 | K39: 0.24328 | L39: =K39*TAN(PI()*I39/180) -> 0.016640808 | M39: =L39*SIN(PI()*(I39/2)/180) -> 0.00056813566 | N39: =M39*COS(PI()*(I39)/180) -> 0.0005668112 | O39: =CÁLCULOS!$F$79 -> 2.3856884 | P39: =L39*K39 -> 0.0040483757 | Q39: =(O39-(2*L39))*N39 -> 0.0013333705 | R39: =P39+Q39 -> 0.0053817463 | S39: =$T$1 -> 0.03939 | T39: =IF($U$1="X",J39-R39-S39,J39-R39) -> 0.47361825 | U39: =(J39-T39)/J39*100 -> 1.1235378
A40: 47 | B40: =(1.205/TAN(PI()/A40)-0.24)*2 -> 35.521248 | C40: =(1.205/TAN(PI()/A40)-0.295)*2 -> 35.411248 | E40: =IF(AND(ENTRADAS!$E$15>13,ENTRADAS!$E$15<=14),14,0) -> 0 | F40: =IF(E40>0,$C$5,0) -> 0 | G40: =IF(E40>0,$C$63,0) -> 0 | H40: =IF(E40=0,0,IF(AND(ENTRADAS!$G$25>=F40,ENTRADAS!$G$25<=G40),1,0)) -> 0 | I40: =180/A40 -> 3.8297872 | J40: 0.479 | K40: 0.24328 | L40: =K40*TAN(PI()*I40/180) -> 0.01628568 | M40: =L40*SIN(PI()*(I40/2)/180) -> 0.00054418562 | N40: =M40*COS(PI()*(I40)/180) -> 0.00054297038 | O40: =CÁLCULOS!$F$79 -> 2.3856884 | P40: =L40*K40 -> 0.0039619802 | Q40: =(O40-(2*L40))*N40 -> 0.0012776729 | R40: =P40+Q40 -> 0.0052396531 | S40: =$T$1 -> 0.03939 | T40: =IF($U$1="X",J40-R40-S40,J40-R40) -> 0.47376035 | U40: =(J40-T40)/J40*100 -> 1.0938733
A41: 48 | B41: =(1.205/TAN(PI()/A41)-0.24)*2 -> 36.289495 | C41: =(1.205/TAN(PI()/A41)-0.295)*2 -> 36.179495 | E41: =IF(AND(ENTRADAS!$E$15>13,ENTRADAS!$E$15<=14),14,0) -> 0 | F41: =IF(E41>0,$C$5,0) -> 0 | G41: =IF(E41>0,$C$63,0) -> 0 | H41: =IF(E41=0,0,IF(AND(ENTRADAS!$G$25>=F41,ENTRADAS!$G$25<=G41),1,0)) -> 0 | I41: =180/A41 -> 3.75 | J41: 0.479 | K41: 0.24328 | L41: =K41*TAN(PI()*I41/180) -> 0.015945414 | M41: =L41*SIN(PI()*(I41/2)/180) -> 0.00052171931 | N41: =M41*COS(PI()*(I41)/180) -> 0.00052060227 | O41: =CÁLCULOS!$F$79 -> 2.3856884 | P41: =L41*K41 -> 0.0038792002 | Q41: =(O41-(2*L41))*N41 -> 0.0012253924 | R41: =P41+Q41 -> 0.0051045926 | S41: =$T$1 -> 0.03939 | T41: =IF($U$1="X",J41-R41-S41,J41-R41) -> 0.47389541 | U41: =(J41-T41)/J41*100 -> 1.0656769
A42: 49 | B42: =(1.205/TAN(PI()/A42)-0.24)*2 -> 37.057695 | C42: =(1.205/TAN(PI()/A42)-0.295)*2 -> 36.947695 | E42: =IF(AND(ENTRADAS!$E$15>13,ENTRADAS!$E$15<=14),14,0) -> 0 | F42: =IF(E42>0,$C$5,0) -> 0 | G42: =IF(E42>0,$C$63,0) -> 0 | H42: =IF(E42=0,0,IF(AND(ENTRADAS!$G$25>=F42,ENTRADAS!$G$25<=G42),1,0)) -> 0 | I42: =180/A42 -> 3.6734694 | J42: 0.479 | K42: 0.24328 | L42: =K42*TAN(PI()*I42/180) -> 0.015619094 | M42: =L42*SIN(PI()*(I42/2)/180) -> 0.00050061661 | N42: =M42*COS(PI()*(I42)/180) -> 0.00049958804 | O42: =CÁLCULOS!$F$79 -> 2.3856884 | P42: =L42*K42 -> 0.0037998132 | Q42: =(O42-(2*L42))*N42 -> 0.0011762552 | R42: =P42+Q42 -> 0.0049760684 | S42: =$T$1 -> 0.03939 | T42: =IF($U$1="X",J42-R42-S42,J42-R42) -> 0.47402393 | U42: =(J42-T42)/J42*100 -> 1.0388452
A43: 50 | B43: =(1.205/TAN(PI()/A43)-0.24)*2 -> 37.825853 | C43: =(1.205/TAN(PI()/A43)-0.295)*2 -> 37.715853 | E43: =IF(AND(ENTRADAS!$E$15>13,ENTRADAS!$E$15<=14),14,0) -> 0 | F43: =IF(E43>0,$C$5,0) -> 0 | G43: =IF(E43>0,$C$63,0) -> 0 | H43: =IF(E43=0,0,IF(AND(ENTRADAS!$G$25>=F43,ENTRADAS!$G$25<=G43),1,0)) -> 0 | I43: =180/A43 -> 3.6 | J43: 0.479 | K43: 0.24328 | L43: =K43*TAN(PI()*I43/180) -> 0.01530588 | M43: =L43*SIN(PI()*(I43/2)/180) -> 0.00048076932 | N43: =M43*COS(PI()*(I43)/180) -> 0.00047982063 | O43: =CÁLCULOS!$F$79 -> 2.3856884 | P43: =L43*K43 -> 0.0037236145 | Q43: =(O43-(2*L43))*N43 -> 0.0011300144 | R43: =P43+Q43 -> 0.0048536289 | S43: =$T$1 -> 0.03939 | T43: =IF($U$1="X",J43-R43-S43,J43-R43) -> 0.47414637 | U43: =(J43-T43)/J43*100 -> 1.0132837
A44: 51 | B44: =(1.205/TAN(PI()/A44)-0.24)*2 -> 38.59397 | C44: =(1.205/TAN(PI()/A44)-0.295)*2 -> 38.48397 | E44: =IF(AND(ENTRADAS!$E$15>13,ENTRADAS!$E$15<=14),14,0) -> 0 | F44: =IF(E44>0,$C$5,0) -> 0 | G44: =IF(E44>0,$C$63,0) -> 0 | H44: =IF(E44=0,0,IF(AND(ENTRADAS!$G$25>=F44,ENTRADAS!$G$25<=G44),1,0)) -> 0 | I44: =180/A44 -> 3.5294118 | J44: 0.479 | K44: 0.24328 | L44: =K44*TAN(PI()*I44/180) -> 0.015004997 | M44: =L44*SIN(PI()*(I44/2)/180) -> 0.00046207975 | N44: =M44*COS(PI()*(I44)/180) -> 0.00046120334 | O44: =CÁLCULOS!$F$79 -> 2.3856884 | P44: =L44*K44 -> 0.0036504156 | Q44: =(O44-(2*L44))*N44 -> 0.0010864468 | R44: =P44+Q44 -> 0.0047368624 | S44: =$T$1 -> 0.03939 | T44: =IF($U$1="X",J44-R44-S44,J44-R44) -> 0.47426314 | U44: =(J44-T44)/J44*100 -> 0.98890655 | X44: 87 | Y44: 8
A45: 52 | B45: =(1.205/TAN(PI()/A45)-0.24)*2 -> 39.36205 | C45: =(1.205/TAN(PI()/A45)-0.295)*2 -> 39.25205 | E45: =IF(AND(ENTRADAS!$E$15>13,ENTRADAS!$E$15<=14),14,0) -> 0 | F45: =IF(E45>0,$C$5,0) -> 0 | G45: =IF(E45>0,$C$63,0) -> 0 | H45: =IF(E45=0,0,IF(AND(ENTRADAS!$G$25>=F45,ENTRADAS!$G$25<=G45),1,0)) -> 0 | I45: =180/A45 -> 3.4615385 | J45: 0.479 | K45: 0.24328 | L45: =K45*TAN(PI()*I45/180) -> 0.014715729 | M45: =L45*SIN(PI()*(I45/2)/180) -> 0.00044445957 | N45: =M45*COS(PI()*(I45)/180) -> 0.00044364868 | O45: =CÁLCULOS!$F$79 -> 2.3856884 | P45: =L45*K45 -> 0.0035800425 | Q45: =(O45-(2*L45))*N45 -> 0.0010453503 | R45: =P45+Q45 -> 0.0046253928 | S45: =$T$1 -> 0.03939 | T45: =IF($U$1="X",J45-R45-S45,J45-R45) -> 0.47437461 | U45: =(J45-T45)/J45*100 -> 0.96563524 | X45: 88 | Y45: 8
A46: 53 | B46: =(1.205/TAN(PI()/A46)-0.24)*2 -> 40.130093 | C46: =(1.205/TAN(PI()/A46)-0.295)*2 -> 40.020093 | E46: =IF(AND(ENTRADAS!$E$15>13,ENTRADAS!$E$15<=14),14,0) -> 0 | F46: =IF(E46>0,$C$5,0) -> 0 | G46: =IF(E46>0,$C$63,0) -> 0 | H46: =IF(E46=0,0,IF(AND(ENTRADAS!$G$25>=F46,ENTRADAS!$G$25<=G46),1,0)) -> 0 | I46: =180/A46 -> 3.3962264 | J46: 0.479 | K46: 0.24328 | L46: =K46*TAN(PI()*I46/180) -> 0.014437416 | M46: =L46*SIN(PI()*(I46/2)/180) -> 0.00042782868 | N46: =M46*COS(PI()*(I46)/180) -> 0.0004270773 | O46: =CÁLCULOS!$F$79 -> 2.3856884 | P46: =L46*K46 -> 0.0035123345 | Q46: =(O46-(2*L46))*N46 -> 0.0010065416 | R46: =P46+Q46 -> 0.0045188761 | S46: =$T$1 -> 0.03939 | T46: =IF($U$1="X",J46-R46-S46,J46-R46) -> 0.47448112 | U46: =(J46-T46)/J46*100 -> 0.94339794 | X46: 89 | Y46: 8
A47: 54 | B47: =(1.205/TAN(PI()/A47)-0.24)*2 -> 40.898102 | C47: =(1.205/TAN(PI()/A47)-0.295)*2 -> 40.788102 | E47: =IF(AND(ENTRADAS!$E$15>13,ENTRADAS!$E$15<=14),14,0) -> 0 | F47: =IF(E47>0,$C$5,0) -> 0 | G47: =IF(E47>0,$C$63,0) -> 0 | H47: =IF(E47=0,0,IF(AND(ENTRADAS!$G$25>=F47,ENTRADAS!$G$25<=G47),1,0)) -> 0 | I47: =180/A47 -> 3.3333333 | J47: 0.479 | K47: 0.24328 | L47: =K47*TAN(PI()*I47/180) -> 0.014169446 | M47: =L47*SIN(PI()*(I47/2)/180) -> 0.00041211436 | N47: =M47*COS(PI()*(I47)/180) -> 0.00041141713 | O47: =CÁLCULOS!$F$79 -> 2.3856884 | P47: =L47*K47 -> 0.0034471429 | Q47: =(O47-(2*L47))*N47 -> 0.00096985397 | R47: =P47+Q47 -> 0.0044169969 | S47: =$T$1 -> 0.03939 | T47: =IF($U$1="X",J47-R47-S47,J47-R47) -> 0.474583 | U47: =(J47-T47)/J47*100 -> 0.92212879 | X47: 90 | Y47: 8
A48: 55 | B48: =(1.205/TAN(PI()/A48)-0.24)*2 -> 41.666079 | C48: =(1.205/TAN(PI()/A48)-0.295)*2 -> 41.556079 | E48: =IF(AND(ENTRADAS!$E$15>13,ENTRADAS!$E$15<=14),14,0) -> 0 | F48: =IF(E48>0,$C$5,0) -> 0 | G48: =IF(E48>0,$C$63,0) -> 0 | H48: =IF(E48=0,0,IF(AND(ENTRADAS!$G$25>=F48,ENTRADAS!$G$25<=G48),1,0)) -> 0 | I48: =180/A48 -> 3.2727273 | J48: 0.479 | K48: 0.24328 | L48: =K48*TAN(PI()*I48/180) -> 0.013911254 | M48: =L48*SIN(PI()*(I48/2)/180) -> 0.00039725047 | N48: =M48*COS(PI()*(I48)/180) -> 0.00039660259 | O48: =CÁLCULOS!$F$79 -> 2.3856884 | P48: =L48*K48 -> 0.0033843298 | Q48: =(O48-(2*L48))*N48 -> 0.00093513573 | R48: =P48+Q48 -> 0.0043194655 | S48: =$T$1 -> 0.03939 | T48: =IF($U$1="X",J48-R48-S48,J48-R48) -> 0.47468053 | U48: =(J48-T48)/J48*100 -> 0.90176733
A49: 56 | B49: =(1.205/TAN(PI()/A49)-0.24)*2 -> 42.434026 | C49: =(1.205/TAN(PI()/A49)-0.295)*2 -> 42.324026 | E49: =IF(AND(ENTRADAS!$E$15>13,ENTRADAS!$E$15<=14),14,0) -> 0 | F49: =IF(E49>0,$C$5,0) -> 0 | G49: =IF(E49>0,$C$63,0) -> 0 | H49: =IF(E49=0,0,IF(AND(ENTRADAS!$G$25>=F49,ENTRADAS!$G$25<=G49),1,0)) -> 0 | I49: =180/A49 -> 3.2142857 | J49: 0.479 | K49: 0.24328 | L49: =K49*TAN(PI()*I49/180) -> 0.013662312 | M49: =L49*SIN(PI()*(I49/2)/180) -> 0.0003831767 | N49: =M49*COS(PI()*(I49)/180) -> 0.00038257389 | O49: =CÁLCULOS!$F$79 -> 2.3856884 | P49: =L49*K49 -> 0.0033237672 | Q49: =(O49-(2*L49))*N49 -> 0.0009022484 | R49: =P49+Q49 -> 0.0042260156 | S49: =$T$1 -> 0.03939 | T49: =IF($U$1="X",J49-R49-S49,J49-R49) -> 0.47477398 | U49: =(J49-T49)/J49*100 -> 0.88225795
A50: 57 | B50: =(1.205/TAN(PI()/A50)-0.24)*2 -> 43.201944 | C50: =(1.205/TAN(PI()/A50)-0.295)*2 -> 43.091944 | E50: =IF(AND(ENTRADAS!$E$15>13,ENTRADAS!$E$15<=14),14,0) -> 0 | F50: =IF(E50>0,$C$5,0) -> 0 | G50: =IF(E50>0,$C$63,0) -> 0 | H50: =IF(E50=0,0,IF(AND(ENTRADAS!$G$25>=F50,ENTRADAS!$G$25<=G50),1,0)) -> 0 | I50: =180/A50 -> 3.1578947 | J50: 0.479 | K50: 0.24328 | L50: =K50*TAN(PI()*I50/180) -> 0.013422132 | M50: =L50*SIN(PI()*(I50/2)/180) -> 0.00036983801 | N50: =M50*COS(PI()*(I50)/180) -> 0.00036927642 | O50: =CÁLCULOS!$F$79 -> 2.3856884 | P50: =L50*K50 -> 0.0032653362 | Q50: =(O50-(2*L50))*N50 -> 0.00087106551 | R50: =P50+Q50 -> 0.0041364017 | S50: =$T$1 -> 0.03939 | T50: =IF($U$1="X",J50-R50-S50,J50-R50) -> 0.4748636 | U50: =(J50-T50)/J50*100 -> 0.86354941
A51: 58 | B51: =(1.205/TAN(PI()/A51)-0.24)*2 -> 43.969835 | C51: =(1.205/TAN(PI()/A51)-0.295)*2 -> 43.859835 | E51: =IF(AND(ENTRADAS!$E$15>13,ENTRADAS!$E$15<=14),14,0) -> 0 | F51: =IF(E51>0,$C$5,0) -> 0 | G51: =IF(E51>0,$C$63,0) -> 0 | H51: =IF(E51=0,0,IF(AND(ENTRADAS!$G$25>=F51,ENTRADAS!$G$25<=G51),1,0)) -> 0 | I51: =180/A51 -> 3.1034483 | J51: 0.479 | K51: 0.24328 | L51: =K51*TAN(PI()*I51/180) -> 0.013190258 | M51: =L51*SIN(PI()*(I51/2)/180) -> 0.00035718408 | N51: =M51*COS(PI()*(I51)/180) -> 0.00035666024 | O51: =CÁLCULOS!$F$79 -> 2.3856884 | P51: =L51*K51 -> 0.003208926 | Q51: =(O51-(2*L51))*N51 -> 0.00084147131 | R51: =P51+Q51 -> 0.0040503974 | S51: =$T$1 -> 0.03939 | T51: =IF($U$1="X",J51-R51-S51,J51-R51) -> 0.4749496 | U51: =(J51-T51)/J51*100 -> 0.84559444
A52: 59 | B52: =(1.205/TAN(PI()/A52)-0.24)*2 -> 44.737699 | C52: =(1.205/TAN(PI()/A52)-0.295)*2 -> 44.627699 | E52: =IF(AND(ENTRADAS!$E$15>13,ENTRADAS!$E$15<=14),14,0) -> 0 | F52: =IF(E52>0,$C$5,0) -> 0 | G52: =IF(E52>0,$C$63,0) -> 0 | H52: =IF(E52=0,0,IF(AND(ENTRADAS!$G$25>=F52,ENTRADAS!$G$25<=G52),1,0)) -> 0 | I52: =180/A52 -> 3.0508475 | J52: 0.479 | K52: 0.24328 | L52: =K52*TAN(PI()*I52/180) -> 0.012966268 | M52: =L52*SIN(PI()*(I52/2)/180) -> 0.00034516881 | N52: =M52*COS(PI()*(I52)/180) -> 0.0003446796 | O52: =CÁLCULOS!$F$79 -> 2.3856884 | P52: =L52*K52 -> 0.0031544336 | Q52: =(O52-(2*L52))*N52 -> 0.00081335971 | R52: =P52+Q52 -> 0.0039677934 | S52: =$T$1 -> 0.03939 | T52: =IF($U$1="X",J52-R52-S52,J52-R52) -> 0.47503221 | U52: =(J52-T52)/J52*100 -> 0.82834934
A53: 60 | B53: =(1.205/TAN(PI()/A53)-0.24)*2 -> 45.505539 | C53: =(1.205/TAN(PI()/A53)-0.295)*2 -> 45.395539 | E53: =IF(AND(ENTRADAS!$E$15>13,ENTRADAS!$E$15<=14),14,0) -> 0 | F53: =IF(E53>0,$C$5,0) -> 0 | G53: =IF(E53>0,$C$63,0) -> 0 | H53: =IF(E53=0,0,IF(AND(ENTRADAS!$G$25>=F53,ENTRADAS!$G$25<=G53),1,0)) -> 0 | I53: =180/A53 -> 3 | J53: 0.479 | K53: 0.24328 | L53: =K53*TAN(PI()*I53/180) -> 0.012749765 | M53: =L53*SIN(PI()*(I53/2)/180) -> 0.00033374993 | N53: =M53*COS(PI()*(I53)/180) -> 0.00033329253 | O53: =CÁLCULOS!$F$79 -> 2.3856884 | P53: =L53*K53 -> 0.0031017627 | Q53: =(O53-(2*L53))*N53 -> 0.00078663333 | R53: =P53+Q53 -> 0.003888396 | S53: =$T$1 -> 0.03939 | T53: =IF($U$1="X",J53-R53-S53,J53-R53) -> 0.4751116 | U53: =(J53-T53)/J53*100 -> 0.81177371
A54: 61 | B54: =(1.205/TAN(PI()/A54)-0.24)*2 -> 46.273356 | C54: =(1.205/TAN(PI()/A54)-0.295)*2 -> 46.163356 | E54: =IF(AND(ENTRADAS!$E$15>13,ENTRADAS!$E$15<=14),14,0) -> 0 | F54: =IF(E54>0,$C$5,0) -> 0 | G54: =IF(E54>0,$C$63,0) -> 0 | H54: =IF(E54=0,0,IF(AND(ENTRADAS!$G$25>=F54,ENTRADAS!$G$25<=G54),1,0)) -> 0 | I54: =180/A54 -> 2.9508197 | J54: 0.479 | K54: 0.24328 | L54: =K54*TAN(PI()*I54/180) -> 0.012540379 | M54: =L54*SIN(PI()*(I54/2)/180) -> 0.00032288859 | N54: =M54*COS(PI()*(I54)/180) -> 0.00032246047 | O54: =CÁLCULOS!$F$79 -> 2.3856884 | P54: =L54*K54 -> 0.0030508234 | Q54: =(O54-(2*L54))*N54 -> 0.00076120265 | R54: =P54+Q54 -> 0.003812026 | S54: =$T$1 -> 0.03939 | T54: =IF($U$1="X",J54-R54-S54,J54-R54) -> 0.47518797 | U54: =(J54-T54)/J54*100 -> 0.79583007
A55: 62 | B55: =(1.205/TAN(PI()/A55)-0.24)*2 -> 47.041151 | C55: =(1.205/TAN(PI()/A55)-0.295)*2 -> 46.931151 | E55: =IF(AND(ENTRADAS!$E$15>13,ENTRADAS!$E$15<=14),14,0) -> 0 | F55: =IF(E55>0,$C$5,0) -> 0 | G55: =IF(E55>0,$C$63,0) -> 0 | H55: =IF(E55=0,0,IF(AND(ENTRADAS!$G$25>=F55,ENTRADAS!$G$25<=G55),1,0)) -> 0 | I55: =180/A55 -> 2.9032258 | J55: 0.479 | K55: 0.24328 | L55: =K55*TAN(PI()*I55/180) -> 0.012337765 | M55: =L55*SIN(PI()*(I55/2)/180) -> 0.00031254908 | N55: =M55*COS(PI()*(I55)/180) -> 0.00031214793 | O55: =CÁLCULOS!$F$79 -> 2.3856884 | P55: =L55*K55 -> 0.0030015315 | Q55: =(O55-(2*L55))*N55 -> 0.00073698527 | R55: =P55+Q55 -> 0.0037385168 | S55: =$T$1 -> 0.03939 | T55: =IF($U$1="X",J55-R55-S55,J55-R55) -> 0.47526148 | U55: =(J55-T55)/J55*100 -> 0.78048367
A56: 63 | B56: =(1.205/TAN(PI()/A56)-0.24)*2 -> 47.808924 | C56: =(1.205/TAN(PI()/A56)-0.295)*2 -> 47.698924 | E56: =IF(AND(ENTRADAS!$E$15>13,ENTRADAS!$E$15<=14),14,0) -> 0 | F56: =IF(E56>0,$C$5,0) -> 0 | G56: =IF(E56>0,$C$63,0) -> 0 | H56: =IF(E56=0,0,IF(AND(ENTRADAS!$G$25>=F56,ENTRADAS!$G$25<=G56),1,0)) -> 0 | I56: =180/A56 -> 2.8571429 | J56: 0.479 | K56: 0.24328 | L56: =K56*TAN(PI()*I56/180) -> 0.0121416 | M56: =L56*SIN(PI()*(I56/2)/180) -> 0.00030269849 | N56: =M56*COS(PI()*(I56)/180) -> 0.00030232221 | O56: =CÁLCULOS!$F$79 -> 2.3856884 | P56: =L56*K56 -> 0.0029538085 | Q56: =(O56-(2*L56))*N56 -> 0.00071390524 | R56: =P56+Q56 -> 0.0036677137 | S56: =$T$1 -> 0.03939 | T56: =IF($U$1="X",J56-R56-S56,J56-R56) -> 0.47533229 | U56: =(J56-T56)/J56*100 -> 0.76570223
A57: 64 | B57: =(1.205/TAN(PI()/A57)-0.24)*2 -> 48.576677 | C57: =(1.205/TAN(PI()/A57)-0.295)*2 -> 48.466677 | E57: =IF(AND(ENTRADAS!$E$15>13,ENTRADAS!$E$15<=14),14,0) -> 0 | F57: =IF(E57>0,$C$5,0) -> 0 | G57: =IF(E57>0,$C$63,0) -> 0 | H57: =IF(E57=0,0,IF(AND(ENTRADAS!$G$25>=F57,ENTRADAS!$G$25<=G57),1,0)) -> 0 | I57: =180/A57 -> 2.8125 | J57: 0.479 | K57: 0.24328 | L57: =K57*TAN(PI()*I57/180) -> 0.01195158 | M57: =L57*SIN(PI()*(I57/2)/180) -> 0.00029330646 | N57: =M57*COS(PI()*(I57)/180) -> 0.00029295316 | O57: =CÁLCULOS!$F$79 -> 2.3856884 | P57: =L57*K57 -> 0.0029075804 | Q57: =(O57-(2*L57))*N57 -> 0.00069189244 | R57: =P57+Q57 -> 0.0035994728 | S57: =$T$1 -> 0.03939 | T57: =IF($U$1="X",J57-R57-S57,J57-R57) -> 0.47540053 | U57: =(J57-T57)/J57*100 -> 0.7514557
A58: 65 | B58: =(1.205/TAN(PI()/A58)-0.24)*2 -> 49.344411 | C58: =(1.205/TAN(PI()/A58)-0.295)*2 -> 49.234411 | E58: =IF(AND(ENTRADAS!$E$15>13,ENTRADAS!$E$15<=14),14,0) -> 0 | F58: =IF(E58>0,$C$5,0) -> 0 | G58: =IF(E58>0,$C$63,0) -> 0 | H58: =IF(E58=0,0,IF(AND(ENTRADAS!$G$25>=F58,ENTRADAS!$G$25<=G58),1,0)) -> 0 | I58: =180/A58 -> 2.7692308 | J58: 0.479 | K58: 0.24328 | L58: =K58*TAN(PI()*I58/180) -> 0.011767421 | M58: =L58*SIN(PI()*(I58/2)/180) -> 0.00028434495 | N58: =M58*COS(PI()*(I58)/180) -> 0.0002840129 | O58: =CÁLCULOS!$F$79 -> 2.3856884 | P58: =L58*K58 -> 0.0028627781 | Q58: =(O58-(2*L58))*N58 -> 0.00067088209 | R58: =P58+Q58 -> 0.0035336602 | S58: =$T$1 -> 0.03939 | T58: =IF($U$1="X",J58-R58-S58,J58-R58) -> 0.47546634 | U58: =(J58-T58)/J58*100 -> 0.73771611
A59: 66 | B59: =(1.205/TAN(PI()/A59)-0.24)*2 -> 50.112126 | C59: =(1.205/TAN(PI()/A59)-0.295)*2 -> 50.002126 | E59: =IF(AND(ENTRADAS!$E$15>13,ENTRADAS!$E$15<=14),14,0) -> 0 | F59: =IF(E59>0,$C$5,0) -> 0 | G59: =IF(E59>0,$C$63,0) -> 0 | H59: =IF(E59=0,0,IF(AND(ENTRADAS!$G$25>=F59,ENTRADAS!$G$25<=G59),1,0)) -> 0 | I59: =180/A59 -> 2.7272727 | J59: 0.479 | K59: 0.24328 | L59: =K59*TAN(PI()*I59/180) -> 0.011588855 | M59: =L59*SIN(PI()*(I59/2)/180) -> 0.00027578806 | N59: =M59*COS(PI()*(I59)/180) -> 0.00027547569 | O59: =CÁLCULOS!$F$79 -> 2.3856884 | P59: =L59*K59 -> 0.0028193366 | Q59: =(O59-(2*L59))*N59 -> 0.00065081425 | R59: =P59+Q59 -> 0.0034701508 | S59: =$T$1 -> 0.03939 | T59: =IF($U$1="X",J59-R59-S59,J59-R59) -> 0.47552985 | U59: =(J59-T59)/J59*100 -> 0.72445738
... A63: 70 | B63: =(1.205/TAN(PI()/A63)-0.24)*2 -> 53.182819 | C63: =(1.205/TAN(PI()/A63)-0.295)*2 -> 53.072819 | E63: =IF(AND(ENTRADAS!$E$15>13,ENTRADAS!$E$15<=14),14,0) -> 0 | F63: =IF(E63>0,$C$5,0) -> 0 | G63: =IF(E63>0,$C$63,0) -> 0 | H63: =IF(E63=0,0,IF(AND(ENTRADAS!$G$25>=F63,ENTRADAS!$G$25<=G63),1,0)) -> 0 | I63: =180/A63 -> 2.5714286 | J63: 0.479 | K63: 0.24328 | L63: =K63*TAN(PI()*I63/180) -> 0.010925717 | M63: =L63*SIN(PI()*(I63/2)/180) -> 0.00024515195 | N63: =M63*COS(PI()*(I63)/180) -> 0.0002449051 | O63: =CÁLCULOS!$F$79 -> 2.3856884 | P63: =L63*K63 -> 0.0026580085 | Q63: =(O63-(2*L63))*N63 -> 0.00057891572 | R63: =P63+Q63 -> 0.0032369243 | S63: =$T$1 -> 0.03939 | T63: =IF($U$1="X",J63-R63-S63,J63-R63) -> 0.47576308 | U63: =(J63-T63)/J63*100 -> 0.67576707
A64: 71 | B64: =(1.205/TAN(PI()/A64)-0.24)*2 -> 53.950454 | C64: =(1.205/TAN(PI()/A64)-0.295)*2 -> 53.840454 | E64: =IF(AND(ENTRADAS!$E$15>12,ENTRADAS!$E$15<=13),13,0) -> 0 | F64: =IF(E64>0,$C$5,0) -> 0 | G64: =IF(E64>0,$C$63,0) -> 0 | H64: =IF(E64=0,0,IF(AND(ENTRADAS!$G$25>=F64,ENTRADAS!$G$25<=G64),1,0)) -> 0 | I64: =180/A64 -> 2.5352113 | J64: 0.479 | K64: 0.24328 | L64: =K64*TAN(PI()*I64/180) -> 0.010771632 | M64: =L64*SIN(PI()*(I64/2)/180) -> 0.00023829097 | N64: =M64*COS(PI()*(I64)/180) -> 0.00023805774 | O64: =CÁLCULOS!$F$79 -> 2.3856884 | P64: =L64*K64 -> 0.0026205225 | Q64: =(O64-(2*L64))*N64 -> 0.00056280305 | R64: =P64+Q64 -> 0.0031833256 | S64: =$T$1 -> 0.03939 | T64: =IF($U$1="X",J64-R64-S64,J64-R64) -> 0.47581667 | U64: =(J64-T64)/J64*100 -> 0.66457736
A65: 72 | B65: =(1.205/TAN(PI()/A65)-0.24)*2 -> 54.718075 | C65: =(1.205/TAN(PI()/A65)-0.295)*2 -> 54.608075 | E65: =IF(AND(ENTRADAS!$E$15>12,ENTRADAS!$E$15<=13),13,0) -> 0 | F65: =IF(E65>0,$C$5,0) -> 0 | G65: =IF(E65>0,$C$63,0) -> 0 | H65: =IF(E65=0,0,IF(AND(ENTRADAS!$G$25>=F65,ENTRADAS!$G$25<=G65),1,0)) -> 0 | I65: =180/A65 -> 2.5 | J65: 0.479 | K65: 0.24328 | L65: =K65*TAN(PI()*I65/180) -> 0.010621834 | M65: =L65*SIN(PI()*(I65/2)/180) -> 0.00023171409 | N65: =M65*COS(PI()*(I65)/180) -> 0.00023149355 | O65: =CÁLCULOS!$F$79 -> 2.3856884 | P65: =L65*K65 -> 0.0025840798 | Q65: =(O65-(2*L65))*N65 -> 0.00054735371 | R65: =P65+Q65 -> 0.0031314335 | S65: =$T$1 -> 0.03939 | T65: =IF($U$1="X",J65-R65-S65,J65-R65) -> 0.47586857 | U65: =(J65-T65)/J65*100 -> 0.65374395
A66: 73 | B66: =(1.205/TAN(PI()/A66)-0.24)*2 -> 55.485682 | C66: =(1.205/TAN(PI()/A66)-0.295)*2 -> 55.375682 | E66: =IF(AND(ENTRADAS!$E$15>11,ENTRADAS!$E$15<=12),12,0) -> 0 | F66: =IF(E66>0,$C$5,0) -> 0 | G66: =IF(E66>0,$C$63,0) -> 0 | H66: =IF(E66=0,0,IF(AND(ENTRADAS!$G$25>=F66,ENTRADAS!$G$25<=G66),1,0)) -> 0 | I66: =180/A66 -> 2.4657534 | J66: 0.479 | K66: 0.24328 | L66: =K66*TAN(PI()*I66/180) -> 0.010476149 | M66: =L66*SIN(PI()*(I66/2)/180) -> 0.00022540583 | N66: =M66*COS(PI()*(I66)/180) -> 0.00022519713 | O66: =CÁLCULOS!$F$79 -> 2.3856884 | P66: =L66*K66 -> 0.0025486374 | Q66: =(O66-(2*L66))*N66 -> 0.00053253179 | R66: =P66+Q66 -> 0.0030811692 | S66: =$T$1 -> 0.03939 | T66: =IF($U$1="X",J66-R66-S66,J66-R66) -> 0.47591883 | U66: =(J66-T66)/J66*100 -> 0.64325036
A67: 74 | B67: =(1.205/TAN(PI()/A67)-0.24)*2 -> 56.253276 | C67: =(1.205/TAN(PI()/A67)-0.295)*2 -> 56.143276 | E67: =IF(AND(ENTRADAS!$E$15>11,ENTRADAS!$E$15<=12),12,0) -> 0 | F67: =IF(E67>0,$C$5,0) -> 0 | G67: =IF(E67>0,$C$63,0) -> 0 | H67: =IF(E67=0,0,IF(AND(ENTRADAS!$G$25>=F67,ENTRADAS!$G$25<=G67),1,0)) -> 0 | I67: =180/A67 -> 2.4324324 | J67: 0.479 | K67: 0.24328 | L67: =K67*TAN(PI()*I67/180) -> 0.010334408 | M67: =L67*SIN(PI()*(I67/2)/180) -> 0.00021935176 | N67: =M67*COS(PI()*(I67)/180) -> 0.00021915412 | O67: =CÁLCULOS!$F$79 -> 2.3856884 | P67: =L67*K67 -> 0.0025141547 | Q67: =(O67-(2*L67))*N67 -> 0.00051830378 | R67: =P67+Q67 -> 0.0030324585 | S67: =$T$1 -> 0.03939 | T67: =IF($U$1="X",J67-R67-S67,J67-R67) -> 0.47596754 | U67: =(J67-T67)/J67*100 -> 0.6330811
A68: 75 | B68: =(1.205/TAN(PI()/A68)-0.24)*2 -> 57.020858 | C68: =(1.205/TAN(PI()/A68)-0.295)*2 -> 56.910858 | E68: =IF(AND(ENTRADAS!$E$15>11,ENTRADAS!$E$15<=12),12,0) -> 0 | F68: =IF(E68>0,$C$5,0) -> 0 | G68: =IF(E68>0,$C$63,0) -> 0 | H68: =IF(E68=0,0,IF(AND(ENTRADAS!$G$25>=F68,ENTRADAS!$G$25<=G68),1,0)) -> 0 | I68: =180/A68 -> 2.4 | J68: 0.479 | K68: 0.24328 | L68: =K68*TAN(PI()*I68/180) -> 0.010196453 | M68: =L68*SIN(PI()*(I68/2)/180) -> 0.0002135384 | N68: =M68*COS(PI()*(I68)/180) -> 0.00021335109 | O68: =CÁLCULOS!$F$79 -> 2.3856884 | P68: =L68*K68 -> 0.0024805931 | Q68: =(O68-(2*L68))*N68 -> 0.00050463838 | R68: =P68+Q68 -> 0.0029852315 | S68: =$T$1 -> 0.03939 | T68: =IF($U$1="X",J68-R68-S68,J68-R68) -> 0.47601477 | U68: =(J68-T68)/J68*100 -> 0.6232216
A69: 76 | B69: =(1.205/TAN(PI()/A69)-0.24)*2 -> 57.788428 | C69: =(1.205/TAN(PI()/A69)-0.295)*2 -> 57.678428 | E69: =IF(AND(ENTRADAS!$E$15>10,ENTRADAS!$E$15<=11),11,0) -> 0 | F69: =IF(E69>0,$C$5,0) -> 0 | G69: =IF(E69>0,$C$63,0) -> 0 | H69: =IF(E69=0,0,IF(AND(ENTRADAS!$G$25>=F69,ENTRADAS!$G$25<=G69),1,0)) -> 0 | I69: =180/A69 -> 2.3684211 | J69: 0.479 | K69: 0.24328 | L69: =K69*TAN(PI()*I69/180) -> 0.010062135 | M69: =L69*SIN(PI()*(I69/2)/180) -> 0.00020795315 | N69: =M69*COS(PI()*(I69)/180) -> 0.00020777551 | O69: =CÁLCULOS!$F$79 -> 2.3856884 | P69: =L69*K69 -> 0.0024479163 | Q69: =(O69-(2*L69))*N69 -> 0.0004915063 | R69: =P69+Q69 -> 0.0029394226 | S69: =$T$1 -> 0.03939 | T69: =IF($U$1="X",J69-R69-S69,J69-R69) -> 0.47606058 | U69: =(J69-T69)/J69*100 -> 0.61365815
A70: 77 | B70: =(1.205/TAN(PI()/A70)-0.24)*2 -> 58.555986 | C70: =(1.205/TAN(PI()/A70)-0.295)*2 -> 58.445986 | E70: =IF(AND(ENTRADAS!$E$15>10,ENTRADAS!$E$15<=11),11,0) -> 0 | F70: =IF(E70>0,$C$5,0) -> 0 | G70: =IF(E70>0,$C$63,0) -> 0 | H70: =IF(E70=0,0,IF(AND(ENTRADAS!$G$25>=F70,ENTRADAS!$G$25<=G70),1,0)) -> 0 | I70: =180/A70 -> 2.3376623 | J70: 0.479 | K70: 0.24328 | L70: =K70*TAN(PI()*I70/180) -> 0.0099313121 | M70: =L70*SIN(PI()*(I70/2)/180) -> 0.00020258424 | N70: =M70*COS(PI()*(I70)/180) -> 0.00020241565 | O70: =CÁLCULOS!$F$79 -> 2.3856884 | P70: =L70*K70 -> 0.0024160896 | Q70: =(O70-(2*L70))*N70 -> 0.00047888016 | R70: =P70+Q70 -> 0.0028949698 | S70: =$T$1 -> 0.03939 | T70: =IF($U$1="X",J70-R70-S70,J70-R70) -> 0.47610503 | U70: =(J70-T70)/J70*100 -> 0.60437782
A71: 78 | B71: =(1.205/TAN(PI()/A71)-0.24)*2 -> 59.323533 | C71: =(1.205/TAN(PI()/A71)-0.295)*2 -> 59.213533 | E71: =IF(AND(ENTRADAS!$E$15>10,ENTRADAS!$E$15<=11),11,0) -> 0 | F71: =IF(E71>0,$C$5,0) -> 0 | G71: =IF(E71>0,$C$63,0) -> 0 | H71: =IF(E71=0,0,IF(AND(ENTRADAS!$G$25>=F71,ENTRADAS!$G$25<=G71),1,0)) -> 0 | I71: =180/A71 -> 2.3076923 | J71: 0.479 | K71: 0.24328 | L71: =K71*TAN(PI()*I71/180) -> 0.0098038488 | M71: =L71*SIN(PI()*(I71/2)/180) -> 0.00019742063 | N71: =M71*COS(PI()*(I71)/180) -> 0.00019726052 | O71: =CÁLCULOS!$F$79 -> 2.3856884 | P71: =L71*K71 -> 0.0023850803 | Q71: =(O71-(2*L71))*N71 -> 0.0004667343 | R71: =P71+Q71 -> 0.0028518147 | S71: =$T$1 -> 0.03939 | T71: =IF($U$1="X",J71-R71-S71,J71-R71) -> 0.47614819 | U71: =(J71-T71)/J71*100 -> 0.5953684
A72: 79 | B72: =(1.205/TAN(PI()/A72)-0.24)*2 -> 60.09107 | C72: =(1.205/TAN(PI()/A72)-0.295)*2 -> 59.98107 | E72: =IF(AND(ENTRADAS!$E$15>9,ENTRADAS!$E$15<=10),10,0) -> 0 | F72: =IF(E72>0,$C$5,0) -> 0 | G72: =IF(E72>0,$C$63,0) -> 0 | H72: =IF(E72=0,0,IF(AND(ENTRADAS!$G$25>=F72,ENTRADAS!$G$25<=G72),1,0)) -> 0 | I72: =180/A72 -> 2.278481 | J72: 0.479 | K72: 0.24328 | L72: =K72*TAN(PI()*I72/180) -> 0.0096796177 | M72: =L72*SIN(PI()*(I72/2)/180) -> 0.00019245198 | N72: =M72*COS(PI()*(I72)/180) -> 0.00019229982 | O72: =CÁLCULOS!$F$79 -> 2.3856884 | P72: =L72*K72 -> 0.0023548574 | Q72: =(O72-(2*L72))*N72 -> 0.00045504468 | R72: =P72+Q72 -> 0.0028099021 | S72: =$T$1 -> 0.03939 | T72: =IF($U$1="X",J72-R72-S72,J72-R72) -> 0.4761901 | U72: =(J72-T72)/J72*100 -> 0.58661839
A73: 80 | B73: =(1.205/TAN(PI()/A73)-0.24)*2 -> 60.858596 | C73: =(1.205/TAN(PI()/A73)-0.295)*2 -> 60.748596 | E73: =IF(AND(ENTRADAS!$E$15>9,ENTRADAS!$E$15<=10),10,0) -> 0 | F73: =IF(E73>0,$C$5,0) -> 0 | G73: =IF(E73>0,$C$63,0) -> 0 | H73: =IF(E73=0,0,IF(AND(ENTRADAS!$G$25>=F73,ENTRADAS!$G$25<=G73),1,0)) -> 0 | I73: =180/A73 -> 2.25 | J73: 0.479 | K73: 0.24328 | L73: =K73*TAN(PI()*I73/180) -> 0.0095584972 | M73: =L73*SIN(PI()*(I73/2)/180) -> 0.0001876686 | N73: =M73*COS(PI()*(I73)/180) -> 0.00018752391 | O73: =CÁLCULOS!$F$79 -> 2.3856884 | P73: =L73*K73 -> 0.0023253912 | Q73: =(O73-(2*L73))*N73 -> 0.00044378872 | R73: =P73+Q73 -> 0.0027691799 | S73: =$T$1 -> 0.03939 | T73: =IF($U$1="X",J73-R73-S73,J73-R73) -> 0.47623082 | U73: =(J73-T73)/J73*100 -> 0.5781169
A74: 81 | B74: =(1.205/TAN(PI()/A74)-0.24)*2 -> 61.626112 | C74: =(1.205/TAN(PI()/A74)-0.295)*2 -> 61.516112 | E74: =IF(AND(ENTRADAS!$E$15>9,ENTRADAS!$E$15<=10),10,0) -> 0 | F74: =IF(E74>0,$C$5,0) -> 0 | G74: =IF(E74>0,$C$63,0) -> 0 | H74: =IF(E74=0,0,IF(AND(ENTRADAS!$G$25>=F74,ENTRADAS!$G$25<=G74),1,0)) -> 0 | I74: =180/A74 -> 2.2222222 | J74: 0.479 | K74: 0.24328 | L74: =K74*TAN(PI()*I74/180) -> 0.0094403719 | M74: =L74*SIN(PI()*(I74/2)/180) -> 0.00018306138 | N74: =M74*COS(PI()*(I74)/180) -> 0.00018292371 | O74: =CÁLCULOS!$F$79 -> 2.3856884 | P74: =L74*K74 -> 0.0022966537 | Q74: =(O74-(2*L74))*N74 -> 0.00043294524 | R74: =P74+Q74 -> 0.0027295989 | S74: =$T$1 -> 0.03939 | T74: =IF($U$1="X",J74-R74-S74,J74-R74) -> 0.4762704 | U74: =(J74-T74)/J74*100 -> 0.56985364
A75: 82 | B75: =(1.205/TAN(PI()/A75)-0.24)*2 -> 62.393619 | C75: =(1.205/TAN(PI()/A75)-0.295)*2 -> 62.283619 | E75: =IF(AND(ENTRADAS!$E$15>9,ENTRADAS!$E$15<=10),10,0) -> 0 | F75: =IF(E75>0,$C$5,0) -> 0 | G75: =IF(E75>0,$C$63,0) -> 0 | H75: =IF(E75=0,0,IF(AND(ENTRADAS!$G$25>=F75,ENTRADAS!$G$25<=G75),1,0)) -> 0 | I75: =180/A75 -> 2.195122 | J75: 0.479 | K75: 0.24328 | L75: =K75*TAN(PI()*I75/180) -> 0.009325132 | M75: =L75*SIN(PI()*(I75/2)/180) -> 0.0001786218 | N75: =M75*COS(PI()*(I75)/180) -> 0.00017849072 | O75: =CÁLCULOS!$F$79 -> 2.3856884 | P75: =L75*K75 -> 0.0022686181 | Q75: =(O75-(2*L75))*N75 -> 0.00042249434 | R75: =P75+Q75 -> 0.0026911125 | S75: =$T$1 -> 0.03939 | T75: =IF($U$1="X",J75-R75-S75,J75-R75) -> 0.47630889 | U75: =(J75-T75)/J75*100 -> 0.56181888
A76: 83 | B76: =(1.205/TAN(PI()/A76)-0.24)*2 -> 63.161117 | C76: =(1.205/TAN(PI()/A76)-0.295)*2 -> 63.051117 | E76: =IF(AND(ENTRADAS!$E$15>8,ENTRADAS!$E$15<=9),9,0) -> 0 | F76: =IF(E76>0,$C$5,0) -> 0 | G76: =IF(E76>0,$C$63,0) -> 0 | H76: =IF(E76=0,0,IF(AND(ENTRADAS!$G$25>=F76,ENTRADAS!$G$25<=G76),1,0)) -> 0 | I76: =180/A76 -> 2.1686747 | J76: 0.479 | K76: 0.24328 | L76: =K76*TAN(PI()*I76/180) -> 0.009212673 | M76: =L76*SIN(PI()*(I76/2)/180) -> 0.0001743418 | N76: =M76*COS(PI()*(I76)/180) -> 0.00017421692 | O76: =CÁLCULOS!$F$79 -> 2.3856884 | P76: =L76*K76 -> 0.0022412591 | Q76: =(O76-(2*L76))*N76 -> 0.00041241729 | R76: =P76+Q76 -> 0.0026536764 | S76: =$T$1 -> 0.03939 | T76: =IF($U$1="X",J76-R76-S76,J76-R76) -> 0.47634632 | U76: =(J76-T76)/J76*100 -> 0.55400342
A77: 84 | B77: =(1.205/TAN(PI()/A77)-0.24)*2 -> 63.928606 | C77: =(1.205/TAN(PI()/A77)-0.295)*2 -> 63.818606 | E77: =IF(AND(ENTRADAS!$E$15>8,ENTRADAS!$E$15<=9),9,0) -> 0 | F77: =IF(E77>0,$C$5,0) -> 0 | G77: =IF(E77>0,$C$63,0) -> 0 | H77: =IF(E77=0,0,IF(AND(ENTRADAS!$G$25>=F77,ENTRADAS!$G$25<=G77),1,0)) -> 0 | I77: =180/A77 -> 2.1428571 | J77: 0.479 | K77: 0.24328 | L77: =K77*TAN(PI()*I77/180) -> 0.0091028954 | M77: =L77*SIN(PI()*(I77/2)/180) -> 0.00017021382 | N77: =M77*COS(PI()*(I77)/180) -> 0.00017009479 | O77: =CÁLCULOS!$F$79 -> 2.3856884 | P77: =L77*K77 -> 0.0022145524 | Q77: =(O77-(2*L77))*N77 -> 0.00040269647 | R77: =P77+Q77 -> 0.0026172488 | S77: =$T$1 -> 0.03939 | T77: =IF($U$1="X",J77-R77-S77,J77-R77) -> 0.47638275 | U77: =(J77-T77)/J77*100 -> 0.54639851
A78: 85 | B78: =(1.205/TAN(PI()/A78)-0.24)*2 -> 64.696086 | C78: =(1.205/TAN(PI()/A78)-0.295)*2 -> 64.586086 | E78: =IF(AND(ENTRADAS!$E$15>8,ENTRADAS!$E$15<=9),9,0) -> 0 | F78: =IF(E78>0,$C$5,0) -> 0 | G78: =IF(E78>0,$C$63,0) -> 0 | H78: =IF(E78=0,0,IF(AND(ENTRADAS!$G$25>=F78,ENTRADAS!$G$25<=G78),1,0)) -> 0 | I78: =180/A78 -> 2.1176471 | J78: 0.479 | K78: 0.24328 | L78: =K78*TAN(PI()*I78/180) -> 0.0089957043 | M78: =L78*SIN(PI()*(I78/2)/180) -> 0.00016623076 | N78: =M78*COS(PI()*(I78)/180) -> 0.00016611724 | O78: =CÁLCULOS!$F$79 -> 2.3856884 | P78: =L78*K78 -> 0.0021884749 | Q78: =(O78-(2*L78))*N78 -> 0.00039331529 | R78: =P78+Q78 -> 0.0025817902 | S78: =$T$1 -> 0.03939 | T78: =IF($U$1="X",J78-R78-S78,J78-R78) -> 0.47641821 | U78: =(J78-T78)/J78*100 -> 0.53899587
A79: 86 | B79: =(1.205/TAN(PI()/A79)-0.24)*2 -> 65.463559 | C79: =(1.205/TAN(PI()/A79)-0.295)*2 -> 65.353559 | E79: =IF(AND(ENTRADAS!$E$15>8,ENTRADAS!$E$15<=9),9,0) -> 0 | F79: =IF(E79>0,$C$5,0) -> 0 | G79: =IF(E79>0,$C$63,0) -> 0 | H79: =IF(E79=0,0,IF(AND(ENTRADAS!$G$25>=F79,ENTRADAS!$G$25<=G79),1,0)) -> 0 | I79: =180/A79 -> 2.0930233 | J79: 0.479 | K79: 0.24328 | L79: =K79*TAN(PI()*I79/180) -> 0.0088910094 | M79: =L79*SIN(PI()*(I79/2)/180) -> 0.00016238591 | N79: =M79*COS(PI()*(I79)/180) -> 0.00016227758 | O79: =CÁLCULOS!$F$79 -> 2.3856884 | P79: =L79*K79 -> 0.0021630048 | Q79: =(O79-(2*L79))*N79 -> 0.00038425811 | R79: =P79+Q79 -> 0.0025472629 | S79: =$T$1 -> 0.03939 | T79: =IF($U$1="X",J79-R79-S79,J79-R79) -> 0.47645274 | U79: =(J79-T79)/J79*100 -> 0.53178766
A80: 87 | B80: =(1.205/TAN(PI()/A80)-0.24)*2 -> 66.231023 | C80: =(1.205/TAN(PI()/A80)-0.295)*2 -> 66.121023 | E80: =IF(AND(ENTRADAS!$E$15>7,ENTRADAS!$E$15<=8),8,0) -> 8 | F80: =IF(E80>0,$C$5,0) -> 8.4042424 | G80: =IF(E80>0,$C$63,0) -> 53.072819 | H80: =IF(E80=0,0,IF(AND(ENTRADAS!$G$25>=F80,ENTRADAS!$G$25<=G80),1,0)) -> 1 | I80: =180/A80 -> 2.0689655 | J80: 0.479 | K80: 0.24328 | L80: =K80*TAN(PI()*I80/180) -> 0.0087887245 | M80: =L80*SIN(PI()*(I80/2)/180) -> 0.00015867294 | N80: =M80*COS(PI()*(I80)/180) -> 0.0001585695 | O80: =CÁLCULOS!$F$79 -> 2.3856884 | P80: =L80*K80 -> 0.0021381209 | Q80: =(O80-(2*L80))*N80 -> 0.00037551018 | R80: =P80+Q80 -> 0.0025136311 | S80: =$T$1 -> 0.03939 | T80: =IF($U$1="X",J80-R80-S80,J80-R80) -> 0.47648637 | U80: =(J80-T80)/J80*100 -> 0.5247664
A81: 88 | B81: =(1.205/TAN(PI()/A81)-0.24)*2 -> 66.998479 | C81: =(1.205/TAN(PI()/A81)-0.295)*2 -> 66.888479 | E81: =IF(AND(ENTRADAS!$E$15>7,ENTRADAS!$E$15<=8),8,0) -> 8 | F81: =IF(E81>0,$C$5,0) -> 8.4042424 | G81: =IF(E81>0,$C$63,0) -> 53.072819 | H81: =IF(E81=0,0,IF(AND(ENTRADAS!$G$25>=F81,ENTRADAS!$G$25<=G81),1,0)) -> 1 | I81: =180/A81 -> 2.0454545 | J81: 0.479 | K81: 0.24328 | L81: =K81*TAN(PI()*I81/180) -> 0.0086887672 | M81: =L81*SIN(PI()*(I81/2)/180) -> 0.0001550859 | N81: =M81*COS(PI()*(I81)/180) -> 0.00015498708 | O81: =CÁLCULOS!$F$79 -> 2.3856884 | P81: =L81*K81 -> 0.0021138033 | Q81: =(O81-(2*L81))*N81 -> 0.00036705758 | R81: =P81+Q81 -> 0.0024808609 | S81: =$T$1 -> 0.03939 | T81: =IF($U$1="X",J81-R81-S81,J81-R81) -> 0.47651914 | U81: =(J81-T81)/J81*100 -> 0.51792503
A82: 89 | B82: =(1.205/TAN(PI()/A82)-0.24)*2 -> 67.765928 | C82: =(1.205/TAN(PI()/A82)-0.295)*2 -> 67.655928 | E82: =IF(AND(ENTRADAS!$E$15>7,ENTRADAS!$E$15<=8),8,0) -> 8 | F82: =IF(E82>0,$C$5,0) -> 8.4042424 | G82: =IF(E82>0,$C$63,0) -> 53.072819 | H82: =IF(E82=0,0,IF(AND(ENTRADAS!$G$25>=F82,ENTRADAS!$G$25<=G82),1,0)) -> 1 | I82: =180/A82 -> 2.0224719 | J82: 0.479 | K82: 0.24328 | L82: =K82*TAN(PI()*I82/180) -> 0.008591059 | M82: =L82*SIN(PI()*(I82/2)/180) -> 0.00015161914 | N82: =M82*COS(PI()*(I82)/180) -> 0.00015152469 | O82: =CÁLCULOS!$F$79 -> 2.3856884 | P82: =L82*K82 -> 0.0020900328 | Q82: =(O82-(2*L82))*N82 -> 0.00035888718 | R82: =P82+Q82 -> 0.00244892 | S82: =$T$1 -> 0.03939 | T82: =IF($U$1="X",J82-R82-S82,J82-R82) -> 0.47655108 | U82: =(J82-T82)/J82*100 -> 0.51125679
A83: 90 | B83: =(1.205/TAN(PI()/A83)-0.24)*2 -> 68.53337 | C83: =(1.205/TAN(PI()/A83)-0.295)*2 -> 68.42337 | E83: =IF(AND(ENTRADAS!$E$15>7,ENTRADAS!$E$15<=8),8,0) -> 8 | F83: =IF(E83>0,$C$5,0) -> 8.4042424 | G83: =IF(E83>0,$C$63,0) -> 53.072819 | H83: =IF(E83=0,0,IF(AND(ENTRADAS!$G$25>=F83,ENTRADAS!$G$25<=G83),1,0)) -> 1 | I83: =180/A83 -> 2 | J83: 0.479 | K83: 0.24328 | L83: =K83*TAN(PI()*I83/180) -> 0.0084955248 | M83: =L83*SIN(PI()*(I83/2)/180) -> 0.00014826735 | N83: =M83*COS(PI()*(I83)/180) -> 0.00014817703 | O83: =CÁLCULOS!$F$79 -> 2.3856884 | P83: =L83*K83 -> 0.0020667913 | Q83: =(O83-(2*L83))*N83 -> 0.00035098654 | R83: =P83+Q83 -> 0.0024177778 | S83: =$T$1 -> 0.03939 | T83: =IF($U$1="X",J83-R83-S83,J83-R83) -> 0.47658222 | U83: =(J83-T83)/J83*100 -> 0.50475528
A84: 91 | B84: =(1.205/TAN(PI()/A84)-0.24)*2 -> 69.300805 | C84: =(1.205/TAN(PI()/A84)-0.295)*2 -> 69.190805 | G84: soma= | H84: =SUM(H5:H83) -> 4 | I84: =180/A84 -> 1.978022 | J84: 0.479 | K84: 0.24328 | L84: =K84*TAN(PI()*I84/180) -> 0.0084020928 | M84: =L84*SIN(PI()*(I84/2)/180) -> 0.00014502551 | N84: =M84*COS(PI()*(I84)/180) -> 0.00014493909 | O84: =CÁLCULOS!$F$79 -> 2.3856884 | P84: =L84*K84 -> 0.0020440611 | Q84: =(O84-(2*L84))*N84 -> 0.00034334392 | R84: =P84+Q84 -> 0.0023874051 | S84: =$T$1 -> 0.03939 | T84: =IF($U$1="X",J84-R84-S84,J84-R84) -> 0.47661259 | U84: =(J84-T84)/J84*100 -> 0.49841442
A85: 92 | B85: =(1.205/TAN(PI()/A85)-0.24)*2 -> 70.068234 | C85: =(1.205/TAN(PI()/A85)-0.295)*2 -> 69.958234 | I85: =180/A85 -> 1.9565217 | J85: 0.479 | K85: 0.24328 | L85: =K85*TAN(PI()*I85/180) -> 0.0083106942 | M85: =L85*SIN(PI()*(I85/2)/180) -> 0.00014188884 | N85: =M85*COS(PI()*(I85)/180) -> 0.00014180613 | O85: =CÁLCULOS!$F$79 -> 2.3856884 | P85: =L85*K85 -> 0.0020218257 | Q85: =(O85-(2*L85))*N85 -> 0.00033594822 | R85: =P85+Q85 -> 0.0023577739 | S85: =$T$1 -> 0.03939 | T85: =IF($U$1="X",J85-R85-S85,J85-R85) -> 0.47664223 | U85: =(J85-T85)/J85*100 -> 0.49222837
A86: 93 | B86: =(1.205/TAN(PI()/A86)-0.24)*2 -> 70.835656 | C86: =(1.205/TAN(PI()/A86)-0.295)*2 -> 70.725656 | I86: =180/A86 -> 1.9354839 | J86: 0.479 | K86: 0.24328 | L86: =K86*TAN(PI()*I86/180) -> 0.0082212635 | M86: =L86*SIN(PI()*(I86/2)/180) -> 0.00013885287 | N86: =M86*COS(PI()*(I86)/180) -> 0.00013877365 | O86: =CÁLCULOS!$F$79 -> 2.3856884 | P86: =L86*K86 -> 0.002000069 | Q86: =(O86-(2*L86))*N86 -> 0.0003287889 | R86: =P86+Q86 -> 0.0023288579 | S86: =$T$1 -> 0.03939 | T86: =IF($U$1="X",J86-R86-S86,J86-R86) -> 0.47667114 | U86: =(J86-T86)/J86*100 -> 0.48619163
A87: 94 | B87: =(1.205/TAN(PI()/A87)-0.24)*2 -> 71.603071 | C87: =(1.205/TAN(PI()/A87)-0.295)*2 -> 71.493071 | I87: =180/A87 -> 1.9148936 | J87: 0.479 | K87: 0.24328 | L87: =K87*TAN(PI()*I87/180) -> 0.0081337378 | M87: =L87*SIN(PI()*(I87/2)/180) -> 0.00013591331 | N87: =M87*COS(PI()*(I87)/180) -> 0.00013583741 | O87: =CÁLCULOS!$F$79 -> 2.3856884 | P87: =L87*K87 -> 0.0019787757 | Q87: =(O87-(2*L87))*N87 -> 0.000321856 | R87: =P87+Q87 -> 0.0023006317 | S87: =$T$1 -> 0.03939 | T87: =IF($U$1="X",J87-R87-S87,J87-R87) -> 0.47669937 | U87: =(J87-T87)/J87*100 -> 0.4802989
A88: 95 | B88: =(1.205/TAN(PI()/A88)-0.24)*2 -> 72.370481 | C88: =(1.205/TAN(PI()/A88)-0.295)*2 -> 72.260481 | I88: =180/A88 -> 1.8947368 | J88: 0.479 | K88: 0.24328 | L88: =K88*TAN(PI()*I88/180) -> 0.0080480567 | M88: =L88*SIN(PI()*(I88/2)/180) -> 0.00013306613 | N88: =M88*COS(PI()*(I88)/180) -> 0.00013299337 | O88: =CÁLCULOS!$F$79 -> 2.3856884 | P88: =L88*K88 -> 0.0019579312 | Q88: =(O88-(2*L88))*N88 -> 0.00031514007 | R88: =P88+Q88 -> 0.0022730713 | S88: =$T$1 -> 0.03939 | T88: =IF($U$1="X",J88-R88-S88,J88-R88) -> 0.47672693 | U88: =(J88-T88)/J88*100 -> 0.47454516
A89: 96 | B89: =(1.205/TAN(PI()/A89)-0.24)*2 -> 73.137884 | C89: =(1.205/TAN(PI()/A89)-0.295)*2 -> 73.027884 | I89: =180/A89 -> 1.875 | J89: 0.479 | K89: 0.24328 | L89: =K89*TAN(PI()*I89/180) -> 0.0079641626 | M89: =L89*SIN(PI()*(I89/2)/180) -> 0.00013030749 | N89: =M89*COS(PI()*(I89)/180) -> 0.00013023772 | O89: =CÁLCULOS!$F$79 -> 2.3856884 | P89: =L89*K89 -> 0.0019375215 | Q89: =(O89-(2*L89))*N89 -> 0.00030863215 | R89: =P89+Q89 -> 0.0022461536 | S89: =$T$1 -> 0.03939 | T89: =IF($U$1="X",J89-R89-S89,J89-R89) -> 0.47675385 | U89: =(J89-T89)/J89*100 -> 0.4689256
A90: 97 | B90: =(1.205/TAN(PI()/A90)-0.24)*2 -> 73.905282 | C90: =(1.205/TAN(PI()/A90)-0.295)*2 -> 73.795282 | I90: =180/A90 -> 1.8556701 | J90: 0.479 | K90: 0.24328 | L90: =K90*TAN(PI()*I90/180) -> 0.0078820001 | M90: =L90*SIN(PI()*(I90/2)/180) -> 0.00012763377 | N90: =M90*COS(PI()*(I90)/180) -> 0.00012756683 | O90: =CÁLCULOS!$F$79 -> 2.3856884 | P90: =L90*K90 -> 0.001917533 | Q90: =(O90-(2*L90))*N90 -> 0.00030232375 | R90: =P90+Q90 -> 0.0022198567 | S90: =$T$1 -> 0.03939 | T90: =IF($U$1="X",J90-R90-S90,J90-R90) -> 0.47678014 | U90: =(J90-T90)/J90*100 -> 0.46343564
A91: 98 | B91: =(1.205/TAN(PI()/A91)-0.24)*2 -> 74.672675 | C91: =(1.205/TAN(PI()/A91)-0.295)*2 -> 74.562675 | I91: =180/A91 -> 1.8367347 | J91: 0.479 | K91: 0.24328 | L91: =K91*TAN(PI()*I91/180) -> 0.0078015161 | M91: =L91*SIN(PI()*(I91/2)/180) -> 0.00012504151 | N91: =M91*COS(PI()*(I91)/180) -> 0.00012497727 | O91: =CÁLCULOS!$F$79 -> 2.3856884 | P91: =L91*K91 -> 0.0018979528 | Q91: =(O91-(2*L91))*N91 -> 0.00029620679 | R91: =P91+Q91 -> 0.0021941596 | S91: =$T$1 -> 0.03939 | T91: =IF($U$1="X",J91-R91-S91,J91-R91) -> 0.47680584 | U91: =(J91-T91)/J91*100 -> 0.4580709
A92: 99 | B92: =(1.205/TAN(PI()/A92)-0.24)*2 -> 75.440062 | C92: =(1.205/TAN(PI()/A92)-0.295)*2 -> 75.330062 | I92: =180/A92 -> 1.8181818 | J92: 0.479 | K92: 0.24328 | L92: =K92*TAN(PI()*I92/180) -> 0.0077226597 | M92: =L92*SIN(PI()*(I92/2)/180) -> 0.00012252744 | N92: =M92*COS(PI()*(I92)/180) -> 0.00012246575 | O92: =CÁLCULOS!$F$79 -> 2.3856884 | P92: =L92*K92 -> 0.0018787687 | Q92: =(O92-(2*L92))*N92 -> 0.0002902736 | R92: =P92+Q92 -> 0.0021690423 | S92: =$T$1 -> 0.03939 | T92: =IF($U$1="X",J92-R92-S92,J92-R92) -> 0.47683096 | U92: =(J92-T92)/J92*100 -> 0.45282719
A93: 100 | B93: =(1.205/TAN(PI()/A93)-0.24)*2 -> 76.207443 | C93: =(1.205/TAN(PI()/A93)-0.295)*2 -> 76.097443 | I93: =180/A93 -> 1.8 | J93: 0.479 | K93: 0.24328 | L93: =K93*TAN(PI()*I93/180) -> 0.007645382 | M93: =L93*SIN(PI()*(I93/2)/180) -> 0.00012008844 | N93: =M93*COS(PI()*(I93)/180) -> 0.00012002918 | O93: =CÁLCULOS!$F$79 -> 2.3856884 | P93: =L93*K93 -> 0.0018599685 | Q93: =(O93-(2*L93))*N93 -> 0.0002845169 | R93: =P93+Q93 -> 0.0021444854 | S93: =$T$1 -> 0.03939 | T93: =IF($U$1="X",J93-R93-S93,J93-R93) -> 0.47685551 | U93: =(J93-T93)/J93*100 -> 0.44770051
A94: 101 | B94: =(1.205/TAN(PI()/A94)-0.24)*2 -> 76.97482 | C94: =(1.205/TAN(PI()/A94)-0.295)*2 -> 76.86482 | I94: =180/A94 -> 1.7821782 | J94: 0.479 | K94: 0.24328 | L94: =K94*TAN(PI()*I94/180) -> 0.0075696361 | M94: =L94*SIN(PI()*(I94/2)/180) -> 0.00011772156 | N94: =M94*COS(PI()*(I94)/180) -> 0.00011766461 | O94: =CÁLCULOS!$F$79 -> 2.3856884 | P94: =L94*K94 -> 0.0018415411 | Q94: =(O94-(2*L94))*N94 -> 0.00027892974 | R94: =P94+Q94 -> 0.0021204708 | S94: =$T$1 -> 0.03939 | T94: =IF($U$1="X",J94-R94-S94,J94-R94) -> 0.47687953 | U94: =(J94-T94)/J94*100 -> 0.44268702
A95: 102 | B95: =(1.205/TAN(PI()/A95)-0.24)*2 -> 77.742192 | C95: =(1.205/TAN(PI()/A95)-0.295)*2 -> 77.632192 | I95: =180/A95 -> 1.7647059 | J95: 0.479 | K95: 0.24328 | L95: =K95*TAN(PI()*I95/180) -> 0.0074953768 | M95: =L95*SIN(PI()*(I95/2)/180) -> 0.00011542397 | N95: =M95*COS(PI()*(I95)/180) -> 0.00011536923 | O95: =CÁLCULOS!$F$79 -> 2.3856884 | P95: =L95*K95 -> 0.0018234753 | Q95: =(O95-(2*L95))*N95 -> 0.00027350555 | R95: =P95+Q95 -> 0.0020969808 | S95: =$T$1 -> 0.03939 | T95: =IF($U$1="X",J95-R95-S95,J95-R95) -> 0.47690302 | U95: =(J95-T95)/J95*100 -> 0.43778305
A96: 103 | B96: =(1.205/TAN(PI()/A96)-0.24)*2 -> 78.509559 | C96: =(1.205/TAN(PI()/A96)-0.295)*2 -> 78.399559 | I96: =180/A96 -> 1.7475728 | J96: 0.479 | K96: 0.24328 | L96: =K96*TAN(PI()*I96/180) -> 0.0074225607 | M96: =L96*SIN(PI()*(I96/2)/180) -> 0.000113193 | N96: =M96*COS(PI()*(I96)/180) -> 0.00011314035 | O96: =CÁLCULOS!$F$79 -> 2.3856884 | P96: =L96*K96 -> 0.0018057606 | Q96: =(O96-(2*L96))*N96 -> 0.00026823805 | R96: =P96+Q96 -> 0.0020739986 | S96: =$T$1 -> 0.03939 | T96: =IF($U$1="X",J96-R96-S96,J96-R96) -> 0.476926 | U96: =(J96-T96)/J96*100 -> 0.4329851
... A126: 133 | B126: =(1.205/TAN(PI()/A126)-0.24)*2 -> 101.52889 | C126: =(1.205/TAN(PI()/A126)-0.295)*2 -> 101.41889 | I126: =180/A126 -> 1.3533835 | J126: 0.479 | K126: 0.24328 | L126: =K126*TAN(PI()*I126/180) -> 0.0057475852 | M126: =L126*SIN(PI()*(I126/2)/180) -> 6.788027e-05 | N126: =M126*COS(PI()*(I126)/180) -> 6.7861334e-05 | O126: =CÁLCULOS!$F$79 -> 2.3856884 | P126: =L126*K126 -> 0.0013982725 | Q126: =(O126-(2*L126))*N126 -> 0.00016111592 | R126: =P126+Q126 -> 0.0015593885 | S126: =$T$1 -> 0.03939 | T126: =IF($U$1="X",J126-R126-S126,J126-R126) -> 0.47744061 | U126: =(J126-T126)/J126*100 -> 0.32555083
F140: =IF(L2>0,L2,K2) -> 47.041151
F141: =IF(J2>0,J2,IF(I2>0,I2,D2)) -> 62
F142: =IF(F141>A83,0,VLOOKUP(F141,A5:C83,3,0)) -> 46.931151
F143: =IF(F141>A83,0,VLOOKUP(F141,A5:E83,5,0)) -> 0
F144: =IF(AND(ENTRADAS!G25<=F142,ENTRADAS!E15<=F143),"sim","não") -> não
F145: tabelado
F147: =IF(AND(ENTRADAS!G25<=F142,F148<=F143),"sim","não") -> não
F148: =IF(ENTRADAS!E15<=7,"sim",IF(AND(ENTRADAS!E15>7,ENTRADAS!E15<=8),8,IF(AND(ENTRADAS!E15>8,ENTRADAS!E15<=9),9,IF(AND(ENTRADAS!E15>9,ENTRADAS!E15<=10),10,IF(AND(ENTRADAS!E15>10,ENTRADAS!E15<=11),11,IF(AND(ENTRADAS!E15>11,ENTRADAS!E15<=12),12,IF(AND(ENTRADAS!E15>12,ENTRADAS!E15<=13),13,G14))))))) -> 8

Sheet GUINDASTE
E2: GUINDASTES | M2: DATA: | O2: =CÁLCULOS!O1 -> 45638
M3: REVISÃO: | O3: =CÁLCULOS!O2 -> 3
E4: CLIENTE: | F4: =CÁLCULOS!F3 -> Passarelli | M4: LOCAL
E5: LOCAL: | F5: =CÁLCULOS!F4 -> 12 tqs Nereda | M5: =CÁLCULOS!M4 -> São Paulo - Tatuapé
C8: ANÁLISE DE TEMPO MÍNIMO DE GUINDASTE NA OBRA: ( verificar se o locador estipula mínimo de 30 dias para locação )
C10: GUINDASTE MENOR QUE 90 ton, considerar mínimo 30 dias ? | I10: x | J10: sim | M10: não | N10: =IF(I10="X",1,0) -> 1 | O10: =IF(L10="X",1,0) -> 0 | S10: =IF(OR(G77<90,G90<90,G103<90),"GUINDASTE MENOR QUE 90 ton, considerar mínimo 30 dias ?",0) -> GUINDASTE MENOR QUE 90 ton, considerar mínimo 30 dias ?
C12: GUINDASTE MAIOR ou IGUAL à 90 ton, considerar mínimo 30 dias ? | I12: x | J12: sim | M12: não | N12: =IF(I12="X",1,0) -> 1 | O12: =IF(L12="X",1,0) -> 0 | S12: =IF(OR(G77>=90,G90>=90,G103>=90),"GUINDASTE MAIOR ou IGUAL à 90 ton, considerar mínimo 30 dias ?",0) -> 0
D16: MONTAGEM DA PAREDE:
C19: UTILIZAR GIRADOR DE PLACAS ? | F19: x | G19: sim | J19: não
C20: =IF(ENTRADAS!I15=0,0,IF(ENTRADAS!I15<=7,"Altura do painel menor que 7,00 m, logo não há necessidade do GIRADOR DE PLACAS!",0)) -> 0
C22: GUINDASTE 1 (calculado) capacidade= | F22: =IF(L63>0,L63,CÁLCULOS!I279) -> 70 | G22: toneladas | I22: =IF(E62="X","guindaste era "&CÁLCULOS!O279&" ton., mas você optou por igualar ao da cobertura",0) -> 0
BJ23: X
C24: GUINDASTE 2 (calculado) capacidade= | F24: =CÁLCULOS!I280 -> 0 | G24: toneladas | I24: =IF(I29="X"," << Você marcou X para não utilizar este guind. 2 que era de "&CÁLCULOS!O280&" ton",0) -> 0
C26: CASO NÃO QUEIRA UTILIZAR OS GUINDASTES CALCULADOS, INSIRA ABAIXO OS NOVOS GUINDASTES:
C27: GUINDASTE 1 = | E27: 70 | F27: toneladas
C28: GUINDASTE 2 = | F28: toneladas
C29: =IF(F19="X",0,"CASO NÃO QUEIRA O GUINDASTE 2 CALCULADO, MARQUE X:") -> 0 | J29: =IF(I29="x",1000,0) -> 0 | L29: =IF(F23<>0,1000,0) -> 0
C31: MOBILIZAÇÃO do GUINDASTE 1 ( calculado )= | G31: =CÁLCULOS!L281 -> 1 | H31: ------------- | I31: MUDAR QUANT.= | M31: mobilizações de guindaste
F32: =IF(AND(G31>0,G31<1),"ESTE VALOR É DEVIDO AO RATEAMENTO ENTRE PAREDES E COBERTURAS",0) -> 0
C34: MOBILIZAÇÃO do GUINDASTE 2 ( calculado )= | G34: =CÁLCULOS!L282 -> 0 | H34: ------------- | I34: MUDAR QUANT.= | M34: mobilizações de guindaste
C36: PRAZO DE GUINDASTE À DISPOSIÇÃO:
D37: DURANTE CABEAMENTO / INJEÇÃO / ACABAMENTOS / FOLGAS DE CAMPO = | L37: =CÁLCULOS!L141 -> 46 | M37: dias | N37: =SUM(J386:J388)+SUM(J338:J340)+J498*H447 -> 0
D39: DURANTE INTERVALO ENTRE TANQUES = | H39: =CÁLCULOS!H143 -> 0 | I39: dias
E40: PARA DESCONSIDERAR GUINDASTE À DISPOSIÇÃO ( marcar "X" )
D46: =IF(ENTRADAS!D912="x","MONTAGEM DE COBERTURA","NÃO HÁ COBERTURAS") -> NÃO HÁ COBERTURAS
C48: =IF(ENTRADAS!D912="x","Em relação ao espaço para patolagem do guindaste externamente ao tanque ( percentual livre do perímetro):",0) -> 0
D50: =IF(ENTRADAS!D912="x","<= 50%",0) -> 0 | F50: =IF(ENTRADAS!D912="x",">51%",0) -> 0
C53: =IF(ENTRADAS!D912="x","a) GUINDASTE CALCULADO ---------------------------",0) -> 0 | F53: =IF(ENTRADAS!D912="x",IF(ENTRADAS!D912="X",IF(GUINDASTE!E57>0,GUINDASTE!E57,SUM(LAJES!AO154:AO158))),0)&" toneladas" -> 0 toneladas | G53: =IF(ENTRADAS!D912="x","( se for exclusivo para cobertura )",0) -> 0 | O53: =IF(E57>0,"(mudou para "&E57&" toneladas )",0) -> 0
C54: =IF(ENTRADAS!D912="x","b) GUINDASTE CALCULADO ---------------------------",0) -> 0 | F54: =IF(ENTRADAS!D912="x",G103&" toneladas",0) -> 0 | G54: =IF(ENTRADAS!D912="x","( se for cobertura junto com parede)",0) -> 0
C56: =IF(ENTRADAS!D912="x","CASO NÃO QUEIRA UTILIZAR O GUINDASTE CALCULADO no ítem a, INSIRA ABAIXO OS NOVO GUINDASTE:",0) -> 0
C57: =IF(ENTRADAS!D912="x"," GUINDASTE =",0) -> 0 | F57: =IF(ENTRADAS!D912="x","toneladas",0) -> 0
G58: =IF(ENTRADAS!D912="X",IF(L59>0,L59,IF(ENTRADAS!G91+ENTRADAS!G93+ENTRADAS!G97>40,2,1)),0) -> 0
C59: MOBILIZAÇÃO do GUINDASTE ( calculado )= | G59: =IF(ENTRADAS!D912="X",IF(L59>0,L59&" mobilização",IF(C123=1,I94&" mobilização",IF(C125=1,I107&" mobilização",0))),0) -> 0 | H59: ------------- | I59: MUDAR QUANT.= | M59: mobilizações de guindaste
C61: COMPARANDO ESTE GUINDASTE COM O GUINDASTE 1 DA MONTAGEM DAS PAREDES USAR O MAIOR NAS DUAS MONTAGENS ?
F62: SIM | H62: NÃO | I62: =IF(E62="X","o guindaste 1 das paredes e o da cobertura passaram para=","o guindaste 1 das paredes é=") -> o guindaste 1 das paredes é=
L63: =IF(E62="X",IF(E62="X",IF(CÁLCULOS!O279>SUM(LAJES!AO154:AO158),CÁLCULOS!O279,IF(SUM(LAJES!AO154:AO158)>CÁLCULOS!O279,SUM(LAJES!AO154:AO158),G90)),CÁLCULOS!O279),IF(D125="X",G103,0)) -> 0 | M63: toneladas
D68: ANÁLISE DE MOBILIZAÇÃO / DESMOBILIZAÇÃO:
C70: CASO SOMENTE PAREDES | F70: =IF(C72=0,0,1) -> 0 | G70: =IF(I73=0,0,1) -> 0 | H70: =IF(L73=0,0,1) -> 0 | I70: =IF(F70+G70+H70=1,"OBRIGATÓRIO DEFINIÇÃO, SIM OU NÃO !",0) -> 0 | N70: =IF(I70<>0,1,0) -> 0
O71: =IF($D$127<>0,1,0) -> 0
C72: =IF('cronograma unit.'!$E$381=0,0,IF('cronograma unit.'!$E$381=1,"Analisando o cronograma, existe "&'cronograma unit.'!$E$381&" intervalo de "&'cronograma unit.'!$E$380/'cronograma unit.'!$E$381&" dias entre as montagem de paredes. ","Analisando o cronograma, existem "&'cronograma unit.'!$E$381&" intervalos de "&'cronograma unit.'!$E$380/'cronograma unit.'!$E$381&" dias em média entre as montagem de paredes. ")) -> 0 | K72: =IF($D$127<>0,1,0) -> 0
C73: =IF('cronograma unit.'!$E$381=0,0,IF('cronograma unit.'!$E$381=1," Considerar que o guindaste será desmobilizado neste intervalo ?"," Considerar que o guindaste será desmobilizado nestes intervalos ?")) -> 0 | J73: =IF('cronograma unit.'!$E$381=0,0,"sim") -> 0 | M73: =IF('cronograma unit.'!$E$381=0,0,"não") -> 0
O74: =IF($D$127<>0,1,0) -> 0 | S74: NÃO DESMOB. | V74: SIM DESMOB.
O75: =IF($D$127<>0,1,0) -> 0 | S75: a disposição | V75: a disposição
C76: =IF(ENTRADAS!$C$395="x","MONTAGEM SEQUENCIAL:",IF(ENTRADAS!$C$397="x","MONTAGEM NÃO SEQUENCIAL:",0)) -> MONTAGEM SEQUENCIAL: | F76: =IF(SUM($N$10:$O$12)>0,0,"VOLTE E DEFINA O TEMPO MÍNIMO DE GUINDASTE ACIMA !") -> 0 | S76: =S78 -> 70 | T76: =IF(S76=0,0,IF(S76<90,IF((ROUNDUP('cronograma unit.'!$E$378/7*6,0)+ROUNDUP('cronograma unit.'!$E$380/7*6,0))>=30/7*6,ROUNDUP('cronograma unit.'!$E$380/7*6,0),IF($O$10=1,ROUNDUP('cronograma unit.'!$E$380/7*6,0),IF($N$10=1,ROUNDUP((30/7*6),0)-ROUNDUP('cronograma unit.'!$E$378/7*6,0),0))),IF((ROUNDUP('cronograma unit.'!$E$378/7*6,0)+ROUNDUP('cronograma unit.'!$E$380/7*6,0))>=30/7*6,ROUNDUP('cronograma unit.'!$E$380/7*6,0),IF($O$12=1,ROUNDUP('cronograma unit.'!$E$380/7*6,0),IF($N$12=1,ROUNDUP((30/7*6),0)-ROUNDUP('cronograma unit.'!$E$378/7*6,0),0))))) -> 0 | V76: =V78 -> 70 | W76: =0 -> 0
D77: GUINDASTE G1 TRABALHANDO= | G77: =$F$22 -> 70 | H77: ton | I77: =IF(AND(ENTRADAS!F22=1,O10=1,G77<90,C125<>1),ROUNDUP(SUM(RELATÓRIO!S181:S187),0),IF(AND(ENTRADAS!F22=1,O12=1,G77>=90,C125<>1),ROUNDUP(SUM(RELATÓRIO!S181:S187),0),IF('cronograma unit.'!$E$381>0,IF(L73="X",T78,IF(I73="X",W78,0)),T78))) -> 88 | J77: dias (seg a sab ) | S77: trabalhando | V77: trabalhando
O78: =IF($D$127<>0,1,0) -> 0 | S78: =G77 -> 70 | T78: =IF(S78=0,0,IF(S78<90,IF((ROUNDUP('cronograma unit.'!$E$378/7*6,0)+ROUNDUP('cronograma unit.'!$E$380/7*6,0))>=30/7*6,ROUNDUP('cronograma unit.'!$E$378/7*6,0),IF($O$10=1,ROUNDUP('cronograma unit.'!$E$378/7*6,0),IF($N$10=1,ROUNDUP(30/7*6,0),0))),IF(S78>=90,IF((ROUNDUP('cronograma unit.'!$E$378/7*6,0)+ROUNDUP('cronograma unit.'!$E$380/7*6,0))>=30/7*6,ROUNDUP('cronograma unit.'!$E$378/7*6,0),IF($O$12=1,ROUNDUP('cronograma unit.'!$E$378/7*6,0),IF($N$12=1,ROUNDUP(30/7*6,0),0))),1000))) -> 88 | V78: =G77 -> 70 | W78: =IF(V78=0,0,IF(V78<90,IF(((ROUNDUP('cronograma unit.'!$E$378/7*6,0)+ROUNDUP('cronograma unit.'!$E$380/7*6,0)))/('cronograma unit.'!$E$381+1)>=30/7*6,ROUNDUP('cronograma unit.'!$E$378/7*6,0),IF($O$10=1,ROUNDUP('cronograma unit.'!$E$378/7*6,0),IF($N$10=1,ROUNDUP(30/7*6,0)*('cronograma unit.'!$E$381+1),0))),IF(V78>=90,IF(((ROUNDUP('cronograma unit.'!$E$378/7*6,0)+ROUNDUP('cronograma unit.'!$E$380/7*6,0)))/('cronograma unit.'!$E$381+1)>=30/7*6,ROUNDUP('cronograma unit.'!$E$378/7*6,0),IF($O$12=1,ROUNDUP('cronograma unit.'!$E$378/7*6,0),IF($N$12=1,ROUNDUP(30/7*6,0)*('cronograma unit.'!$E$381+1),0)))))) -> 88
D79: =IF(I79=0,0,"GUINDASTE G1 À DISPOSIÇÃO=") -> 0 | G79: =IF(I79=0,0,$F$22) -> 0 | H79: ton | I79: =IF(L73="X",T76,IF(I73="X",W76,0)) -> 0 | J79: dias (seg a sab ) | S79: mob /desmob | T79: =IF(N10+O10+N12+O12=0,0,1) -> 1 | V79: mob /desmob | W79: =IF(N10+O10+N12+O12=0,0,'cronograma unit.'!$E$381+1) -> 1
O80: =IF($D$127<>0,1,0) -> 0
D81: =IF(I77=0,0,"MOBILIZAÇÃO G1=") -> MOBILIZAÇÃO G1= | G81: =IF(I81=0,0,$F$22) -> 70 | H81: ton | I81: =IF('cronograma unit.'!$E$381>0,IF(I73="X",W79,IF(L73="x",T79,0)),T79) -> 1 | J81: mobilização / desmobiliz.
O82: =IF($D$127<>0,1,0) -> 0
C83: =IF(ENTRADAS!D912="x","CASO SOMENTE COBERTURA",0) -> 0 | F83: =IF(C85=0,0,1) -> 0 | G83: =IF(I86=0,0,1) -> 0 | H83: =IF(L86=0,0,1) -> 0 | I83: =IF(F83+G83+H83=1,"OBRIGATÓRIO DEFINIÇÃO, SIM OU NÃO !",0) -> 0 | N83: =IF(I83<>0,1,0) -> 0 | O83: =IF($D$127<>0,1,0) -> 0
O84: =IF($D$127<>0,1,0) -> 0
C85: =IF(ENTRADAS!D912="x",IF('cronograma unit.'!$E$386=0,0,IF('cronograma unit.'!$E$386=1,"Analisando o cronograma, existe "&'cronograma unit.'!$E$386&" intervalo de "&'cronograma unit.'!$E$385/'cronograma unit.'!$E$386&" dias entre as montagem de coberturas. ","Analisando o cronograma, existem "&'cronograma unit.'!$E$386&" intervalos de "&'cronograma unit.'!$E$385/'cronograma unit.'!$E$386&" dias em média entre as montagem de coberturas. ")),0) -> 0 | O85: =IF($D$127<>0,1,0) -> 0
C86: =IF(ENTRADAS!D912="x",IF('cronograma unit.'!$E$386=0,0,IF('cronograma unit.'!$E$386=1," Considerar que o guindaste será desmobilizado neste intervalo ?"," Considerar que o guindaste será desmobilizado nestes intervalos ?")),0) -> 0 | J86: =IF(ENTRADAS!D912="x",IF('cronograma unit.'!$E$386=0,0,"sim"),0) -> 0 | M86: =IF(ENTRADAS!D912="x",IF('cronograma unit.'!$E$386=0,0,"não"),0) -> 0 | O86: =IF($D$127<>0,1,0) -> 0
O87: =IF($D$127<>0,1,0) -> 0 | S87: NÃO DESMOB. | V87: SIM DESMOB.
O88: =IF($D$127<>0,1,0) -> 0 | S88: a disposição | V88: a disposição
C89: =IF(ENTRADAS!D912="x",IF(ENTRADAS!$C$395="x","MONTAGEM SEQUENCIAL:",IF(ENTRADAS!$C$397="x","MONTAGEM NÃO SEQUENCIAL:",0)),0) -> 0 | F89: =IF(ENTRADAS!D912="x",IF(SUM($N$10:$O$12)>0,0,"VOLTE E DEFINA O TEMPO MÍNIMO DE GUINDASTE ACIMA !"),0) -> 0 | O89: =IF($D$127<>0,1,0) -> 0 | S89: =S91 -> 0 | T89: =IF(S89=0,0,IF(S89<90,IF((ROUNDUP('cronograma unit.'!$E$383/7*6,0)+ROUNDUP('cronograma unit.'!$E$385/7*6,0))>=30/7*6,ROUNDUP('cronograma unit.'!$E$385/7*6,0),IF($O$10=1,ROUNDUP('cronograma unit.'!$E$385/7*6,0),IF($N$10=1,ROUNDUP((30/7*6),0)-ROUNDUP('cronograma unit.'!$E$383/7*6,0),0))),IF(S89>=90,IF((ROUNDUP('cronograma unit.'!$E$383/7*6,0)+ROUNDUP('cronograma unit.'!$E$385/7*6,0))>=30/7*6,ROUNDUP('cronograma unit.'!$E$385/7*6,0),IF($O$12=1,ROUNDUP('cronograma unit.'!$E$385/7*6,0),IF($N$12=1,ROUNDUP((30/7*6),0)-ROUNDUP('cronograma unit.'!$E$383/7*6,0),0)))))) -> 0 | V89: =V91 -> 0 | W89: =0 -> 0
D90: =IF(ENTRADAS!D912="x","GUINDASTE COBERT. TRABALHANDO=",0) -> 0 | G90: =IF(ENTRADAS!D912="X",IF(GUINDASTE!E62="X",IF(SUM(LAJES!AO154:AO158)>=CÁLCULOS!O279,SUM(LAJES!AO154:AO158),CÁLCULOS!O279),IF(GUINDASTE!E57>0,GUINDASTE!E57,SUM(LAJES!AO154:AO158))),0) -> 0 | H90: =IF(ENTRADAS!D912="x","ton",0) -> 0 | I90: =IF(ENTRADAS!D912="x",IF('cronograma unit.'!$E$386>0,IF(L86="X",T91,IF(I86="X",W91,0)),T91),0) -> 0 | J90: =IF(ENTRADAS!D912="x","dias (seg a sab )",0) -> 0 | O90: =IF($D$127<>0,1,0) -> 0 | S90: trabalhando | V90: trabalhando
O91: =IF($D$127<>0,1,0) -> 0 | S91: =G90 -> 0 | T91: =IF(S91=0,0,IF(S91<90,IF((ROUNDUP('cronograma unit.'!$E$383/7*6,0)+ROUNDUP('cronograma unit.'!$E$385/7*6,0))>=30/7*6,ROUNDUP('cronograma unit.'!$E$383/7*6,0),IF($O$10=1,ROUNDUP('cronograma unit.'!$E$383/7*6,0),IF($N$10=1,ROUNDUP(30/7*6,0),0))),IF(S91>=90,IF((ROUNDUP('cronograma unit.'!$E$383/7*6,0)+ROUNDUP('cronograma unit.'!$E$385/7*6,0))>=30/7*6,ROUNDUP('cronograma unit.'!$E$383/7*6,0),IF($O$12=1,ROUNDUP('cronograma unit.'!$E$383/7*6,0),IF($N$12=1,ROUNDUP(30/7*6,0),0)))))) -> 0 | V91: =G90 -> 0 | W91: =IF(V91=0,0,IF(V91<90,IF(((ROUNDUP('cronograma unit.'!$E$383/7*6,0)+ROUNDUP('cronograma unit.'!$E$385/7*6,0)))/('cronograma unit.'!$E$386+1)>=30/7*6,ROUNDUP('cronograma unit.'!$E$383/7*6,0),IF($O$10=1,ROUNDUP('cronograma unit.'!$E$383/7*6,0),IF($N$10=1,ROUNDUP(30/7*6,0)*('cronograma unit.'!$E$386+1),0))),IF(V91>=90,IF(((ROUNDUP('cronograma unit.'!$E$383/7*6,0)+ROUNDUP('cronograma unit.'!$E$385/7*6,0)))/('cronograma unit.'!$E$386+1)>=30/7*6,ROUNDUP('cronograma unit.'!$E$383/7*6,0),IF($O$12=1,ROUNDUP('cronograma unit.'!$E$383/7*6,0),IF($N$12=1,ROUNDUP(30/7*6,0)*('cronograma unit.'!$E$386+1),0)))))) -> 0
D92: =IF(ENTRADAS!D912="x",IF(I92=0,0,"GUINDASTE COBERT. À DISPOSIÇÃO="),0) -> 0 | G92: =IF(I92=0,0,G90) -> 0 | H92: =IF(ENTRADAS!D912="x","ton",0) -> 0 | I92: =IF(L86="X",T89,IF(I86="X",W89,0)) -> 0 | J92: =IF(ENTRADAS!D912="x","dias (seg a sab )",0) -> 0 | O92: =IF($D$127<>0,1,0) -> 0 | S92: mob /desmob | T92: =IF(N10+O10+N12+O12=0,0,1) -> 1 | V92: mob /desmob | W92: =IF(N10+O10+N12+O12=0,0,'cronograma unit.'!$E$386+1) -> 1
O93: =IF($D$127<>0,1,0) -> 0
D94: =IF(ENTRADAS!D912="x",IF(I90=0,0,"MOBILIZAÇÃO GUINDASTE COBERT.="),0) -> 0 | G94: =IF(I94=0,0,G90) -> 0 | H94: =IF(ENTRADAS!D912="x","ton",0) -> 0 | I94: =IF(ENTRADAS!D912="x",IF('cronograma unit.'!$E$386>0,IF(I86="X",W92,IF(L86="x",T92,0)),T92),0) -> 0 | J94: =IF(ENTRADAS!D912="x","mobilização / desmobiliz.",0) -> 0 | O94: =IF($D$127<>0,1,0) -> 0
O95: =IF($D$127<>0,1,0) -> 0
C96: =IF(ENTRADAS!D912="x","CASO PAREDES E COBERTURA ( considerado o maior guindaste )",0) -> 0 | F96: =IF(C98=0,0,1) -> 0 | G96: =IF(I99=0,0,1) -> 0 | H96: =IF(L99=0,0,1) -> 0 | I96: =IF(F96+G96+H96=1,"OBRIGATÓRIO DEFINIÇÃO, SIM OU NÃO !",0) -> 0 | N96: =IF(I96<>0,1,0) -> 0 | O96: =IF($D$127<>0,1,0) -> 0
O97: =IF($D$127<>0,1,0) -> 0
C98: =IF(ENTRADAS!D912="x",IF('cronograma unit.'!$E$376=0,0,IF('cronograma unit.'!$E$376=1,"Analisando o cronograma, existe "&'cronograma unit.'!$E$376&" intervalo de "&'cronograma unit.'!$E$375/'cronograma unit.'!$E$376&" dias entre as montagem de paredes / coberturas. ","Analisando o cronograma, existem "&'cronograma unit.'!$E$376&" intervalos de "&'cronograma unit.'!$E$375/'cronograma unit.'!$E$376&" dias em média entre as montagem de paredes / coberturas. ")),0) -> 0 | O98: =IF($D$127<>0,1,0) -> 0
C99: =IF(ENTRADAS!D912="x",IF('cronograma unit.'!$E$376=0,0,IF('cronograma unit.'!$E$376=1," Considerar que o guindaste será desmobilizado neste intervalo ?"," Considerar que o guindaste será desmobilizado nestes intervalos ?")),0) -> 0 | J99: =IF(ENTRADAS!D912="x",IF('cronograma unit.'!$E$376=0,0,IF('cronograma unit.'!$E$376=1,"sim","sim")),0) -> 0 | M99: =IF(ENTRADAS!D912="x",IF('cronograma unit.'!$E$376=0,0,IF('cronograma unit.'!$E$376=1,"não","não")),0) -> 0 | O99: =IF($D$127<>0,1,0) -> 0
O100: =IF($D$127<>0,1,0) -> 0 | S100: NÃO DESMOB. | V100: SIM DESMOB.
O101: =IF($D$127<>0,1,0) -> 0 | S101: a disposição | V101: a disposição
C102: =IF(ENTRADAS!D912="x",IF(ENTRADAS!$C$395="x","MONTAGEM SEQUENCIAL:",IF(ENTRADAS!$C$397="x","MONTAGEM NÃO SEQUENCIAL:",0)),0) -> 0 | F102: =IF(ENTRADAS!D912="x",IF(SUM($N$10:$O$12)>0,0,"VOLTE E DEFINA O TEMPO MÍNIMO DE GUINDASTE ACIMA !"),0) -> 0 | O102: =IF($D$127<>0,1,0) -> 0 | S102: =S104 -> 0 | T102: =IF(S102=0,0,IF(S102<90,IF((ROUNDUP('cronograma unit.'!$E$373/7*6,0)+ROUNDUP('cronograma unit.'!$E$375/7*6,0))>=30/7*6,ROUNDUP('cronograma unit.'!$E$375/7*6,0),IF($O$10=1,ROUNDUP('cronograma unit.'!$E$375/7*6,0),IF($N$10=1,ROUNDUP((30/7*6),0)-ROUNDUP('cronograma unit.'!$E$373/7*6,0),0))),IF(S102>=90,IF((ROUNDUP('cronograma unit.'!$E$373/7*6,0)+ROUNDUP('cronograma unit.'!$E$375/7*6,0))>=30/7*6,ROUNDUP('cronograma unit.'!$E$375/7*6,0),IF($O$12=1,ROUNDUP('cronograma unit.'!$E$375/7*6,0),IF($N$12=1,ROUNDUP((30/7*6),0)-ROUNDUP('cronograma unit.'!$E$373/7*6,0),0)))))) -> 0 | V102: =V104 -> 0 | W102: =0 -> 0
D103: =IF(ENTRADAS!D912="x","GUIND. G1 (parede/cob.) TRABALHANDO =",0) -> 0 | G103: =IF(ENTRADAS!D912="x",IF(CÁLCULOS!O279>=SUM(LAJES!AO154:AO158),CÁLCULOS!O279,IF(SUM(LAJES!AO154:AO158)>CÁLCULOS!O279,SUM(LAJES!AO154:AO158))),0) -> 0 | H103: =IF(ENTRADAS!D912="x","ton",0) -> 0 | I103: =IF(ENTRADAS!D912="x",IF('cronograma unit.'!$E$376>0,IF(L99="X",T104,IF(I99="X",W104,0)),T104),0) -> 0 | J103: =IF(ENTRADAS!D912="x","dias (seg a sab )",0) -> 0 | O103: =IF($D$127<>0,1,0) -> 0 | S103: trabalhando | V103: trabalhando
O104: =IF($D$127<>0,1,0) -> 0 | S104: =G103 -> 0 | T104: =IF(S104=0,0,IF(S104<90,IF((ROUNDUP('cronograma unit.'!$E$373/7*6,0)+ROUNDUP('cronograma unit.'!$E$375/7*6,0))>=30/7*6,ROUNDUP('cronograma unit.'!$E$373/7*6,0),IF($O$10=1,ROUNDUP('cronograma unit.'!$E$373/7*6,0),IF($N$10=1,ROUNDUP(30/7*6,0),0))),IF(S104>=90,IF((ROUNDUP('cronograma unit.'!$E$373/7*6,0)+ROUNDUP('cronograma unit.'!$E$375/7*6,0))>=30/7*6,ROUNDUP('cronograma unit.'!$E$373/7*6,0),IF($O$12=1,ROUNDUP('cronograma unit.'!$E$373/7*6,0),IF($N$12=1,ROUNDUP(30/7*6,0),0)))))) -> 0 | V104: =G103 -> 0 | W104: =IF(V104=0,0,IF(V104<90,IF(((ROUNDUP('cronograma unit.'!$E$373/7*6,0)+ROUNDUP('cronograma unit.'!$E$375/7*6,0)))/('cronograma unit.'!$E$386+1)>=30/7*6,ROUNDUP('cronograma unit.'!$E$373/7*6,0),IF(O$10=1,ROUNDUP('cronograma unit.'!$E$373/7*6,0),IF($N$10=1,ROUNDUP(30/7*6,0)*('cronograma unit.'!$E$376+1),0))),IF(V104>=90,IF(((ROUNDUP('cronograma unit.'!$E$373/7*6,0)+ROUNDUP('cronograma unit.'!$E$375/7*6,0)))/('cronograma unit.'!$E$386+1)>=30/7*6,ROUNDUP('cronograma unit.'!$E$373/7*6,0),IF($O$12=1,ROUNDUP('cronograma unit.'!$E$373/7*6,0),IF($N$12=1,ROUNDUP(30/7*6,0)*('cronograma unit.'!$E$376+1),0)))))) -> 0
D105: =IF(ENTRADAS!D912="x",IF(I105=0,0,"GUIND. G1 ( parede/cob.) À DISPOSIÇÃO="),0) -> 0 | G105: =IF(I105=0,0,IF(ENTRADAS!D912="x",IF(CÁLCULOS!O279>=SUM(LAJES!AO154:AO158),CÁLCULOS!O279,IF(SUM(LAJES!AO154:AO158)>CÁLCULOS!O279,SUM(LAJES!AO154:AO158))),0)) -> 0 | H105: =IF(ENTRADAS!D912="x","ton",0) -> 0 | I105: =IF(L99="X",T102,IF(I99="X",W102,0)) -> 0 | J105: =IF(ENTRADAS!D912="x","dias (seg a sab )",0) -> 0 | O105: =IF($D$127<>0,1,0) -> 0 | S105: mob /desmob | T105: =IF(N10+O10+N12+O12=0,0,1) -> 1 | V105: mob /desmob | W105: =IF(N10+O10+N12+O12=0,0,'cronograma unit.'!$E$386+1) -> 1
O106: =IF($D$127<>0,1,0) -> 0
D107: =IF(ENTRADAS!D912="x",IF(I103=0,0,"MOBILIZAÇÃO G1 (parede/cob.)="),0) -> 0 | G107: =IF(I107=0,0,IF(ENTRADAS!D912="x",IF(CÁLCULOS!O279>=SUM(LAJES!AO154:AO158),CÁLCULOS!O279,IF(SUM(LAJES!AO154:AO158)>CÁLCULOS!O279,SUM(LAJES!AO154:AO158))),0)) -> 0 | H107: =IF(ENTRADAS!D912="x","ton",0) -> 0 | I107: =IF(ENTRADAS!D912="x",IF('cronograma unit.'!$E$376>0,IF(I99="X",W105,IF(L99="x",T105,0)),T105),0) -> 0 | J107: =IF(ENTRADAS!D912="x","dias (seg a sab )",0) -> 0 | O107: =IF($D$127<>0,1,0) -> 0 | S107: percetual parede= | U107: ='cronograma unit.'!E378/'cronograma unit.'!E373 -> 1
O108: =IF($D$127<>0,1,0) -> 0 | S108: percentual cobertura=
O109: =IF($D$127<>0,1,0) -> 0
O110: =IF($D$127<>0,1,0) -> 0
C111: ÍTEM | D111: CASOS | G111: CUSTO | O111: =IF($D$127<>0,1,0) -> 0
G112: G1 trabalhando | I112: G1 à disposição | J112: G1 mob. / desmob. | K112: TOTAL G1 | O112: =IF($D$127<>0,1,0) -> 0
O113: =IF($D$127<>0,1,0) -> 0
C114: A | D114: CASO SOMENTE PAREDES | G114: =IF(G77=0,0,I77*VLOOKUP(G77,INSUMOS!$V$56:$Y$63,2,0)) -> 325600 | I114: =IF(G79=0,0,I79*VLOOKUP(G79,INSUMOS!$V$56:$Y$63,4,0)) -> 0 | J114: =IF(G81=0,0,I81*VLOOKUP(G81,INSUMOS!$V$56:$Y$63,3,0)) -> 5000 | K114: =G114+I114+J114 -> 330600 | O114: =IF($D$127<>0,1,0) -> 0
O115: =IF($D$127<>0,1,0) -> 0
C116: =IF(ENTRADAS!D912="x","B",0) -> 0 | D116: =IF(ENTRADAS!D912="x","CASO SOMENTE COBERTURA",0) -> 0 | G116: =IF(G90=0,0,I90*VLOOKUP(G90,INSUMOS!$V$56:$Y$63,2,0)) -> 0 | I116: =IF(G92=0,0,I92*VLOOKUP(G92,INSUMOS!$V$56:$Y$63,4,0)) -> 0 | J116: =IF(G94=0,0,I94*VLOOKUP(G94,INSUMOS!$V$56:$Y$63,3,0)) -> 0 | K116: =G116+I116+J116 -> 0 | O116: =IF($D$127<>0,1,0) -> 0
O117: =IF($D$127<>0,1,0) -> 0
C118: =IF(ENTRADAS!D912="x","C",0) -> 0 | D118: =IF(ENTRADAS!D912="x","CASO PAREDES E COBERTURA",0) -> 0 | G118: =IF(G103=0,0,I103*VLOOKUP(G103,INSUMOS!$V$56:$Y$63,2,0)) -> 0 | I118: =IF(G105=0,0,I105*VLOOKUP(G105,INSUMOS!$V$56:$Y$63,4,0)) -> 0 | J118: =IF(G107=0,0,I107*VLOOKUP(G107,INSUMOS!$V$56:$Y$63,3,0)) -> 0 | K118: =G118+I118+J118 -> 0 | O118: =IF($D$127<>0,1,0) -> 0
O119: =IF($D$127<>0,1,0) -> 0
D120: ANALISE: CRONOGRAMA, DESMOBILIZAÇÃO, MÍNIMO de 30 dias e ESCOLHA A MELHOR OPÇÃO: | O120: =IF($D$127<>0,1,0) -> 0
O121: =IF($D$127<>0,1,0) -> 0
O122: =IF($D$127<>0,1,0) -> 0
C123: =IF(AND(ENTRADAS!F22>0,ENTRADAS!D912=0),1,IF(ENTRADAS!D912="x",IF(D123="X",1,0),0)) -> 1 | D123: x | E123: =IF(ENTRADAS!D912="x","A + B =","A =") -> A = | G123: =IF(D123=0,0,K114+K116) -> 330600 | I123: marcar "X" e anotar valores. Depois comparar os dois e decidir qual opção é melhor. | O123: =IF($D$127<>0,1,0) -> 0
O124: =IF($D$127<>0,1,0) -> 0
C125: =IF(D125="X",1,0) -> 0 | E125: =IF(AND(D123="X",D125="X"),"tire o X da opção anterior",IF(ENTRADAS!D912="x","C =",0)) -> 0 | G125: =IF(AND(D123="X",D125="X"),"*******",IF(D125=0,0,K118)) -> 0 | O125: =IF($D$127<>0,1,0) -> 0
O126: =IF($D$127<>0,1,0) -> 0
D127: =IF('cronograma unit.'!$E$381=0,0,IF(AND(C125=1,'cronograma unit.'!$E$380/'cronograma unit.'!$E$381>0),"******Alerta !!! Volte na linha 72 e 73 e confirme !!!",0)) -> 0 | O127: =IF($D$127<>0,1,0) -> 0
I128: =IF($D$127<>0,1,0) -> 0 | J128: =IF($D$127<>0,1,0) -> 0 | K128: =IF($D$127<>0,1,0) -> 0 | L128: =IF($D$127<>0,1,0) -> 0 | M128: =IF($D$127<>0,1,0) -> 0 | N128: =IF($D$127<>0,1,0) -> 0 | O128: =IF($D$127<>0,1,0) -> 0
D130: =IF(ENTRADAS!D912="X",IF(C123+C125=0,0,IF(D123="x","As montagens de paredes e coberturas serão independentes uma da outra.","As montagens de paredes e coberturas serão em conjunto uma com a outra.")),IF(ENTRADAS!F22>0,0,0)) -> 0
D132: =IF(AND(ENTRADAS!D912="x",ENTRADAS!F22>0),0,IF(C123+C125=0,0,IF(D123="x",IF(E62="X","Como as montagens de paredes e coberturas serão independentes uma da outra, volte na célula E46 e reavalie a sua decisão. Em seguida volte na tabela acima e a analise outra vez.",0),0))) -> 0

Sheet X MPa 
C2: COMPOSIÇÃO DE PREÇO DE CONCRETO FABRICAÇÃO NA FORTANKS
B12: INSUMOS: | C12: UNID. | E12: PREÇO MATERIAL | F12: FRETE | G12: SERVIÇO
B13: CIMENTO CP3 | C13: tonelada | E13: 483 | F13: =36*1.1 -> 39.6 | G13: -
B14: CIMENTO CP5 | C14: tonelada | E14: 722.85 | G14: -
B15: BRITA 0 | C15: tonelada | E15: 128 | F15: =16*1.1 -> 17.6 | G15: -
B16: AREIA MÉDIA | C16: m³ | E16: 198.28 | G16: -
B17: SÍLICA ATIVA | C17: kg | E17: 1.58 | G17: -
B18: ADITIVO SUPER | C18: kg | E18: 11.05 | F18: =0.75*1.1 -> 0.825 | G18: -
B19: DIESEL | C19: Litro | E19: 8.5 | F19: - | G19: -
B20: SERVIÇO VILAMIX | C20: m³ | E20: - | F20: -
B22: TRAÇO À UTILIZAR: | C22: X
A23: =C23 -> 0 | B23: ='tabela traços'!C3 -> 30 MPa 24 h | D23: =IF(C23=0,0,1) -> 0
A24: =C24 -> 0 | B24: ='tabela traços'!C4 -> 28 MPa 24 h | D24: =IF(C24=0,0,1) -> 0
A25: =C25 -> 0 | B25: ='tabela traços'!C5 -> 25 MPa 24 h | D25: =IF(C25=0,0,1) -> 0
A26: =C26 -> x | B26: ='tabela traços'!C6 -> 20 MPa 24 h | C26: x | D26: =IF(C26=0,0,1) -> 1
A27: =C27 -> 0 | B27: ='tabela traços'!C7 -> 15 MPa 24 h | D27: =IF(C27=0,0,1) -> 0
B28: ='tabela traços'!C8 -> 10 MPa 24 h | D28: =IF(C28=0,0,1) -> 0
B29: ='tabela traços'!C9 -> 0 | D29: =IF(C29=0,0,1) -> 0
B30: ='tabela traços'!C10 -> 0 | D30: =IF(C30=0,0,1) -> 0
B32: =IF(SUM($D$23:$D$27)=0,0,"PREÇO POR m³ TRAÇO ref. Umidade da areia à 6%:") -> PREÇO POR m³ TRAÇO ref. Umidade da areia à 6%: | F32: =IF(SUM($D$23:$D$27)=0,0,VLOOKUP($C$22,$A$23:$B$27,2,0)) -> 20 MPa 24 h | I32: DATA: | J32: 44722
B34: Insumo | C34: unid. | D34: consumo /m³ | E34: preço unit. | F34: valor /m³ | H34: frete/ t | I34: material/ t | M34: % ICMS
B35: cimento CP3 | C35: t | D35: =IF(SUM($D$23:$D$30)=0,0,VLOOKUP($C$22,'tabela traços'!$A$3:$M$15,5,0)) -> 0.343 | E35: =IF(SUM($D$23:$D$30)=0,0,H35+I35) -> 522.6 | F35: =D35*E35 -> 179.2518 | H35: =F13 -> 39.6 | I35: =E13 -> 483 | J35: CP3 | M35: 0.17 | N35: =M35*F35 -> 30.472806
B36: cimento CP5 | C36: t | D36: =IF(SUM($D$23:$D$30)=0,0,VLOOKUP($C$22,'tabela traços'!$A$3:$M$15,6,0)) -> 0.184 | E36: =IF(SUM($D$23:$D$30)=0,0,E14) -> 722.85 | F36: =D36*E36 -> 133.0044 | M36: 0.07 | N36: =M36*F36 -> 9.310308
H37: frete/ t | I37: material/ t
B38: brita zero | C38: t | D38: =IF(SUM($D$23:$D$30)=0,0,VLOOKUP($C$22,'tabela traços'!$A$3:$M$15,7,0)) -> 0.859 | E38: =IF(SUM($D$23:$D$30)=0,0,H38+I38) -> 145.6 | F38: =D38*E38 -> 125.0704 | H38: =F15 -> 17.6 | I38: =E15 -> 128 | J38: BRITA ZERO | M38: 0.17 | N38: =M38*F38 -> 21.261968
H40: frete/ m3 | I40: material/m3 | J40: peso espec. (t/m³)
B41: areia média (umidade 6,4%) | C41: t | D41: =IF(SUM($D$23:$D$30)=0,0,VLOOKUP($C$22,'tabela traços'!$A$3:$M$15,8,0)) -> 0.846 | E41: =IF(SUM($D$23:$D$30)=0,0,(H41+I41)/J41) -> 123.925 | F41: =D41*E41 -> 104.84055 | H41: =F16 -> 0 | I41: =E16 -> 198.28 | J41: 1.6 | K41: AREIA | M41: 0.17 | N41: =M41*F41 -> 17.822894
B42: sílica | C42: kg | D42: =IF(SUM($D$23:$D$30)=0,0,VLOOKUP($C$22,'tabela traços'!$A$3:$M$15,11,0)) -> 30.77 | E42: =IF(SUM($D$23:$D$30)=0,0,E17+F17) -> 1.58 | F42: =D42*E42 -> 48.6166 | M42: 0.07 | N42: =M42*F42 -> 3.403162
B43: água | C43: litro | D43: =IF(SUM($D$23:$D$30)=0,0,VLOOKUP($C$22,'tabela traços'!$A$3:$M$15,10,0)) -> 144 | F43: =D43*E43 -> 0 | H43: frete/ kg | I43: material/kg
B44: aditivo super | C44: kg | D44: =IF(SUM($D$23:$D$30)=0,0,VLOOKUP($C$22,'tabela traços'!$A$3:$M$15,9,0)) -> 3.689 | E44: =IF(SUM($D$23:$D$30)=0,0,H44+I44) -> 11.875 | F44: =D44*E44 -> 43.806875 | H44: =F18 -> 0.825 | I44: =E18 -> 11.05 | J44: SUPER | M44: 0.07 | N44: =M44*F44 -> 3.0664813
B45: aditivo poli | C45: kg | F45: =D45*E45 -> 0 | M45: 0.07 | N45: =M45*F45 -> 0
B46: diesel | C46: litros | D46: =IF(SUM($D$23:$D$30)=0,0,VLOOKUP($C$22,'tabela traços'!$A$3:$M$15,12,0)) -> 2 | E46: =IF(SUM($D$23:$D$30)=0,0,E19) -> 8.5 | F46: =D46*E46 -> 17 | M46: 0.17 | N46: =M46*F46 -> 2.89
B47: serviço Vilamix | C47: m³ | E47: =IF(SUM($D$23:$D$30)=0,0,G20) -> 0 | F47: =D47*E47 -> 0
D50: TOTAL INSUMOS 1= | F50: =SUM(F35:F49) -> 651.59062 | G50: /m³ | M50: média pond.
M51: =N51/F50 -> 0.13540345 | N51: =SUM(N35:N46) -> 88.227619
B52: para o 30 MPa | C52: --------- | G52: /m³
B56: DEFINIÇÃO DA USINA DE CONCRETO: | I56: PARA DEFINIR VALOR m³
B59: produção média de concreto por mês= | E59: 400 | F59: m³/mês | H59: copiar valor abaixo e colar "só valores" em A.
B61: índice (proporcional ao volume real)= | E61: =IF(E59=0,0,I75/E59*100) -> 223.17072 | F61: % | H61: depois marcar "X" antes de B,
H63: copiar valor abaixo e colar "só valores" em B.
B64: DESCRIÇÃO | C64: UNID. | E64: Valor unit. | F64: índ/m³ | H64: a diferença será o custo total da equipe da central
B65: RETRO ESCAVADEIRA | C65: DIÁRIA | E65: 1300 | F65: =IF(E59=0,0,E65*25/E59) -> 81.25 | J65: de concreto.
B66: CAMINHÃO BETONEIRA | C66: DIÁRIA | E66: =22000*2/25 -> 1760 | F66: =IF(E59=0,0,E66*25/E59) -> 110 | I66: =INSUMOS!Q195+INSUMOS!Q236 -> 521069.54
B67: OPERADOR DE CENTRAL | C67: MÊS | E67: =IF(D72="X",0,3745*2.26) -> 8463.7 | F67: TRANFORMADO EM SOLDADOR= | J67: =(E67/(ENTRADAS!$F$751*2.26)) -> 1.5417867 | K67: UNID.
B68: MOTORISTA BETONEIRA | C68: MÊS | E68: =IF(D72="X",0,1*2737*2.26) -> 6185.62 | F68: TRANFORMADO EM SOLDADOR= | J68: =(E68/(ENTRADAS!$F$751*2.26)) -> 1.1268012 | K68: UNID.
E71: A | F71: com equipe da usina= | I71: 521069.54
E72: B | F72: sem equipe da usina= | I72: 450349.8
H73: diferença= | I73: =I71-I72 -> 70719.745 | J73: valor da eq. Usina +
D74: =IF(D72="X","NA SEQUÊNCIA DELETAR O X",0) -> 0 | J74: vale transp +refeições
D75: volume de concreto total do tanque= | I75: =INSUMOS!K154+INSUMOS!K249 -> 892.68287 | J75: m³
D76: capacidade de produção no prazo do tanque= | I76: =('cronograma unit.'!F23*ENTRADAS!F22/30)*E59 -> 1346.6667 | J76: m³
D77: valor da equipe por /m³ = | I77: =I73/I76 -> 52.514662 | J77: R$/m³
D79: VALOR DOS INSUMOS 1= | I79: =IF(ENTRADAS!I15=0,0,F50) -> 651.59062 | J79: R$/m³
D81: VALOR RETROESCAVADEIRA= | I81: =F65 -> 81.25 | J81: R$/m³
D83: VALOR DOS CAMINHÕES BETONEIRA= | I83: =F66 -> 110 | J83: R$/m³
D85: VALOR DA MÃO-OBRA NA USINA= | I85: =I77 -> 52.514662 | J85: R$/m³
D87: VALOR FINAL DO CONCRETO = | I87: =SUM(I79:I85) -> 895.35529 | K87: /m³

Sheet INSUMOS
C1: X | F1: SISTEMA SC-10 e SC-14 ORÇAMENTO INSUMOS E PREÇOS DE CUSTO | Q1: DATA: | R1: =CÁLCULOS!O1 -> 45638 | V1: X
Q2: REVISÃO: | R2: =CÁLCULOS!O2 -> 3
F3: CLIENTE: | G3: =CÁLCULOS!F3 -> Passarelli | Q3: LOCAL:
F4: OBRA: | G4: =CÁLCULOS!F4 -> 12 tqs Nereda | Q4: =FECHAMENTO!M5 -> São Paulo - Tatuapé - SP
E12: COTAÇÃO DO EURO= | G12: 6.15
D14: ANTES DE FINALIZAR FAÇA UMA CONFERÊNCIA NOS ITENS ABAIXO, INDO NESTES ITENS E VERIFICANDO SE FOI LANÇADO OS PREÇOS
E15: UNITÁRIOS OU ALTERAÇÃO DE QUANTIDADE ( CASO ALGUM INSUMO REALMENTE NÃO PRECISAR DE PREÇO MARCAR "X" NO ÍTEM ) :
D17: coluna/ÍTEM | E17: CONFERIDO ? | I17: col./ÍTEM | J17: CONFERIDO ?
C18: =VLOOKUP(D18,$B$40:$AC$277,16,0) -> 750 | D18: Q15 | F18: =IF(C18>0,"SIM",IF(E18="x","SIM","NÃO")) -> SIM | H18: =VLOOKUP(I18,$B$40:$AC$277,16,0) -> 2300 | I18: Q67 | K18: =IF(H18>0,"SIM",IF(J18="x","SIM","NÃO")) -> SIM
C19: =VLOOKUP(D19,$B$40:$AC$277,16,0) -> 2000 | D19: Q16 | F19: =IF(C19>0,"SIM",IF(E19="x","SIM","NÃO")) -> SIM | H19: =VLOOKUP(I19,$B$40:$AC$277,16,0) -> 180 | I19: Q69 | K19: =IF(H19>0,"SIM",IF(J19="x","SIM","NÃO")) -> SIM
C20: =VLOOKUP(D20,$B$40:$AC$277,16,0) -> 3700 | D20: Q17 | F20: =IF(C20>0,"SIM",IF(E20="x","SIM","NÃO")) -> SIM | H20: =VLOOKUP(I20,$B$40:$AC$277,16,0) -> 30 | I20: Q71 | K20: =IF(H20>0,"SIM",IF(J20="x","SIM","NÃO")) -> SIM
C21: =VLOOKUP(D21,$B$40:$AC$277,16,0) -> 0 | D21: Q18 | F21: =IF(C21>0,"SIM",IF(E21="x","SIM","NÃO")) -> NÃO | H21: =VLOOKUP(I21,$B$40:$AC$277,16,0) -> 35 | I21: Q72 | K21: =IF(H21>0,"SIM",IF(J21="x","SIM","NÃO")) -> SIM
C22: =VLOOKUP(D22,$B$40:$AC$277,16,0) -> 0 | D22: Q19 | F22: =IF(C22>0,"SIM",IF(E22="x","SIM","NÃO")) -> NÃO | H22: =VLOOKUP(I22,$B$40:$AC$277,16,0) -> 35 | I22: Q73 | K22: =IF(H22>0,"SIM",IF(J22="x","SIM","NÃO")) -> SIM
C23: =VLOOKUP(D23,$B$40:$AC$277,16,0) -> 5000 | D23: Q20 | F23: =IF(C23>0,"SIM",IF(E23="x","SIM","NÃO")) -> SIM | H23: =VLOOKUP(I23,$B$40:$AC$277,16,0) -> 7.5 | I23: Q74 | K23: =IF(H23>0,"SIM",IF(J23="x","SIM","NÃO")) -> SIM
C24: =VLOOKUP(D24,$B$40:$AC$277,16,0) -> 0 | D24: Q21 | F24: =IF(C24>0,"SIM",IF(E24="x","SIM","NÃO")) -> NÃO | H24: =VLOOKUP(I24,$B$40:$AC$277,16,0) -> 7.5 | I24: Q75 | K24: =IF(H24>0,"SIM",IF(J24="x","SIM","NÃO")) -> SIM
C25: =VLOOKUP(D25,$B$40:$AC$277,16,0) -> 0 | D25: Q22 | F25: =IF(C25>0,"SIM",IF(E25="x","SIM","NÃO")) -> NÃO | H25: =VLOOKUP(I25,$B$40:$AC$277,16,0) -> 4 | I25: Q143 | K25: =IF(H25>0,"SIM",IF(J25="x","SIM","NÃO")) -> SIM
C26: =VLOOKUP(D26,$B$40:$AC$277,16,0) -> 2220 | D26: Q23 | F26: =IF(C26>0,"SIM",IF(E26="x","SIM","NÃO")) -> SIM | H26: =VLOOKUP(I26,$B$40:$AC$277,16,0) -> 41 | I26: Q144 | K26: =IF(H26>0,"SIM",IF(J26="x","SIM","NÃO")) -> SIM
C27: =VLOOKUP(D27,$B$40:$AC$277,16,0) -> 0 | D27: Q24 | F27: =IF(C27>0,"SIM",IF(E27="x","SIM","NÃO")) -> NÃO | H27: =VLOOKUP(I27,$B$40:$AC$277,16,0) -> 4.8 | I27: Q145 | K27: =IF(H27>0,"SIM",IF(J27="x","SIM","NÃO")) -> SIM
C28: =VLOOKUP(D28,$B$40:$AC$277,23,0) -> 10502 | D28: X25 | F28: =IF(C28>0,"SIM",IF(E28="x","SIM","NÃO")) -> SIM | H28: =VLOOKUP(I28,$B$40:$AC$277,16,0) -> 999.998 | I28: Q146 | K28: =IF(H28>0,"SIM",IF(J28="x","SIM","NÃO")) -> SIM
C29: =VLOOKUP(D29,$B$40:$AC$277,23,0) -> 10502 | D29: X26 | F29: =IF(C29>0,"SIM",IF(E29="x","SIM","NÃO")) -> SIM | I29: Q156 a Q157 | K29: =IF(H29>0,"SIM",IF(J29="x","SIM","NÃO")) -> NÃO
C30: =VLOOKUP(D30,$B$40:$AC$277,23,0) -> 0 | D30: X27 | F30: =IF(C30>0,"SIM",IF(E30="x","SIM","NÃO")) -> NÃO | I30: Q158 a Q170 | K30: =IF(H30>0,"SIM",IF(J30="x","SIM","NÃO")) -> NÃO
C31: =VLOOKUP(D31,$B$40:$AC$277,23,0) -> 0 | D31: X28 | F31: =IF(C31>0,"SIM",IF(E31="x","SIM","NÃO")) -> NÃO | I31: EURO | K31: =IF(H30>0,"SIM",IF(J31="x","SIM","NÃO")) -> NÃO | P31: verificar "AQUI" célula G12
C32: =VLOOKUP(D32,$B$40:$AC$277,23,0) -> 14002.667 | D32: X29 | F32: =IF(C32>0,"SIM",IF(E32="x","SIM","NÃO")) -> SIM | I32: LUCRO | K32: =IF(H31>0,"SIM",IF(J32="x","SIM","NÃO")) -> NÃO | P32: verificar na aba "FECHAMENTO" célula G17
C33: =VLOOKUP(D33,$B$40:$AC$277,16,0) -> 4.8 | D33: Q65 | F33: =IF(C33>0,"SIM",IF(E33="x","SIM","NÃO")) -> SIM | I33: INVESTIMENTO | K33: =IF(H32>0,"SIM",IF(J33="x","SIM","NÃO")) -> NÃO | P33: verificar na aba "FECHAMENTO" célula U34
C34: =VLOOKUP(D34,$B$40:$AC$277,16,0) -> 180 | D34: Q66 | F34: =IF(C34>0,"SIM",IF(E34="x","SIM","NÃO")) -> SIM | G34: =IF(G35=0,0,"informado ?") -> 0 | I34: FATURAMENTO | K34: =IF(H33>0,"SIM",IF(J34="x","SIM","NÃO")) -> NÃO | P34: verificar na aba "FECHAMENTO" célula H106 e l106
D35: =IF(FECHAMENTO!X115<>0,"informar faturamento direto FORTES",IF(FECHAMENTO!X98<>0,"informar faturamento direto para CLIENTE",0)) -> 0 | G35: =IF(D35=0,0,IF(C35>0,"SIM",IF(F35="x","SIM","NÃO"))) -> 0 | I35: ICMS / ISS | K35: =IF(H34>0,"SIM",IF(J35="x","SIM","NÃO")) -> NÃO | P35: verificar na aba "FECHAMENTO" célula D62 e I62
I36: % vendedor | K36: =IF(H32>0,"SIM",IF(J36="x","SIM","NÃO")) -> NÃO | P36: verificar na aba "FECHAMENTO" célula I87
C38: ítem | D38: MONTAGEM - MATERIAIS, FERRAM., EQUIPAM. e LOCAÇÕES | K38: QUANT. | O38: UNID. | Q38: Preço unit. | R38: Preço Total
C39: =IF(ENTRADAS!F21>4,"AS QUANTIDADES DOS INSUMOS SÃO PARA 4 TANQUES","AS QUANTIDADES DOS INSUMOS SÃO PARA "&ENTRADAS!F21&" TANQUES") -> AS QUANTIDADES DOS INSUMOS SÃO PARA 4 TANQUES | V39: PARAFUSO Escora | W39: preço unit.
B40: Q1 | C40: Q1 | D40: =CÁLCULOS!C233 -> CHAPA AÇO 500 x 300 x 3/16' | I40: percentual redução: | J40: 0.7 | K40: =CÁLCULOS!L233 -> 248 | O40: =CÁLCULOS!M233 -> unid. | Q40: =IF(K40=0,0,IF(J40>0,J40*CÁLCULOS!P233*Q159*2.7,CÁLCULOS!P233*Q159*2.7)) -> 62.4456 | R40: =K40*Q40 -> 15486.509 | V40: M16 x 1 1/2" | W40: 8 | AC40: =Q40 -> 62.4456
A41: cimento | B41: Q2 | C41: Q2 | D41: =CÁLCULOS!C234 -> CIMENTO PORTLAND ( SACO 50 kg ) | K41: =CÁLCULOS!L234 -> 22 | O41: =CÁLCULOS!M234 -> sacos | Q41: 40 | R41: =K41*Q41 -> 880 | V41: M16 x 1 3/4" | W41: 9 | AC41: =Q41 -> 40
A42: areia | B42: Q3 | C42: Q3 | D42: =CÁLCULOS!C235 -> AREIA MÉDIA | K42: =CÁLCULOS!L235 -> 3.3 | O42: =CÁLCULOS!M235 -> m³ | Q42: 200 | R42: =K42*Q42 -> 660 | AC42: =Q42 -> 200
A43: parabolt | B43: Q4 | C43: Q4 | D43: =CÁLCULOS!C236 -> PARABOLT 5/8" x 6" | H43: =CÁLCULOS!G236 -> para fixar escora na base | K43: =CÁLCULOS!L236 -> 124 | O43: =CÁLCULOS!M236 -> unid. | Q43: 12.8 | R43: =K43*Q43 -> 1587.2 | AC43: =Q43 -> 12.8
A44: parabolt | B44: Q5 | C44: Q5 | D44: =CÁLCULOS!C237 -> PARABOLT 5/8" x 6" | H44: =CÁLCULOS!G237 -> para fixar escora 9 m aproveitadas | K44: =CÁLCULOS!L237 -> 80 | O44: =CÁLCULOS!M237 -> unid. | Q44: 12.8 | R44: =K44*Q44 -> 1024 | V44: PARAFUSO Nivelam.(ton) | W44: preço unit. | AC44: =Q44 -> 12.8
A45: parafuso | B45: Q6 | C45: Q6 | D45: =CÁLCULOS!C238 -> PARAFUSO p/ escora M16 x 1 3/4" | H45: =CÁLCULOS!G238 -> para fixar escora no painel | K45: =CÁLCULOS!L238 -> 496 | O45: =CÁLCULOS!M238 -> unid. | Q45: =IF(D45="PARAFUSO p/ escora M16 x 1 1/2""",W40,IF(D45="PARAFUSO p/ escora M16 x 1 3/4""",W41,0)) -> 9 | R45: =K45*Q45 -> 4464 | AC45: =Q45 -> 9
A46: parafuso | B46: Q7 | C46: Q7 | D46: =CÁLCULOS!C239 -> PARAFUSO p/ Nivelam. M30 x 85 ( pé do P. Normal ) ----------- | H46: =CÁLCULOS!G239 -> 6 | I46: =CÁLCULOS!H239 -> ton p/ painel normal | J46: =CÁLCULOS!J239 -> 6 | K46: =CÁLCULOS!L239 -> 480 | O46: =CÁLCULOS!M239 -> unid. | Q46: =IF(H46=0,0,VLOOKUP(J46,V46:W49,2,0)) -> 40 | R46: =K46*Q46 -> 19200 | V46: =CÁLCULOS!Z280/1000 -> 0 | W46: 27 | X46: =CÁLCULOS!AA280 -> 0 | AC46: =Q46 -> 40
A47: parafuso | B47: Q8 | C47: Q8 | D47: =CÁLCULOS!C240 -> PARAFUSO p/ Nivelam. M30 x 85 ( pé do P. Fecho ) ----------- | H47: =CÁLCULOS!G240 -> 6 | I47: =CÁLCULOS!H240 -> ton p/ painel fecho | J47: =CÁLCULOS!J240 -> 6 | K47: =CÁLCULOS!L240 -> 16 | O47: =CÁLCULOS!M240 -> unid. | Q47: =IF(H47=0,0,VLOOKUP(J47,V46:W49,2,0)) -> 40 | R47: =K47*Q47 -> 640 | V47: =CÁLCULOS!Z281/1000 -> 6 | W47: 40 | X47: =CÁLCULOS!AA281 -> M30 x 85 | AC47: =Q47 -> 40
A48: parafuso | B48: Q9 | C48: Q9 | D48: =CÁLCULOS!C241 -> PARAFUSO SEXTAVADO M12 x 45 mm | H48: =CÁLCULOS!G241 -> para fixar flutuadores | K48: =CÁLCULOS!L241 -> 124 | O48: =CÁLCULOS!M241 -> unid. | Q48: 1.5 | R48: =K48*Q48 -> 186 | V48: =CÁLCULOS!Z282/1000 -> 10 | W48: 64 | X48: =CÁLCULOS!AA282 -> M36 x 85 | AC48: =Q48 -> 1.5
A49: arruela | B49: Q10 | C49: Q10 | D49: =CÁLCULOS!C242 -> ARRUELA 16 mm | H49: =CÁLCULOS!G242 -> para fixar escora no painel | K49: =CÁLCULOS!L242 -> 204 | O49: =CÁLCULOS!M242 -> unid. | Q49: 0.35 | R49: =K49*Q49 -> 71.4 | V49: =CÁLCULOS!Z283/1000 -> 15 | W49: 78 | X49: =CÁLCULOS!AA283 -> M39 x 85 | AC49: =Q49 -> 0.35
C50: Q10a | D50: =CÁLCULOS!C243 -> BROCA SDS Plus DIÂMETRO 16 mm x 210 mm | K50: =CÁLCULOS!L243 -> 5 | O50: =CÁLCULOS!M243 -> unid. | Q50: 35 | R50: =K50*Q50 -> 175
B51: Q10A | C51: Q10b | D51: =CÁLCULOS!C244 -> BORRACHA DE VEDAÇÃO VERTICAL SOPLACAS | K51: =CÁLCULOS!L244 -> 0 | O51: =CÁLCULOS!M244 -> m | Q51: =10*G12*1.25 -> 76.875 | R51: =K51*Q51 -> 0 | U51: F | V51: =INSUMOS!R69+INSUMOS!R71 -> 0
A52: masterseal | B52: Q11 | C52: Q11 | D52: =CÁLCULOS!C245 -> SELANTE FLEXÍVEL PU 40 ( sachê 600 ml ) | K52: =CÁLCULOS!L245+LAJES!I267 -> 2319 | O52: =CÁLCULOS!M245 -> unid. | Q52: 30 | R52: =K52*Q52 -> 69570 | U52: M | V52: =LAJES!I267*INSUMOS!Q52+INSUMOS!R54+INSUMOS!R55+LAJES!I263*INSUMOS!Q56+(IF(CÁLCULOS!L278=0,LAJES!I264,0))*INSUMOS!Q57+INSUMOS!R60+R64+INSUMOS!R63 -> 0 | X52: =SUM(R40:R49)+CÁLCULOS!L245*Q52+R53+CÁLCULOS!L277*Q56+CÁLCULOS!L278*Q57+R58+R59+R61+R62+R67+R73+R51 -> 1430051.1 | Y52: M | AC52: =Q52 -> 30
A53: sikaprimer | B53: Q12 | C53: Q12 | D53: =CÁLCULOS!C246 -> D11 ( MC-BAUCHIMIE ) - primer para substrados absorventes ( embalagem: galão de 4 litros ) | K53: =CÁLCULOS!L246 -> 2 | O53: =CÁLCULOS!M246 -> galão de 4 litros | Q53: 130 | R53: =K53*Q53 -> 260 | V53: coluna cobertura | X53: coluna parede | AC53: =Q53 -> 130
B54: Q13 | C54: Q13 | D54: =LAJES!B271 -> NEOPRENE 50 X 5 X 0,5 cm | K54: =LAJES!I271 -> 0 | O54: unid. | Q54: 15 | R54: =K54*Q54 -> 0 | V54: GUINDASTE (ton) | W54: preço trabalhando/ DIA | X54: preço / MOB. e DESMOB. | Y54: preço à disposição/ DIA | AC54: =Q54 -> 15
B55: Q14 | C55: Q14 | D55: =LAJES!B262 -> SISTEMA DE ANCORAGEM PILAR x PISO ( TREJOR ) | K55: =IF(ENTRADAS!D912="x",IF(ENTRADAS!D998="x",LAJES!I262,0),0) -> 0 | O55: conjuntos | Q55: 5000 | R55: =K55*Q55 -> 0 | AC55: =Q55 -> 5000
A56: plataforma elevatória | B56: Q15 | C56: Q15 | D56: =CÁLCULOS!C277 -> PLATAFORMA ELEVATÓRIA ARTICULADA (PTA) TIPO 450AJ | K56: =IF(J56>0,J56,CÁLCULOS!L277+LAJES!I263) -> 107 | O56: =CÁLCULOS!M277 -> dias | Q56: 750 | R56: =K56*Q56 -> 80250 | V56: 30 | W56: 2500 | X56: 4000 | Y56: =W56*0.6 -> 1500 | AC56: =Q56 -> 750
A57: plataforma elevatória | B57: Q16 | C57: Q16 | D57: =CÁLCULOS!C278 -> MOBILIZAÇÃO DE PLATAFORMA ELEVATÓRIA | K57: =IF(CÁLCULOS!L278=0,LAJES!I264,CÁLCULOS!L278) -> 1 | O57: =CÁLCULOS!M278 -> unid. | Q57: 2000 | R57: =K57*Q57 -> 2000 | V57: 60 | W57: 3000 | X57: 6000 | Y57: =W57*0.6 -> 1800 | AC57: =Q57 -> 2000
A58: guindaste | B58: Q17 | C58: Q17 | D58: =IF(K61=2," GUINDASTE 1 (mont. painés + retirada P.T.A)","GUINDASTE 1 - montagem dos painés CAP=") -> GUINDASTE 1 - montagem dos painés CAP= | H58: =GUINDASTE!F22&" toneladas" -> 70 toneladas | K58: =IF(ENTRADAS!E15=0,0,IF(J58="X",0,IF(J58>0,J58,CÁLCULOS!L279))) -> 88 | O58: =CÁLCULOS!M279 -> dias trabalhados | Q58: =IF(GUINDASTE!F22=0,0,VLOOKUP(GUINDASTE!F22,V56:X63,2,0)) -> 3700 | R58: =K58*Q58 -> 325600 | V58: 70 | W58: 3700 | X58: 5000 | Y58: =W58*0.6 -> 2220 | AC58: =Q58 -> 3700
A59: guindaste | B59: Q18 | C59: Q18 | D59: =CÁLCULOS!E280 -> 0 | H59: =IF(D59=0,0,CÁLCULOS!I280&" toneladas") -> 0 | K59: =IF(ENTRADAS!E15=0,0,IF(J59="X",0,IF(J59>0,J59,CÁLCULOS!L280))) -> 0 | O59: =CÁLCULOS!M280 -> 0 | Q59: =IF(CÁLCULOS!I280=0,0,VLOOKUP(CÁLCULOS!I280,V56:X63,2,0)) -> 0 | R59: =K59*Q59 -> 0 | V59: 90 | W59: 6000 | X59: 13000 | Y59: =W59*0.6 -> 3600 | AC59: =Q59 -> 0
B60: Q19 | C60: Q19 | D60: =LAJES!B154 -> GUINDASTE PARA LAJES | F60: =LAJES!E155 -> 0 | G60: =LAJES!F155 -> toneladas | K60: =IF(ENTRADAS!E15=0,0,IF(J60="X",0,IF(J60>0,J60,LAJES!I154))) -> 0 | O60: dias trabalhados | Q60: =IF(LAJES!E155=0,0,VLOOKUP(LAJES!E155,V56:X63,2,0)) -> 0 | R60: =K60*Q60 -> 0 | V60: 100 | W60: 7500 | X60: 20000 | Y60: =W60*0.6 -> 4500 | AC60: =Q60 -> 0
A61: guindaste | B61: Q20 | C61: Q20 | D61: =IF(K61=2,"MOBILIZAÇÃO DO GUINDASTE 1 ( montagem dos painés + retirada de P.T.A )","MOBILIZAÇÃO DO GUINDASTE 1 ( montagem dos painés )") -> MOBILIZAÇÃO DO GUINDASTE 1 ( montagem dos painés ) | K61: =IF(ENTRADAS!E15=0,0,IF(J61="X",0,IF(J61>0,J61,CÁLCULOS!L281))) -> 1 | O61: =CÁLCULOS!M281 -> unid. | Q61: =IF(CÁLCULOS!I279=0,0,VLOOKUP(CÁLCULOS!I279,V56:X63,3,0)) -> 5000 | R61: =K61*Q61 -> 5000 | V61: 130 | W61: 8000 | X61: 25000 | Y61: =W61*0.6 -> 4800 | AC61: =Q61 -> 5000
A62: guindaste | B62: Q21 | C62: Q21 | D62: =IF(K62=2,"MOBILIZAÇÃO DO GUINDASTE 2 ( montagem dos painés + retirada de P.T.A )",IF(AND(CÁLCULOS!V283=1,CÁLCULOS!V284=1),"MOBILIZAÇÃO DO GUINDASTE 2 ( montagem dos painés + retirada de P.T.A )",IF(AND(CÁLCULOS!V283=1,CÁLCULOS!V284=0),"MOBILIZAÇÃO DO GUINDASTE 2 ( retirada de P.T.A )",IF(AND(CÁLCULOS!V283=0,CÁLCULOS!V284=1),"MOBILIZAÇÃO DO GUINDASTE 2 ( montagem de painéis )",IF(K62=1,"MOBILIZAÇÃO DO GUINDASTE 2 ( montagem de painéis )",0))))) -> 0 | K62: =IF(ENTRADAS!E15=0,0,IF(J62="X",0,IF(J62>0,J62,CÁLCULOS!L282))) -> 0 | O62: =CÁLCULOS!M282 -> 0 | Q62: =IF(CÁLCULOS!I280=0,0,VLOOKUP(CÁLCULOS!I280,V56:X63,3,0)) -> 0 | R62: =K62*Q62 -> 0 | V62: 160 | W62: 9800 | X62: 30000 | Y62: =W62*0.6 -> 5880 | AC62: =Q62 -> 0
B63: Q22 | C63: Q22 | D63: =IF(K63=0,0,LAJES!B155) -> 0 | G63: =IF(J63="X",0,LAJES!E155) -> 0 | H63: =IF(K63=0,0,LAJES!F155) -> 0 | K63: =IF(ENTRADAS!E15=0,0,IF(J63="X",0,IF(J63>0,J63,LAJES!I155))) -> 0 | O63: unid. | Q63: =IF(LAJES!E155=0,0,VLOOKUP(LAJES!E155,V56:X63,3,0)) -> 0 | R63: =K63*Q63 -> 0 | V63: 200 | W63: 13000 | X63: 50000 | Y63: 5500 | AC63: =Q63 -> 0
C64: Q22a | D64: =IF(K64=0,0,LAJES!B160) -> 0 | J64: =IF(K64=0,0,LAJES!E160&" toneladas") -> 0 | K64: =LAJES!I160 -> 0 | O64: unid. | Q64: =IF(LAJES!E160=0,0,VLOOKUP(LAJES!E160,V56:Y63,4,0)) -> 0 | R64: =K64*Q64 -> 0 | AC64: =Q64 -> 0
A65: guindaste | B65: Q23 | C65: Q23 | D65: =IF(K65=0,0,CÁLCULOS!C283) -> 0 | J65: =IF(K65=0,0,CÁLCULOS!I283&" toneladas") -> 0 | K65: =CÁLCULOS!L283 -> 0 | O65: =CÁLCULOS!M283 -> dia | Q65: =IF(CÁLCULOS!L279=0,0,VLOOKUP(CÁLCULOS!I279,V56:Y63,4,0)) -> 2220 | R65: =K65*Q65 -> 0 | AC65: =Q65 -> 2220
B66: Q24 | C66: Q24 | D66: =IF(K66=0,0,CÁLCULOS!C284) -> 0 | J66: =IF(D66=0,0,CÁLCULOS!I284&" toneladas") -> 0 | K66: =CÁLCULOS!L284 -> 0 | O66: =CÁLCULOS!M284 -> dia | Q66: =IF(CÁLCULOS!L280=0,0,VLOOKUP(CÁLCULOS!I280,V56:Y63,4,0)) -> 0 | R66: =K66*Q66 -> 0 | V66: TIPO DE FRETE | X66: VALOR / FRETE | AC66: =Q66 -> 0
B67: X25 | C67: X25 | D67: FRETE P/ RETORNAR C/ MATERIAIS E EQUIP. AO FINAL DA OBRA | J67: 2 | K67: =IF(ENTRADAS!E15=0,0,IF(J67="X",0,IF(J67>0,J67,1))) -> 2 | O67: frete | Q67: =IF(ENTRADAS!I15=0,0,X67) -> 10502 | R67: =K67*Q67 -> 21004 | V67: =IF(ENTRADAS!E461=0,0,ENTRADAS!E461&"-- "&ENTRADAS!H461&" ton --"&ENTRADAS!I461&" m") -> CARRETA ABERTA -- 25 ton --12,4 m | X67: =(8900*1.18) -> 10502 | AC67: =Q67 -> 10502
B68: X26 | C68: X26 | D68: CARRETA CARGA SECA 24 toneladas | V68: =IF(ENTRADAS!E462=0,0,ENTRADAS!E462&"-- "&ENTRADAS!H462&" ton --"&ENTRADAS!I462&" m") -> CARRETA LS-- 31 ton --12,4 m | X68: =X67 -> 10502 | AC68: =Q68 -> 0
B69: X27 | C69: X27 | D69: =LAJES!B156 -> FRETE p/ 1000 km com 0 | K69: =IF(ENTRADAS!D912="X",IF(J69="X",0,IF(J69>0,J69,LAJES!AJ165)),0) -> 0 | O69: fretes | Q69: =IF(LAJES!C166="X",X67,IF(LAJES!C169="X",X68,IF(LAJES!C172="X",X69,IF(LAJES!C175="X",X70,IF(LAJES!C178="X",X71,0))))) -> 10502 | R69: =K69*Q69 -> 0 | V69: =IF(ENTRADAS!E463=0,0,ENTRADAS!E463&"-- "&ENTRADAS!H463&" ton --"&ENTRADAS!I463&" m") -> CARRETA VANDERLEIA-- 25 ton --15 m | AC69: =Q69 -> 10502
B70: X28 | C70: X28 | D70: =LAJES!B157 -> CARGA com pré-moldadados entre lajes e pilares | I70: P/ LAJES e PILARES | V70: =IF(ENTRADAS!E464=0,0,ENTRADAS!E464&"-- "&ENTRADAS!H464&" ton --"&ENTRADAS!I464&" m") -> CARRETA VANDERLEIA-- 31 ton --15 m | AC70: =Q70 -> 0
B71: X29 | C71: X29 | D71: =LAJES!B158 -> FRETE para 1000 km com 0 | K71: =IF(ENTRADAS!D912="X",IF(J71="X",0,IF(J71>0,J71,LAJES!I158)),0) -> 0 | O71: fretes | Q71: =IF(LAJES!C217="X",X67,IF(LAJES!C220="X",X68,IF(LAJES!C223="X",X69,IF(LAJES!C226="X",X70,IF(LAJES!C229="X",X71,0))))) -> 10502 | R71: =K71*Q71 -> 0 | V71: =IF(ENTRADAS!E465=0,0,ENTRADAS!E465&"-- "&ENTRADAS!H465&" ton --"&ENTRADAS!I465&" m") -> CARRETA VANDERLEIA-- 35 ton --15 m | X71: =X68/3*4 -> 14002.667 | AC71: =Q71 -> 10502
B72: Q30 | C72: X30 | D72: =LAJES!B159 -> CARGA com 0 vigas | J72: P/ VIGAS | AC72: =Q72 -> 0
A73: frete | B73: Q31 | C73: Q31 | D73: =CÁLCULOS!C285 -> FRETE para 1000 km com CARRETA LS capac.= 31 ton | K73: =IF(J73="X",0,IF(J73>0,J73,CÁLCULOS!L285)) -> 84 | O73: =CÁLCULOS!M285 -> unid. | Q73: =IF(CÁLCULOS!C176="X",X67,IF(CÁLCULOS!C179="X",X68,IF(CÁLCULOS!C182="X",X69,IF(CÁLCULOS!C185="X",X70,IF(CÁLCULOS!C188="X",X71,0))))) -> 10502 | R73: =K73*Q73 -> 882168 | S73: =IF(ENTRADAS!D912=0,0,"estão sendo transportadas "&LAJES!Y152&" lajes junto com os painéis de parede") -> 0 | AC73: =Q73 -> 10502
B74: Q32 | C74: Q32 | D74: =CÁLCULOS!C286 -> CARGA c/ 3 painéis ( larg.= 2,40m // espess.= 0,25 m // comp.= 7,3 m ) | J74: P/ PAINÉIS | AC74: =Q74 -> 0
B75: Q33 | C75: Q33 | R75: =K75*Q75 -> 0 | AC75: =Q75 -> 0
B76: Q34 | C76: Q34 | D76: TRANSPORTE ESPECÍFICO ( ESCREVER NA LINHA ACIMA) | AC76: =Q76 -> 0
B77: Q35 | C77: Q35 | D77: =CÁLCULOS!C287 -> PESO TOTAL TRANSPORTADO | K77: =CÁLCULOS!L287+LAJES!AR126 -> 2177.2753 | O77: =CÁLCULOS!M287 -> ton | AC77: =Q77 -> 0
K78: SUB-TOTAL - A | Q78: =SUM(R40:R77) -> 1430226.1 | AC78: =Q78 -> 1430226.1
AC79: =Q79 -> 0
C80: ítem | D80: =CÁLCULOS!C338 -> CABEAMENTOS E TENSIONAMENTOS - MATERIAIS, FERRAM., EQUIPAM. e LOCAÇÕES | E80: =CÁLCULOS!D338 -> 0 | F80: =CÁLCULOS!E338 -> 0 | G80: =CÁLCULOS!F338 -> 0 | H80: =CÁLCULOS!G338 -> 0 | I80: =CÁLCULOS!H338 -> 0 | J80: =CÁLCULOS!I338 -> 0 | K80: QUANT. | O80: UNID. | Q80: Preço unit. | R80: Preço Total | AC80: =Q80 -> Preço unit.
A81: cordoalha revestida | B81: Q36 | C81: Q36 | D81: =IF(ENTRADAS!I15=0,CÁLCULOS!S338,IF(ENTRADAS!G66="X",IF(CÁLCULOS!S325=15.2,CÁLCULOS!C339,0),CÁLCULOS!C339)) -> CORDOALHA 7 Fios Revestida e Engraxada ArcelorMittal CP190 RB -- | J81: =IF(ENTRADAS!I15=0,0,IF(ENTRADAS!G66="X",IF(CÁLCULOS!S325=15.2,CÁLCULOS!I339,0),CÁLCULOS!I339)) -> 15,2 mm | K81: =IF(ENTRADAS!G66="X",IF(CÁLCULOS!S325=15.2,CÁLCULOS!J339,0),CÁLCULOS!J339-CÁLCULOS!J339*V82) -> 30427.488 | O81: kg | Q81: 14.15 | R81: =K81*Q81 -> 430548.96 | V81: fator de redução na cordoalha por experiência= | AC81: =Q81 -> 14.15
B82: Q36A | C82: Q36a | D82: =IF(ENTRADAS!I15=0,CÁLCULOS!S339,IF(ENTRADAS!G66="X",IF(CÁLCULOS!S325=15.2,0,CÁLCULOS!C339),0)) -> 0 | J82: =IF(ENTRADAS!I15=0,0,IF(ENTRADAS!G66="X",IF(CÁLCULOS!S325=15.2,0,CÁLCULOS!I339),0)) -> 0 | K82: =IF(ENTRADAS!G66="X",IF(CÁLCULOS!S325=15.2,0,CÁLCULOS!J339),0) -> 0 | O82: kg | Q82: 15 | R82: =K82*Q82 -> 0 | AC82: =Q82 -> 15
B83: Q37 | C83: Q37 | E83: =IF(ENTRADAS!G66="X",IF(K81+K82=0,0,CÁLCULOS!F15*CÁLCULOS!H321*(CÁLCULOS!G44+CÁLCULOS!G46)&" pedaços com "&(CÁLCULOS!G50*2.1+(CÁLCULOS!G44+CÁLCULOS!G46)*2.5*2)/(CÁLCULOS!G44+CÁLCULOS!G46)&" m"),IF(K81=0,0,CÁLCULOS!F15*CÁLCULOS!H321*(CÁLCULOS!G44+CÁLCULOS!G46)&" pedaços com "&(CÁLCULOS!G50*2.4+(CÁLCULOS!G44+CÁLCULOS!G46)*2.7*2)/(CÁLCULOS!G44+CÁLCULOS!G46)&" m")) -> 312 pedaços com 77,4 m | G83: =IF(ENTRADAS!$F$22=1,IF(E83=0,0,"para "&ENTRADAS!$F$22&" tanque"),IF(E83=0,0,"para "&ENTRADAS!$F$22&" tanques")) -> para 4 tanques | AC83: =Q83 -> 0
B84: Q38 | C84: Q38 | E84: =IF(ENTRADAS!G66="X",IF(CÁLCULOS!C301="X",0,16*(CÁLCULOS!G44+CÁLCULOS!G46)*ENTRADAS!F22&" pedaços com ")&IF(CÁLCULOS!C301="X",0,(CÁLCULOS!I11+(2))&" m"),IF(CÁLCULOS!C301="X",0,(20*(CÁLCULOS!G44+CÁLCULOS!G46)*ENTRADAS!F22&" pedaços com ")&IF(CÁLCULOS!C301="X",0,(CÁLCULOS!I11+(2))&" m"))) -> 0 | AC84: =Q84 -> 0
A85: placa de ancoragem | B85: Q39 | C85: Q39 | D85: =CÁLCULOS!C340 -> CABEÇA de ANCORAGEM TRIPLA - ASTM A 572-GR50 (160X80X50 mm) | K85: =CÁLCULOS!J340-CÁLCULOS!J340*V86 -> 208 | O85: =CÁLCULOS!K340 -> unid. | Q85: 175 | R85: =K85*Q85 -> 36400 | V85: fator de redução para ancoragens por experiência= | AC85: =Q85 -> 175
A86: placa de ancoragem | B86: Q40 | C86: Q40 | D86: =CÁLCULOS!C341 -> PLACA DE ANCORAGEM ( AÇO ) 80 x 80 x 20 mm com 1 furos 15,2 mm | K86: =CÁLCULOS!J341 -> 0 | O86: =CÁLCULOS!K341 -> unid. | Q86: 70 | R86: =K86*Q86 -> 0 | AC86: =Q86 -> 70
A87: cunha de ancoragem | B87: Q41 | C87: Q41 | D87: =CÁLCULOS!C342 -> CUNHA DE ANCORAGEM PARA CABO 15,2 mm | K87: =CÁLCULOS!J342-CÁLCULOS!J342*V86 -> 624 | O87: =CÁLCULOS!K342 -> unid. | Q87: =4*1.25*G12 -> 30.75 | R87: =K87*Q87 -> 19188 | AC87: =Q87 -> 30.75
A88: porta cunha aberta | B88: Q42 | C88: Q42 | D88: =CÁLCULOS!C343 -> PORTA CUNHA ABERTA de ANCORAGEM para 1 CABO 15,2 mm | K88: =CÁLCULOS!J343 -> 0 | O88: =CÁLCULOS!K343 -> unid. | Q88: =8*1.25*G12 -> 61.5 | R88: =K88*Q88 -> 0 | AC88: =Q88 -> 61.5
A89: tampa plástica para | B89: Q43 | C89: Q43 | D89: =CÁLCULOS!C344 -> TAMPA PLÁSTICA PARA ANCORAGEM TRIPLA | K89: =CÁLCULOS!J344-CÁLCULOS!J344*V86 -> 208 | O89: =CÁLCULOS!K344 -> unid. | Q89: 14 | R89: =K89*Q89 -> 2912 | AC89: =Q89 -> 14
A90: tampa plástica para | B90: Q44 | C90: Q44 | D90: =CÁLCULOS!C345 -> TAMPA PLÁSTICA PARA ANCORAGEM SIMPLES | K90: =CÁLCULOS!J345 -> 0 | O90: =CÁLCULOS!K345 -> unid. | Q90: =1.5*1.25*G12 -> 11.53125 | R90: =K90*Q90 -> 0 | AC90: =Q90 -> 11.53125
A91: sabonete líquido gel | B91: Q45 | C91: Q45 | D91: =CÁLCULOS!C346 -> SABONETE LÍQUIDO GEL PH NEUTRO | K91: =CÁLCULOS!J346 -> 19 | O91: =CÁLCULOS!K346 -> litros | Q91: 5 | R91: =K91*Q91 -> 95 | AC91: =Q91 -> 5
A92: trapo | B92: Q46 | C92: Q46 | D92: =CÁLCULOS!C347 -> TRAPOS | K92: =CÁLCULOS!J347 -> 48 | O92: =CÁLCULOS!K347 -> kg | Q92: 6.5 | R92: =K92*Q92 -> 312 | AC92: =Q92 -> 6.5
A93: graxa | B93: Q47 | C93: Q47 | D93: =CÁLCULOS!C348 -> GRAXA | K93: =CÁLCULOS!J348 -> 26 | O93: =CÁLCULOS!K348 -> kg | Q93: 15 | R93: =K93*Q93 -> 390 | AC93: =Q93 -> 15
A94: disco de corte | B94: Q48 | C94: Q48 | D94: =CÁLCULOS!C349 -> DISCO DE CORTE PARA AÇO 4 1/2" X 1/8" X 7/8" MARCA STANLEY | K94: =CÁLCULOS!J349 -> 208 | O94: =CÁLCULOS!K349 -> unid. | Q94: 4 | R94: =K94*Q94 -> 832 | AC94: =Q94 -> 4
A95: lâmina de serra | B95: Q49 | C95: Q49 | D95: =CÁLCULOS!C350 -> LÂMINA DE SERRA | K95: =CÁLCULOS!J350 -> 16 | O95: =CÁLCULOS!K350 -> unid. | Q95: 4.2 | R95: =K95*Q95 -> 67.2 | AC95: =Q95 -> 4.2
A96: cunhas de madeira | B96: Q50 | C96: Q50 | D96: =CÁLCULOS!C351 -> CUNHAS DE MADEIRA 8 X 8 X 30 cm para estabilidade painéis junto à base | K96: =CÁLCULOS!J351 -> 126 | O96: =CÁLCULOS!K351 -> unid. | Q96: 1.9 | R96: =K96*Q96 -> 239.4 | AC96: =Q96 -> 1.9
A97: andaime metálico 2,50 x | B97: Q51 | C97: Q51 | D97: =CÁLCULOS!C352 -> ANDAIME Painel Fecho: 8 unid. 2,5 X 1,0 X H=8 m (pisos a c/ 2 m) vol= 168 m³ durante 107 dias | K97: =CÁLCULOS!J352+LAJES!I265 -> 143808 | O97: =CÁLCULOS!K352 -> m³xdia | Q97: 0.13 | R97: =K97*Q97 -> 18695.04 | U97: M | V97: =LAJES!I265*INSUMOS!Q97+LAJES!I266*INSUMOS!Q98 -> 0 | X97: =SUM(R81:R96)+CÁLCULOS!J352*Q97+CÁLCULOS!J353*Q98 -> 509679.6 | Y97: M | AC97: =Q97 -> 0.13
A98: escada de acesso | B98: Q52 | C98: Q52 | D98: =CÁLCULOS!C353 -> ESCADA de ACESSO: 2 unid. de 2,5 X 4,0 X H=8,3 m int/ext /// vol.= 637,44 m³ durante 107 dias | K98: =CÁLCULOS!J353+LAJES!I266 -> 272824.32 | O98: =CÁLCULOS!K353 -> m³xdia | R98: =K98*Q98 -> 0 | AC98: =Q98 -> 0
K99: SUB-TOTAL - B | Q99: =SUM(R81:R98) -> 509679.6 | AC99: =Q99 -> 509679.6
AC100: =Q100 -> 0
C101: ítem | D101: =CÁLCULOS!C368 -> SOLIDARIZAÇÃO - MATERIAIS, FERRAM., EQUIPAM. e LOCAÇÕES | E101: =CÁLCULOS!D368 -> 0 | F101: =CÁLCULOS!E368 -> 0 | G101: =CÁLCULOS!F368 -> 0 | H101: =CÁLCULOS!G368 -> 0 | I101: =CÁLCULOS!H368 -> 0 | J101: =CÁLCULOS!I368 -> 0 | K101: QUANT. | O101: UNID. | Q101: Preço unit. | R101: Preço Total | AC101: =Q101 -> Preço unit.
A102: forma de madeira | B102: Q53 | C102: 53 | D102: =CÁLCULOS!C369 -> FORMA de MADEIRA e MADEIRITE h= | G102: =CÁLCULOS!F369 -> 0,4 m ( incluir material e m.o.) | K102: =CÁLCULOS!J369 -> 61.703672 | O102: =CÁLCULOS!K369 -> m² | Q102: 1000 | R102: =IF(ENTRADAS!J844<>0,0,K102*Q102) -> 0 | AC102: =Q102 -> 1000
A103: concreto fck 40 mpa | B103: Q54 | C103: 54 | D103: =CÁLCULOS!C370 -> CONCRETO fck 40 Mpa - slump ( 12 ± 2 cm ) --- somente material | K103: =CÁLCULOS!J370+LAJES!I269 -> 119 | O103: =CÁLCULOS!K370 -> m³ | Q103: 700 | R103: =IF(ENTRADAS!J844<>0,0,K103*Q103) -> 0 | AC103: =Q103 -> 700
A104: bombeamento de concreto | B104: Q55 | C104: 55 | D104: =CÁLCULOS!C371 -> BOMBEAMENTO DE CONCRETO | K104: =CÁLCULOS!J371+LAJES!I269 -> 119 | O104: =CÁLCULOS!K371 -> m³ | Q104: 200 | R104: =IF(ENTRADAS!J844<>0,0,K104*Q104) -> 0 | U104: M | V104: =LAJES!I269*INSUMOS!Q103+LAJES!I269*INSUMOS!Q104 -> 0 | X104: =R102+CÁLCULOS!J370*Q103+CÁLCULOS!J371*Q104+R105+R106 -> 150770 | Y104: M | AC104: =Q104 -> 200
A105: sikaswell-s2 selante | B105: Q56 | C105: 56 | D105: =CÁLCULOS!C372 -> SIKASWELL-S2 SELANTE HIDROEXPANSÍVEL ( embalagem 300 ml ) | K105: =CÁLCULOS!J372 -> 298 | O105: =CÁLCULOS!K372 -> unid. | Q105: 140 | R105: =K105*Q105 -> 41720 | AC105: =Q105 -> 140
A106: sikalatex resina de | B106: Q57 | C106: 57 | D106: =CÁLCULOS!C373 -> MURAFAN 39 RESINA DE ADERÊNCIA (embalagm de 18 KG ) | K106: =CÁLCULOS!J373 -> 13 | O106: =CÁLCULOS!K373 -> unid. | Q106: 150 | R106: =K106*Q106 -> 1950 | AC106: =Q106 -> 150
K107: SUB-TOTAL - C | Q107: =SUM(R102:R106) -> 43670 | AC107: =Q107 -> 43670
AC108: =Q108 -> 0
D109: =CÁLCULOS!C396 -> INJEÇÃO E ACABAMENTOS - MATERIAIS, FERRAM., EQUIPAM. e LOCAÇÕES | E109: =CÁLCULOS!D396 -> 0 | F109: =CÁLCULOS!E396 -> 0 | G109: =CÁLCULOS!F396 -> 0 | H109: =CÁLCULOS!G396 -> 0 | I109: =CÁLCULOS!H396 -> 0 | J109: =CÁLCULOS!I396 -> 0 | K109: QUANT. | O109: UNID. | Q109: Preço unit. | R109: Preço Total | AC109: =Q109 -> Preço unit.
A110: valvula esfera | B110: Q58 | C110: Q58 | D110: =CÁLCULOS!C399 -> VALVULA ESFERA GALVANIZADA 1 1/4" | K110: =CÁLCULOS!L399*0.6 -> 6.6 | O110: =CÁLCULOS!M399 -> unid. | Q110: 85 | R110: =K110*Q110 -> 561 | AC110: =Q110 -> 85
...

Sheet Aux.
B4: INSUMOS P/ ANÁLISE DE FATURAMENTO DIRETO | E4: PAR / COB | F4: PILAR /CHIC | G4: % A UTILIZAR | H4: TOTAL | I4: FORNECEDOR | J4: PARA ZERAR
B5: GUINDASTES | D5: MONT | E5: =INSUMOS!R58+INSUMOS!R61 -> 330600 | G5: 0.7 | H5: =IF(FECHAMENTO!$S$17<>0,IF(J5="x",0,E5/ENTRADAS!$F$22*FECHAMENTO!$S$17*G5),IF(J5="x",0,E5*G5)) -> 0 | I5: G-MAQ | J5: X
B6: FRETE | D6: FABR | E6: =INSUMOS!R69+INSUMOS!R71+INSUMOS!R73+INSUMOS!R75 -> 882168 | G6: 0.7 | H6: =IF(FECHAMENTO!$S$17<>0,IF(J6="x",0,E6/ENTRADAS!$F$22*FECHAMENTO!$S$17*G6),IF(J6="x",0,E6*G6)) -> 0 | I6: AMH SERVIÇOS | J6: X
B7: CORDOALHA ENGRAXADA | D7: MONT | H7: =IF(FECHAMENTO!$S$17<>0,IF(J7="x",0,E7/ENTRADAS!$F$22*FECHAMENTO!$S$17*G7),IF(J7="x",0,E7*G7)) -> 0 | I7: BELGO BEKAERT
B8: ARGAMASSA INJEÇÃO | D8: MONT | H8: =IF(FECHAMENTO!$S$17<>0,IF(J8="x",0,E8/ENTRADAS!$F$22*FECHAMENTO!$S$17*G8),IF(J8="x",0,E8*G8)) -> 0 | I8: TECNOSIL
B9: GROUT | D9: MONT | H9: =IF(FECHAMENTO!$S$17<>0,IF(J9="x",0,E9/ENTRADAS!$F$22*FECHAMENTO!$S$17*G9),IF(J9="x",0,E9*G9)) -> 0 | I9: TECNOSIL
B10: MATERIAIS BAUCHIMIE | D10: MONT | H10: =IF(FECHAMENTO!$S$17<>0,IF(J10="x",0,E10/ENTRADAS!$F$22*FECHAMENTO!$S$17*G10),IF(J10="x",0,E10*G10)) -> 0 | I10: BAUCHIMIE
B11: MATERIAIS IÇAMENTO TREJOR | D11: FABR | E11: =SUM(INSUMOS!R140:R148) -> 136251.2 | G11: 0.7 | H11: =IF(FECHAMENTO!$S$17<>0,IF(J11="x",0,E11/ENTRADAS!$F$22*FECHAMENTO!$S$17*G11),IF(J11="x",0,E11*G11)) -> 0 | I11: TREJOR | J11: x
B12: EMENDA TREJOR PISO X PILAR | D12: FABR | H12: =IF(FECHAMENTO!$S$17<>0,IF(J12="x",0,E12/ENTRADAS!$F$22*FECHAMENTO!$S$17*G12),IF(J12="x",0,E12*G12)) -> 0 | I12: TREJOR
B13: AÇO | D13: FABR | H13: =IF(FECHAMENTO!$S$17<>0,IF(J13="x",0,E13/ENTRADAS!$F$22*FECHAMENTO!$S$17*G13),IF(J13="x",0,E13*G13)) -> 0 | I13: ARCELOR
B14: CORDOALHA NUA 12,7 | D14: FABR | H14: =IF(FECHAMENTO!$S$17<>0,IF(J14="x",0,E14/ENTRADAS!$F$22*FECHAMENTO!$S$17*G14),IF(J14="x",0,E14*G14)) -> 0 | I14: BELGO BEKAERT
B15: AREIA P/ CONCRETO | D15: FABR | H15: =IF(FECHAMENTO!$S$17<>0,IF(J15="x",0,E15/ENTRADAS!$F$22*FECHAMENTO!$S$17*G15),IF(J15="x",0,E15*G15)) -> 0
B16: BRITA 0 | D16: FABR | H16: =IF(FECHAMENTO!$S$17<>0,IF(J16="x",0,E16/ENTRADAS!$F$22*FECHAMENTO!$S$17*G16),IF(J16="x",0,E16*G16)) -> 0
B17: CIMENTO CP3 | D17: FABR | H17: =IF(FECHAMENTO!$S$17<>0,IF(J17="x",0,E17/ENTRADAS!$F$22*FECHAMENTO!$S$17*G17),IF(J17="x",0,E17*G17)) -> 0
B18: CIMENTO CP5 | D18: FABR | H18: =IF(FECHAMENTO!$S$17<>0,IF(J18="x",0,E18/ENTRADAS!$F$22*FECHAMENTO!$S$17*G18),IF(J18="x",0,E18*G18)) -> 0
B20: TOTAL | E20: =SUM(E5:E19) -> 1349019.2 | F20: =SUM(F5:F19) -> 0 | H20: =SUM(H5:H19) -> 0
C22: TOTAL FABRICAÇÃO= | E22: =SUM(E11:F18) -> 136251.2
C23: TOTAL MONTAGEM= | E23: =SUM(E5:F10) -> 1212768

Sheet ICMS
A1: LANÇAMENTO DE PERCENTUAIS DE ICMS PARA INSUMOS DE FABRICAÇÃO
C3: TOTAL ICMS = | E3: =SUM(E4:E65) -> 296264.73
A4: INSUMO | B4: ORIGEM | C4: % ICMS | D4: VALOR INSUMO | E4: ICMS ORIGEM
A5: =INSUMOS!D67 -> FRETE P/ RETORNAR C/ MATERIAIS E EQUIP. AO FINAL DA OBRA | B5: MS | C5: 0.12 | D5: =INSUMOS!R67 -> 21004 | E5: =D5*C5 -> 2520.48
A6: =INSUMOS!D69 -> FRETE p/ 1000 km com 0 | B6: MS | C6: 0.12 | D6: =INSUMOS!R69 -> 0 | E6: =D6*C6 -> 0
A7: =INSUMOS!D71 -> FRETE para 1000 km com 0 | B7: MS | C7: 0.12 | D7: =INSUMOS!R71 -> 0 | E7: =D7*C7 -> 0
A8: =INSUMOS!D73 -> FRETE para 1000 km com CARRETA LS capac.= 31 ton | B8: MS | C8: 0.12 | D8: =INSUMOS!R73 -> 882168 | E8: =D8*C8 -> 105860.16
A9: =INSUMOS!D75 -> 0 | B9: MS | C9: 0.12 | D9: =INSUMOS!R75 -> 0 | E9: =D9*C9 -> 0
A10: =INSUMOS!D140 -> A- PINO PARA MONTAGEM ( no topo do painel ) ----------- | B10: SP | C10: 0.07 | D10: =INSUMOS!R140 -> 35040 | E10: =D10*C10 -> 2452.8
A11: =INSUMOS!D141 -> B- PINO PARA MONTAGEM ( no topo do painel ) --------- | B11: SP | C11: 0.07 | D11: =INSUMOS!R141 -> 1888 | E11: =D11*C11 -> 132.16
A12: =INSUMOS!D142 -> C- PINO PARA MOVIMENTAÇÃO ( na face do painel ) --- | B12: SP | C12: 0.07 | D12: =INSUMOS!R142 -> 52800 | E12: =D12*C12 -> 3696
A13: =INSUMOS!D143 -> D- PINO PARA MOVIMENTAÇÃO ( na face do painel ) --- | B13: SP | C13: 0.07 | D13: =INSUMOS!R143 -> 2528 | E13: =D13*C13 -> 176.96
A14: =INSUMOS!D144 -> PINO DE MOVIMENTAÇÃO 5 tf /125 | B14: SP | C14: 0.07 | D14: =INSUMOS!R144 -> 0 | E14: =D14*C14 -> 0
A15: =INSUMOS!D145 -> LUVA de Nivelamento M30 x 70 ( no pé do painel ) ----------- | B15: SP | C15: 0.07 | D15: =INSUMOS!R145 -> 22080 | E15: =D15*C15 -> 1545.6
A16: =INSUMOS!D146 -> LUVA de Nivelamento M30 x 70 ( no pé do painel ) ----------- | B16: SP | C16: 0.07 | D16: =INSUMOS!R146 -> 736 | E16: =D16*C16 -> 51.52
A17: =INSUMOS!D147 -> LUVA para flutuadores TSB-M12 x 50 | B17: SP | C17: 0.07 | D17: =INSUMOS!R147 -> 6299.2 | E17: =D17*C17 -> 440.944
A18: =INSUMOS!D148 -> LUVA p/ escora TSB-M16 x 100 | B18: SP | C18: 0.07 | D18: =INSUMOS!R148 -> 14880 | E18: =D18*C18 -> 1041.6
A19: =INSUMOS!D149 -> CURVA 90° GALVANIZADA 1 1/4" | B19: ES | C19: 0.17 | D19: =INSUMOS!R149 -> 7440 | E19: =D19*C19 -> 1264.8
A20: =INSUMOS!D150 -> TUBO 2,50 m para BAINHA 3 CABOS | B20: RS | C20: 0.07 | D20: =INSUMOS!R150 -> 93184 | E20: =D20*C20 -> 6522.88
A21: =INSUMOS!D151 -> TUBO 2,50 m para BAINHA 1 CABO | B21: ES | C21: 0.01 | D21: =INSUMOS!R151 -> 0 | E21: =D21*C21 -> 0
A22: =INSUMOS!D152 -> CONE PARA TUBO 3 CABOS | B22: ES | D22: =INSUMOS!R152 -> 0 | E22: =D22*C22 -> 0
A23: =INSUMOS!D153 -> CONE PARA TUBO 1 CABO | B23: ES | D23: =INSUMOS!R153 -> 0 | E23: =D23*C23 -> 0
A24: =INSUMOS!D155 -> INSUMOS GERAIS PARA CONCRETO fcK>=25 MPa 24h | B24: DIV | C24: ='X MPa '!M51 -> 0.13540345 | D24: =INSUMOS!R155 -> 581663.79 | E24: =D24*C24 -> 78759.284
A25: =INSUMOS!D156 -> CHAPA DE ANCORAGEM - ASTM A 572-GR50 (200 X 120 X 19 mm) | B25: ES | C25: 0.17 | D25: =INSUMOS!R156 -> 29120 | E25: =D25*C25 -> 4950.4
A26: =INSUMOS!D157 -> CHAPA DE ANCORAGEM - ASTM A 572-GR50 (120 X 120 X 16 mm) | B26: ES | C26: 0.17 | D26: =INSUMOS!R157 -> 0 | E26: =D26*C26 -> 0
A27: =INSUMOS!D158 -> TELA SOLDADA | B27: ES | C27: 0.17 | D27: =INSUMOS!R158 -> 0 | E27: =D27*C27 -> 0
A28: =INSUMOS!D159 -> AÇO CA-50 | B28: SP | C28: 0.091 | D28: =INSUMOS!R159 -> 419290.97 | E28: =D28*C28 -> 38155.478
A29: =INSUMOS!D160 -> CORDOALHA 7 fios Arcellor Mittal CP 190 RB 12,70 mm | B29: SP | C29: 0.07 | D29: =INSUMOS!R160 -> 291124.52 | E29: =D29*C29 -> 20378.717
A30: =INSUMOS!D161 -> DISTANCIADOR PLÁSTICO COPLAS cadeirinha SCP-45/30 | B30: SP | C30: 0.07 | D30: =INSUMOS!R161 -> 5865.696 | E30: =D30*C30 -> 410.59872
A31: =INSUMOS!D162 -> ARAME RECOZIDO TORCIDO | B31: ES | C31: 0.17 | D31: =INSUMOS!R162 -> 17823.419 | E31: =D31*C31 -> 3029.9813
A32: =INSUMOS!D163 -> ISOPOR 3 cm ( folha 50x100 cm) | B32: ES | C32: 0.17 | D32: =INSUMOS!R163 -> 149.24 | E32: =D32*C32 -> 25.3708
A33: =INSUMOS!D164 -> DESMOLDANTE DENVER SM ECO | B33: SP | C33: 0.07 | D33: =INSUMOS!R164 -> 16988.95 | E33: =D33*C33 -> 1189.2265
A34: =INSUMOS!D165 -> AGENTE DE CURA hidrocarbonetos parafínicos ( CURING ) | B34: SP | C34: 0.07 | D34: =INSUMOS!R165 -> 6952 | E34: =D34*C34 -> 486.64
A35: =INSUMOS!D166 -> D11 ( MC-BAUCHIMIE ) - primer para substrados absorventes ( embalagem: galão de 4 litros ) | B35: SP | C35: 0.07 | D35: =INSUMOS!R166 -> 1782.048 | E35: =D35*C35 -> 124.74336
A36: =INSUMOS!D168 -> ARAME PARA SOLDA MIG/MAG 1,2mm | B36: ES | C36: 0.17 | D36: =INSUMOS!R168 -> 3284.45 | E36: =D36*C36 -> 558.3565
A37: =INSUMOS!D169 -> GÁS MISTURA (cilindro com 6 m³) | B37: ES | C37: 0.17 | D37: =INSUMOS!R169 -> 2925 | E37: =D37*C37 -> 497.25
A38: =INSUMOS!D250 -> INSUMOS GERAIS PARA CONCRETO fcK>=10 MPa 24h | B38: DIV | C38: =C24 -> 0.13540345 | D38: =INSUMOS!R250 -> 0 | E38: =D38*C38 -> 0
A39: =INSUMOS!D251 -> CORDOALHA 7 Fios Revestida e Engraxada ArcelorMittal CP190 RB -- 12,7 mm EM LAJES | B39: BA | C39: 0.07 | D39: =INSUMOS!R251 -> 0 | E39: =D39*C39 -> 0
A40: =INSUMOS!D252 -> ANCORAGENS PARA PÓS-TENSÃO EM LAJES | B40: ES | C40: 0.17 | D40: =INSUMOS!R252 -> 0 | E40: =D40*C40 -> 0
A42: OUTROS DOS SERVIÇOS ADICIONAIS (LANÇAR MANUALMENTE)
A43: PASSAMUROS | B43: ES | C43: 0.17 | D43: 129369.31 | E43: =D43*C43 -> 21992.783
E44: =D44*C44 -> 0
E45: =D45*C45 -> 0
E46: =D46*C46 -> 0
E47: =D47*C47 -> 0
E48: =D48*C48 -> 0
E49: =D49*C49 -> 0
E50: =D50*C50 -> 0
E51: =D51*C51 -> 0
E52: =D52*C52 -> 0
E53: =D53*C53 -> 0
E54: =D54*C54 -> 0
E55: =D55*C55 -> 0
... E65: =D65*C65 -> 0

Sheet FECHAMENTO
E2: SISTEMA SC-10 e SC-14 FECHAMENTO FINAL | M2: DATA: | O2: =CÁLCULOS!O1 -> 45638 | S2: X | U2: F
M3: REVISÃO: | O3: =CÁLCULOS!O2 -> 3 | U3: M
E4: CLIENTE: | F4: =CÁLCULOS!F3 -> Passarelli | M4: LOCAL:
E5: OBRA: | F5: =CÁLCULOS!F4 -> 12 tqs Nereda | M5: =CÁLCULOS!M4&" - "&ENTRADAS!P4 -> São Paulo - Tatuapé - SP
C9: 1- CUSTOS | H9: QUANDO ENVIAR ESTA PLANILHA P/ SOPLACAS MARCAR "X" | S9: fretes= | T9: =IF(S17<>0,(INSUMOS!R67+INSUMOS!R69+INSUMOS!R71+INSUMOS!R73+INSUMOS!R75)/ENTRADAS!F22*S17,(INSUMOS!R67+INSUMOS!R69+INSUMOS!R71+INSUMOS!R73+INSUMOS!R75)) -> 2709516
C11: FABRICAÇÃO | G11: MONTAGEM | L11: FABRICAÇÃO + MONTAGEM | S11: adicionais ñ royalties= | T11: =IF(S17<>0,INSUMOS!Z275/ENTRADAS!F22*FECHAMENTO!S17,INSUMOS!Z275) -> 0
C12: =IF(P9="X",(E12-T9-T11),"") | E12: =IF(S17<>0,((INSUMOS!R67+INSUMOS!R69+INSUMOS!R71+INSUMOS!R73+INSUMOS!R75)+INSUMOS!Q174+INSUMOS!Q195+INSUMOS!Q230+INSUMOS!Q236+INSUMOS!Q243+INSUMOS!Q253+INSUMOS!Q275)/ENTRADAS!F22*FECHAMENTO!S17,(INSUMOS!R67+INSUMOS!R69+INSUMOS!R71+INSUMOS!R73+INSUMOS!R75)+INSUMOS!Q174+INSUMOS!Q195+INSUMOS!Q230+INSUMOS!Q236+INSUMOS!Q243+INSUMOS!Q253+INSUMOS!Q275) -> 10824923 | G12: =IF(P9="x",(I12+T9+T11),"") | I12: =IF(S17<>0,(INSUMOS!Q78-(INSUMOS!R67+INSUMOS!R69+INSUMOS!R71+INSUMOS!R73+INSUMOS!R75)+INSUMOS!Q99+INSUMOS!Q107+INSUMOS!Q119+INSUMOS!Q137+INSUMOS!Q183+INSUMOS!Q214+INSUMOS!Q276+INSUMOS!R257+INSUMOS!R258)/ENTRADAS!F22*FECHAMENTO!S17,(INSUMOS!Q78-(INSUMOS!R67+INSUMOS!R69+INSUMOS!R71+INSUMOS!R73+INSUMOS!R75)+INSUMOS!Q99+INSUMOS!Q107+INSUMOS!Q119+INSUMOS!Q137+INSUMOS!Q183+INSUMOS!Q214+INSUMOS!Q276+INSUMOS!R257+INSUMOS!R258)) -> 20884875 | N12: =IF(P9<>0,C12+G12,E12+I12) -> 31709798
C13: PERCENTUAL = | E13: =IF(E12=0,0,E12/N12) -> 0.3413747 | G13: PERCENTUAL = | J13: =IF(I12=0,0,I12/N12) -> 0.6586253 | S13: DIGITE AQUI A QUANTIDADE DE TANQUES CASO SEJA FOR MAIOR QUE 4.
C17: 2- LUCRO ------ PERCENTUAL = | G17: 23 | H17: =IF(G17=0," FALTA PERCENTUAL DE LUCRO !","%") -> % | I17: =IF(W62<>0,"alterado o lucro sobre faturamento direto PREBMOL para "&W62&"%",0) -> alterado o lucro sobre faturamento direto PREBMOL para 21,57945763% | S17: =IF(ENTRADAS!F21>4,ENTRADAS!F21,0) -> 12 | T17: QUANTIDADE DE TANQUES (QUANDO ACIMA DE 4 TQS)
C19: =IF(P9="x","LUCRO NA FABRICAÇÃO","FABRICAÇÃO") -> FABRICAÇÃO | G19: =IF(P9="x","LUCRO NA MONTAGEM","MONTAGEM") -> MONTAGEM | L19: =IF(P9="x","LUCRO NA FABRICAÇÃO + MONTAGEM","FABRICAÇÃO + MONTAGEM") -> FABRICAÇÃO + MONTAGEM | S19: ROYALTIES SOBRE A FABRICAÇÃO + LUCRO:
C20: =IF(P9="x",C12*G17/100,"LUCRO =") -> LUCRO = | E20: =(E12*G17/100)-(0*(G17-W62)/100) -> 2489732.2 | G20: =IF(P9="x",G12*G17/100,"LUCRO =") -> LUCRO = | I20: =(I12*G17/100)-(AB85*(G17-W62)/100) -> 4611951 | L20: LUCRO = | N20: =IF(P9<>0,C20+G20,E20+I20) -> 7101683.2 | S20: x | T20: SIM
C24: 3- SUB-TOTAL ( CUSTO + LUCRO )
C26: FABRICAÇÃO | G26: MONTAGEM | L26: FABRICAÇÃO + MONTAGEM | S26: PERCENTUAL INVESTIMENTO CALCULADO:
C27: =IF(P9="x",C12+C20,"") | E27: =E12+E20 -> 13314655 | G27: =IF(P9="x",G12+G20,"") | I27: =I12+I20 -> 25496826 | N27: =N12+N20 -> 38811481 | S27: PERCENTUAL= | U27: =((CÁLCULOS!G701/30)*(V51/(3*12)))/O38 -> 0.17908719
C31: 4- ROYALTIES ------ PERCENTUAL = | G31: 5 | H31: % | S31: CONSIDERAR PERCENTUAL DO VALOR DE INVESTIMENTO EM:
C33: =IF(S20="x",0,"REFERENTE À FABRICAÇÃO") -> 0 | G33: =IF(S20="x","REFERENTE À FABRICAÇÃO + LUCRO",0) -> REFERENTE À FABRICAÇÃO + LUCRO | L33: TOTAL DE ROYALTIES
I34: =IF(S17<>0,IF(S20="X",((E12-((INSUMOS!R67+INSUMOS!R69+INSUMOS!R71+INSUMOS!R73+INSUMOS!R75)+INSUMOS!Z275)/ENTRADAS!F22*FECHAMENTO!S17)*(1+G17/100))*G31/100,((E12-((INSUMOS!R67+INSUMOS!R69+INSUMOS!R71+INSUMOS!R73+INSUMOS!R75)+INSUMOS!Z275)/ENTRADAS!F22*FECHAMENTO!S17)*(1+G17/100))*G31/100),IF(S20="X",((E12-((INSUMOS!R67+INSUMOS!R69+INSUMOS!R71+INSUMOS!R73+INSUMOS!R75)+INSUMOS!Z275))*(1+G17/100))*G31/100,((E12-((INSUMOS!R67+INSUMOS!R69+INSUMOS!R71+INSUMOS!R73+INSUMOS!R75)+INSUMOS!Z275))*(1+G17/100))*G31/100)) -> 499097.51 | N34: =D34+I34 -> 499097.51 | S34: PERCENTUAL= | U34: 0.15
C38: 5- INVESTIMENTOS= | E38: =U53 -> 75.220711 | F38: / m³ fabricado | J38: VOLUME fabricado ( painel )= | O38: =IF(S17<>0,CÁLCULOS!N619/ENTRADAS!F22*FECHAMENTO!S17,CÁLCULOS!N619) -> 2612.7304 | P38: m³ | S38: total= | T38: =(INSUMOS!Q331+INSUMOS!Q356)*U34 -> 376356.08
C40: REFERENTE À FABRICAÇÃO | G40: REFERENTE À MONTAGEM | L40: TOTAL INVESTIMENTOS | T40: considerando amortização em 3 anos
C41: ver comentário | I41: =(O38*J13*E38)+(O38*E38*E13) -> 196531.43 | N41: =D41+I41 -> 196531.43 | T41: média fabricação por dia=2,15 placas
C45: 6- TOTAL SEM IMPOSTOS | T45: por ano= 240 * 2,15 = 516 placas
C47: REFERENTE À FABRICAÇÃO | G47: REFERENTE À MONTAGEM | L47: TOTAL SEM IMPOSTOS | T47: 3 anos= 720 * 2,15 = 1548 placas
D48: =IF(P9<>0,(E27+D34+D41),E27+D34+D41) -> 13314655 | I48: =IF(P9<>0,(I27+I34+I41),I27+I34+I41) -> 26192455 | N48: =N27+N34+N41 -> 39507110
C50: ICMS ADOTADO(%)= | E50: 0.18 | H50: FATURAMENTO DIRETO: | T50: volume de uma placa 6,65m= | V50: =90.5/28 -> 3.2321429 | W50: m³
C51: ICMS CHEIO= | E51: =(($D$48-L51)/(1-E50)-($D$48-L51)) -> 2922729.1 | H51: Valor do faturamento direto na fabricação= | L51: =T62 -> 0 | T51: volume de 720 placas= | V51: =1548*V50 -> 5003.3571 | W51: m³
C53: ICMS CRÉDITOS= | E53: =IF(S17<>0,(ICMS!E3-AC62)/ENTRADAS!F22*FECHAMENTO!S17,ICMS!E3-AC62) -> 888794.2 | H53: Valor do faturamento direto na montagem= | L53: =U62 -> 13485714 | T53: amortiz/m³= | U53: =T38/V51 -> 75.220711
C54: INVEST (%)=
C58: 7- IMPOSTOS | T58: FATURAMENTO DIRETO | V58: alterar percentual de lucro sobre Faturamento direto só sobre Prebmol
D59: 0.17 | I59: 0.05
C60: FABRICAÇÃO | H60: MONTAGEM | S60: marcar x p/ zerar | T60: Valor ref. Fabricação | U60: Valor ref. Montagem | AC60: Total créditos (abater)
C62: ICMS FINAL | D62: =E62/D48 -> 0.15275912 | E62: =(E51-E53)-(E51-E53)*E54 -> 2033934.9 | H62: ISS | I62: 0.05 | J62: =($I$48-$L$53)/(1-I62)-($I$48-$L$53) -> 668775.84 | L62: =IF(I62=0,"foi zerado o ISS -----",IF(I62=I59,0,"foi alterado o ISS -----")) -> 0 | O62: =IF(D62=0,"foi zerado o ICMS -----",IF(D62=D59,0,"foi alterado o ICMS -----")) -> foi alterado o ICMS ----- | S62: faturamento direto | T62: =IF(S58="X",0,IF(SUM($T$66:$T$110)=0,0,SUM(AA66:AA104))) -> 0 | U62: =IF(S58="X",0,IF(SUM($T$66:$T$110)=0,0,SUM(AB66:AB104))) -> 13485714 | V62: ***** | W62: 21.579458 | X62: % | Z62: % ICMS | AC62: =SUM(AC66:AC104) -> 0
C64: PIS | D64: 0.0065 | E64: =(($D$48-$L$51)/(1-D64)-($D$48-$L$51)) -> 87111.481 | H64: PIS | I64: 0.0065 | J64: =($I$48-$L$53)/(1-I64)-($I$48-$L$53) -> 83134.189 | S64: F ou M | T64: VALOR | U64: REFERENTE À: | Z64: ORIGEM | AA64: FABRICAÇÃO | AB64: MONTAGEM | AC64: CRÉDITO ICMS
C66: CONFINS | D66: 0.03 | E66: =(($D$48-$L$51)/(1-D66)-($D$48-$L$51)) -> 411793.45 | H66: CONFINS | I66: 0.03 | J66: =($I$48-$L$53)/(1-I66)-($I$48-$L$53) -> 392991.99 | S66: F | T66: =Aux.!H11 -> 0 | U66: TREJOR | Z66: 0.07 | AA66: =IF(T66=0,0,IF(S66="F",T66,0)) -> 0 | AB66: =IF(T66=0,0,IF(S66="M",T66,0)) -> 0 | AC66: =IF(T66=0,0,IF(S66="F",T66*Z66,0)) -> 0
AA67: =IF(T67=0,0,IF(S67="F",T67,0)) -> 0 | AB67: =IF(T67=0,0,IF(S67="M",T67,0)) -> 0 | AC67: =IF(T67=0,0,IF(S67="F",T67*Z67,0)) -> 0
C68: IR | D68: 0.02 | E68: =(($D$48-$L$51)/(1-D68)-($D$48-$L$51)) -> 271727.65 | H68: IR | I68: 0.02 | J68: =($I$48-$L$53)/(1-I68)-($I$48-$L$53) -> 259321.25 | S68: F | T68: =Aux.!H6 -> 0 | U68: FRETE | AA68: =IF(T68=0,0,IF(S68="F",T68,0)) -> 0 | AB68: =IF(T68=0,0,IF(S68="M",T68,0)) -> 0 | AC68: =IF(T68=0,0,IF(S68="F",T68*Z68,0)) -> 0
AA69: =IF(T69=0,0,IF(S69="F",T69,0)) -> 0 | AB69: =IF(T69=0,0,IF(S69="M",T69,0)) -> 0 | AC69: =IF(T69=0,0,IF(S69="F",T69*Z69,0)) -> 0
C70: CSLL | D70: 0.0108 | E70: =(($D$48-$L$51)/(1-D70)-($D$48-$L$51)) -> 145368.25 | H70: CSLL | I70: 0.0108 | J70: =($I$48-$L$53)/(1-I70)-($I$48-$L$53) -> 138731.1 | S70: M | T70: =Aux.!H5 -> 0 | U70: GUINDASTE | AA70: =IF(T70=0,0,IF(S70="F",T70,0)) -> 0 | AB70: =IF(T70=0,0,IF(S70="M",T70,0)) -> 0 | AC70: =IF(T70=0,0,IF(S70="F",T70*Z70,0)) -> 0
AA71: =IF(T71=0,0,IF(S71="F",T71,0)) -> 0 | AB71: =IF(T71=0,0,IF(S71="M",T71,0)) -> 0 | AC71: =IF(T71=0,0,IF(S71="F",T71*Z71,0)) -> 0
C72: IPI | E72: =(($D$48-$L$51)/(1-D72)-($D$48-$L$51)) -> 0 | S72: M | U72: BAUCHIMIE | AA72: =IF(T72=0,0,IF(S72="F",T72,0)) -> 0 | AB72: =IF(T72=0,0,IF(S72="M",T72,0)) -> 0 | AC72: =IF(T72=0,0,IF(S72="F",T72*Z72,0)) -> 0
AA73: =IF(T73=0,0,IF(S73="F",T73,0)) -> 0 | AB73: =IF(T73=0,0,IF(S73="M",T73,0)) -> 0 | AC73: =IF(T73=0,0,IF(S73="F",T73*Z73,0)) -> 0
C74: TOTAL IMPOSTOS NA FABRICAÇÃO = | H74: TOTAL IMPOSTOS NA MONTAGEM = | L74: IMPOSTOS ( FABRICAÇÃO + MONTAGEM ) | S74: F | U74: TECNOSIL | AA74: =IF(T74=0,0,IF(S74="F",T74,0)) -> 0 | AB74: =IF(T74=0,0,IF(S74="M",T74,0)) -> 0 | AC74: =IF(T74=0,0,IF(S74="F",T74*Z74,0)) -> 0
D75: =SUM(E62:E72) -> 2949935.7 | I75: =SUM(J62:J72) -> 1542954.4 | M75: =D75+I75 -> 4492890.1 | AA75: =IF(T75=0,0,IF(S75="F",T75,0)) -> 0 | AB75: =IF(T75=0,0,IF(S75="M",T75,0)) -> 0 | AC75: =IF(T75=0,0,IF(S75="F",T75*Z75,0)) -> 0
AA76: =IF(T76=0,0,IF(S76="F",T76,0)) -> 0 | AB76: =IF(T76=0,0,IF(S76="M",T76,0)) -> 0 | AC76: =IF(T76=0,0,IF(S76="F",T76*Z76,0)) -> 0
C77: % IMPOSTOS NA FABRICAÇÃO = | H77: % IMPOSTOS NA MONTAGEM = | AA77: =IF(T77=0,0,IF(S77="F",T77,0)) -> 0 | AB77: =IF(T77=0,0,IF(S77="M",T77,0)) -> 0 | AC77: =IF(T77=0,0,IF(S77="F",T77*Z77,0)) -> 0
D78: =IF(D75=0,0,D75/D48) -> 0.22155556 | I78: =IF(I75=0,0,I75/I48) -> 0.058908352 | AA78: =IF(T78=0,0,IF(S78="F",T78,0)) -> 0 | AB78: =IF(T78=0,0,IF(S78="M",T78,0)) -> 0 | AC78: =IF(T78=0,0,IF(S78="F",T78*Z78,0)) -> 0
AA79: =IF(T79=0,0,IF(S79="F",T79,0)) -> 0 | AB79: =IF(T79=0,0,IF(S79="M",T79,0)) -> 0 | AC79: =IF(T79=0,0,IF(S79="F",T79*Z79,0)) -> 0
AA80: =IF(T80=0,0,IF(S80="F",T80,0)) -> 0 | AB80: =IF(T80=0,0,IF(S80="M",T80,0)) -> 0 | AC80: =IF(T80=0,0,IF(S80="F",T80*Z80,0)) -> 0
AA81: =IF(T81=0,0,IF(S81="F",T81,0)) -> 0 | AB81: =IF(T81=0,0,IF(S81="M",T81,0)) -> 0 | AC81: =IF(T81=0,0,IF(S81="F",T81*Z81,0)) -> 0
C82: 8- VENDA | AA82: =IF(T82=0,0,IF(S82="F",T82,0)) -> 0 | AB82: =IF(T82=0,0,IF(S82="M",T82,0)) -> 0 | AC82: =IF(T82=0,0,IF(S82="F",T82*Z82,0)) -> 0
AA83: =IF(T83=0,0,IF(S83="F",T83,0)) -> 0 | AB83: =IF(T83=0,0,IF(S83="M",T83,0)) -> 0 | AC83: =IF(T83=0,0,IF(S83="F",T83*Z83,0)) -> 0
C84: FABRICAÇÃO | H84: MONTAGEM | L84: FABRICAÇÃO + MONTAGEM | AA84: =IF(T84=0,0,IF(S84="F",T84,0)) -> 0 | AB84: =IF(T84=0,0,IF(S84="M",T84,0)) -> 0 | AC84: =IF(T84=0,0,IF(S84="F",T84*Z84,0)) -> 0
D85: =D48+D75 -> 16264591 | I85: =I48+I75 -> 27735409 | N85: =D85+I85 -> 44000000 | R85: ***** | S85: M | T85: =IF(S17<>0,INSUMOS!R274/ENTRADAS!F22*FECHAMENTO!S17,INSUMOS!R274) -> 13485714 | U85: Pré-moldados internos | AA85: =IF(T85=0,0,IF(S85="F",T85,0)) -> 0 | AB85: =IF(T85=0,0,IF(S85="M",T85,0)) -> 13485714 | AC85: =IF(T85=0,0,IF(S85="F",T85*Z85,0)) -> 0
AA86: =IF(T86=0,0,IF(S86="F",T86,0)) -> 0 | AB86: =IF(T86=0,0,IF(S86="M",T86,0)) -> 0 | AC86: =IF(T86=0,0,IF(S86="F",T86*Z86,0)) -> 0
C87: PERCENTUAL PARA REPRESENTANTE DE VENDAS = | J87: % ---------------------- | L87: ----------- VALOR= | N87: =N85*I87/100 -> 0 | AA87: =IF(T87=0,0,IF(S87="F",T87,0)) -> 0 | AB87: =IF(T87=0,0,IF(S87="M",T87,0)) -> 0 | AC87: =IF(T87=0,0,IF(S87="F",T87*Z87,0)) -> 0
D88: =IF(P88="OK",0,IF(ENTRADAS!D912="x","ESTE TANQUE CONTÉM COBERTURA ! =====================================================>>",0)) -> 0 | P88: OK | AA88: =IF(T88=0,0,IF(S88="F",T88,0)) -> 0 | AB88: =IF(T88=0,0,IF(S88="M",T88,0)) -> 0 | AC88: =IF(T88=0,0,IF(S88="F",T88*Z88,0)) -> 0
D89: =IF(P89="OK",0,"VERIFIQUE SEMPRE OS PREÇOS DE INSUMOS PENDENTES ! ===================================>>") -> 0 | P89: OK | AA89: =IF(T89=0,0,IF(S89="F",T89,0)) -> 0 | AB89: =IF(T89=0,0,IF(S89="M",T89,0)) -> 0 | AC89: =IF(T89=0,0,IF(S89="F",T89*Z89,0)) -> 0
AA90: =IF(T90=0,0,IF(S90="F",T90,0)) -> 0 | AB90: =IF(T90=0,0,IF(S90="M",T90,0)) -> 0 | AC90: =IF(T90=0,0,IF(S90="F",T90*Z90,0)) -> 0
E91: VALOR DE VENDA FINAL = | I91: =IF(L91<>0,"OPS !!!!",IF(R129="x",N85+N87-U156,N85+N87)) -> 44000000 | L91: =IF(G17=0," FALTA PERCENTUAL DE LUCRO !",IF(AND(GUINDASTE!N70+GUINDASTE!N83+GUINDASTE!N96>=1,G17>0)," ANÁLISE DE GUINDASTE INDEFINIDO !",IF('X MPa '!D72="X","FALTOU APAGAR X NA EQUIPE DA USINA",0))) -> 0 | AA91: =IF(T91=0,0,IF(S91="F",T91,0)) -> 0 | AB91: =IF(T91=0,0,IF(S91="M",T91,0)) -> 0 | AC91: =IF(T91=0,0,IF(S91="F",T91*Z91,0)) -> 0
AA92: =IF(T92=0,0,IF(S92="F",T92,0)) -> 0 | AB92: =IF(T92=0,0,IF(S92="M",T92,0)) -> 0 | AC92: =IF(T92=0,0,IF(S92="F",T92*Z92,0)) -> 0
AA93: =IF(T93=0,0,IF(S93="F",T93,0)) -> 0 | AB93: =IF(T93=0,0,IF(S93="M",T93,0)) -> 0 | AC93: =IF(T93=0,0,IF(S93="F",T93*Z93,0)) -> 0
AA94: =IF(T94=0,0,IF(S94="F",T94,0)) -> 0 | AB94: =IF(T94=0,0,IF(S94="M",T94,0)) -> 0 | AC94: =IF(T94=0,0,IF(S94="F",T94*Z94,0)) -> 0
AA95: =IF(T95=0,0,IF(S95="F",T95,0)) -> 0 | AB95: =IF(T95=0,0,IF(S95="M",T95,0)) -> 0 | AC95: =IF(T95=0,0,IF(S95="F",T95*Z95,0)) -> 0
C96: 9- PERCENTUAL DE VALORES SOBRE A VENDA | AA96: =IF(T96=0,0,IF(S96="F",T96,0)) -> 0 | AB96: =IF(T96=0,0,IF(S96="M",T96,0)) -> 0 | AC96: =IF(T96=0,0,IF(S96="F",T96*Z96,0)) -> 0
AA97: =IF(T97=0,0,IF(S97="F",T97,0)) -> 0 | AB97: =IF(T97=0,0,IF(S97="M",T97,0)) -> 0 | AC97: =IF(T97=0,0,IF(S97="F",T97*Z97,0)) -> 0
C98: CUSTO = | E98: =IF(N12=0,0,N12/I91) -> 0.72067722 | AA98: =IF(T98=0,0,IF(S98="F",T98,0)) -> 0 | AB98: =IF(T98=0,0,IF(S98="M",T98,0)) -> 0 | AC98: =IF(T98=0,0,IF(S98="F",T98*Z98,0)) -> 0
AA99: =IF(T99=0,0,IF(S99="F",T99,0)) -> 0 | AB99: =IF(T99=0,0,IF(S99="M",T99,0)) -> 0 | AC99: =IF(T99=0,0,IF(S99="F",T99*Z99,0)) -> 0
C100: LUCRO = | E100: =IF(N20=0,0,N20/I91) -> 0.16140189 | H100: =IF(ENTRADAS!F22=0,0,"VALOR SOMENTE DAS PAREDES para "&ENTRADAS!F22&" TQ ----------------------------------------------") -> VALOR SOMENTE DAS PAREDES para 4 TQ ---------------------------------------------- | M100: =IF(I91="OPS !!!!",0,I91-M102) -> 44000000 | P100: =IF(M100=0,0,M100/I91) -> 1 | AA100: =IF(T100=0,0,IF(S100="F",T100,0)) -> 0 | AB100: =IF(T100=0,0,IF(S100="M",T100,0)) -> 0 | AC100: =IF(T100=0,0,IF(S100="F",T100*Z100,0)) -> 0
AA101: =IF(T101=0,0,IF(S101="F",T101,0)) -> 0 | AB101: =IF(T101=0,0,IF(S101="M",T101,0)) -> 0 | AC101: =IF(T101=0,0,IF(S101="F",T101*Z101,0)) -> 0
C102: ROYALTIES = | E102: =IF(N34=0,0,N34/I91) -> 0.011343125 | H102: =IF(ENTRADAS!F22=0,0,IF(ENTRADAS!D912="X","VALOR SOMENTE DA COBERTURA para "&ENTRADAS!F22&" TQ ---------------------------------------------------------------------","NÃO HÁ COBERTURA------------------------------------------------------------------")) -> NÃO HÁ COBERTURA------------------------------------------------------------------ | M102: ='FECHAMENTO cobertura'!I91 -> 0 | P102: =IF(M102=0,0,M102/I91) -> 0 | AA102: =IF(T102=0,0,IF(S102="F",T102,0)) -> 0 | AB102: =IF(T102=0,0,IF(S102="M",T102,0)) -> 0 | AC102: =IF(T102=0,0,IF(S102="F",T102*Z102,0)) -> 0
AA103: =IF(T103=0,0,IF(S103="F",T103,0)) -> 0 | AB103: =IF(T103=0,0,IF(S103="M",T103,0)) -> 0 | AC103: =IF(T103=0,0,IF(S103="F",T103*Z103,0)) -> 0
C104: INVESTIMENTOS = | E104: =IF(N41=0,0,N41/I91) -> 0.0044666235 | AA104: =IF(T104=0,0,IF(S104="F",T104,0)) -> 0 | AB104: =IF(T104=0,0,IF(S104="M",T104,0)) -> 0 | AC104: =IF(T104=0,0,IF(S104="F",T104*Z104,0)) -> 0
AA105: =IF(T103=0,0,IF(S105="F",T105)) -> 0
C106: IMPOSTOS = | E106: =IF(M75=0,0,M75/I91) -> 0.10211114 | S106: F | U106: ESTE F serve para tirar o erro #N/D da célula T62
C110: 9- ÍNDICES | L110: =IF(ENTRADAS!D912=0,"paredes","paredes + ") -> paredes | O110: somente paredes | P110: somente cobertura | S110: M | U110: ESTE M serve para tirar o erro #N/D da célula U62
L111: =IF(ENTRADAS!D912=0,"sem cobertura","cobertura") -> sem cobertura
C113: =IF(ENTRADAS!D912="x","PREÇO DE CUSTO / m² de PAINEL FABRICADO E COBERTURA SEM IMPOSTOS","PREÇO DE CUSTO / m² de PAINEL FABRICADO SEM IMPOSTOS") -> PREÇO DE CUSTO / m² de PAINEL FABRICADO SEM IMPOSTOS | L113: =IF((N12+N34+N41)=0,0,(N12+N34+N41)/(CÁLCULOS!F83+LAJES!AK4)) -> 7458.1646 | M113: por m² | O113: =IF(L113=0,0,IF(M102=0,(N12+N34+N41)/(CÁLCULOS!F83),((N12+N34+N41)-('FECHAMENTO cobertura'!N12+'FECHAMENTO cobertura'!N34+'FECHAMENTO cobertura'!N41))/CÁLCULOS!F83)) -> 7458.1646 | P113: ='FECHAMENTO cobertura'!L112 -> 0
C115: =IF(ENTRADAS!D912="x","PREÇO DE CUSTO / m² de PAINEL FABRICADO E COBERTURA COM IMPOSTOS","PREÇO DE CUSTO / m² de PAINEL FABRICADO COM IMPOSTOS") -> PREÇO DE CUSTO / m² de PAINEL FABRICADO COM IMPOSTOS | L115: =IF((N12+N34+N41+M75)=0,0,(N12+N34+N41+M75)/(CÁLCULOS!F83+LAJES!AK4)) -> 8492.2109 | M115: por m² | O115: =IF(L115=0,0,IF(M102=0,(N12+N34+N41+M75)/(CÁLCULOS!F83),((N12+N34+N41+M75)-('FECHAMENTO cobertura'!N12+'FECHAMENTO cobertura'!N34+'FECHAMENTO cobertura'!N41+'FECHAMENTO cobertura'!M75))/(CÁLCULOS!F83))) -> 8492.2109 | P115: ='FECHAMENTO cobertura'!L114 -> 0
C117: =IF(ENTRADAS!D912="x","PREÇO DE CUSTO / m³ de PAINEL FABRICADO E COBERTURA SEM IMPOSTOS","PREÇO DE CUSTO / m³ de PAINEL FABRICADO SEM IMPOSTOS") -> PREÇO DE CUSTO / m³ de PAINEL FABRICADO SEM IMPOSTOS | L117: =IF((N12+N34+N41)=0,0,(N12+N34+N41)/(O38+LAJES!C53+LAJES!C60+LAJES!C66+LAJES!C72)) -> 12402.897 | M117: por m³ | O117: =IF(L117=0,0,IF(M102=0,(N12+N34+N41)/(O38),((N12+N34+N41)-('FECHAMENTO cobertura'!N12+'FECHAMENTO cobertura'!N34+'FECHAMENTO cobertura'!N41))/(O38+LAJES!C53+LAJES!C60+LAJES!C66+LAJES!C72))) -> 12402.897 | P117: ='FECHAMENTO cobertura'!L116 -> 0
C119: =IF(ENTRADAS!D912="x","PREÇO DE CUSTO / m³ de PAINEL FABRICADO E COBERTURA COM IMPOSTOS","PREÇO DE CUSTO / m³ de PAINEL FABRICADO COM IMPOSTOS") -> PREÇO DE CUSTO / m³ de PAINEL FABRICADO COM IMPOSTOS | L119: =IF((N12+N34+N41+M75)=0,0,(N12+N34+N41+M75)/(O38+LAJES!C53+LAJES!C60+LAJES!C66+LAJES!C72)) -> 14122.512 | M119: por m³ | O119: =IF(L119=0,0,IF(M102=0,(N12+N34+N41+M75)/(O38),((N12+N34+N41+M75)-('FECHAMENTO cobertura'!N12+'FECHAMENTO cobertura'!N34+'FECHAMENTO cobertura'!N41+'FECHAMENTO cobertura'!M75))/(O38))) -> 14122.512 | P119: ='FECHAMENTO cobertura'!L118 -> 0
C121: =IF(ENTRADAS!D912="x","PREÇO DE VENDA FINAL / m² de PAINEL FABRICADO E COBERTURA INCLUINDO IMPOSTOS","PREÇO DE VENDA FINAL / m² de PAINEL FABRICADO") -> PREÇO DE VENDA FINAL / m² de PAINEL FABRICADO | L121: =IF(I91="OPS !!!!",0,IF(I91=0,0,I91/(CÁLCULOS!F83+LAJES!AK4))) -> 10126.676 | M121: por m² | O121: =IF(I91="OPS !!!!",0,IF(I91=0,0,M100/CÁLCULOS!F83)) -> 10126.676 | P121: =IF(I91=0,0,'FECHAMENTO cobertura'!L120) -> 0
C123: =IF(ENTRADAS!D912="x","PREÇO DE VENDA FINAL / m³ de PAINEL FABRICADO E COBERTURA INCLUINDO IMPOSTOS","PREÇO DE VENDA FINAL / m³ de PAINEL FABRICADO") -> PREÇO DE VENDA FINAL / m³ de PAINEL FABRICADO | L123: =IF(I91="OPS !!!!",0,IF(I91=0,0,I91/(O38+LAJES!C53+LAJES!C60+LAJES!C66+LAJES!C72))) -> 16840.62 | M123: por m³ | O123: =IF(I91="OPS !!!!",0,IF(I91=0,0,M100/O38)) -> 16840.62 | P123: =IF(I91=0,0,'FECHAMENTO cobertura'!L122) -> 0

Sheet FECHAMENTO cobertura
E2: SISTEMA SC-10 e SC-14 FECHAMENTO FINAL | M2: DATA: | O2: =CÁLCULOS!O1 -> 45638
M3: REVISÃO: | O3: =CÁLCULOS!O2 -> 3
E4: CLIENTE: | F4: =CÁLCULOS!F3 -> Passarelli | M4: LOCAL:
E5: OBRA: | F5: =CÁLCULOS!F4 -> 12 tqs Nereda | M5: =CÁLCULOS!M4 -> São Paulo - Tatuapé
C9: 1- CUSTOS
C11: FABRICAÇÃO | G11: MONTAGEM | L11: FABRICAÇÃO + MONTAGEM
E12: =INSUMOS!V278 -> 0 | I12: =INSUMOS!V280 -> 0 | N12: =E12+I12 -> 0
C13: PERCENTUAL = | E13: =IF(E12=0,0,E12/N12) -> 0 | G13: PERCENTUAL = | J13: =IF(I12=0,0,I12/N12) -> 0
C17: 2- LUCRO ------ PERCENTUAL = | G17: =FECHAMENTO!G17 -> 23 | H17: %
C19: FABRICAÇÃO | G19: MONTAGEM | L19: FABRICAÇÃO + MONTAGEM
E20: =E12*G17/100 -> 0 | G20: LUCRO = | I20: =I12*G17/100 -> 0 | L20: LUCRO = | N20: =E20+I20 -> 0
C24: 3- SUB-TOTAL ( CUSTO + LUCRO )
C26: FABRICAÇÃO | G26: MONTAGEM | L26: FABRICAÇÃO + MONTAGEM
E27: =E12+E20 -> 0 | I27: =I12+I20 -> 0 | N27: =N12+N20 -> 0
C31: 4- ROYALTIES ------ PERCENTUAL = | G31: =FECHAMENTO!G31 -> 5 | H31: %
G33: REFERENTE À FABRICAÇÃO | L33: TOTAL DE ROYALTIES
I34: =G31*E27/100 -> 0 | N34: =I34 -> 0
C38: 5- INVESTIMENTOS= | E38: =U53 -> 501.47141 | F38: / m³ fabricado | J38: VOLUME FABRICADO ( painel )= | P38: m³ | S38: total= | T38: =INSUMOS!Q331+INSUMOS!Q356 -> 2509040.5
C40: REFERENTE À FABRICAÇÃO | G40: REFERENTE À MONTAGEM | L40: TOTAL INVESTIMENTOS | T40: considerando amortização em 3 anos
D41: =O38*E38*E13 -> 0 | I41: =O38*J13*E38 -> 0 | N41: =D41+I41 -> 0 | T41: média fabricação por dia=2,15 placas
C45: 6- TOTAL SEM IMPOSTOS | T45: por ano= 240 * 2,15 = 516 placas
C47: REFERENTE À FABRICAÇÃO | G47: REFERENTE À MONTAGEM | L47: TOTAL SEM IMPOSTOS | T47: 3 anos= 720 * 2,15 = 1548 placas
D48: =E27+D34+D41 -> 0 | I48: =I27+I34+I41 -> 0 | N48: =N27+N34+N41 -> 0
C50: TOTAL de MATERIAL | T50: volume de uma placa 6,65m= | V50: =90.5/28 -> 3.2321429 | W50: m³
C51: ( FABRICAÇÃO )= | E51: =INSUMOS!V145+INSUMOS!R250+INSUMOS!R251+INSUMOS!R252 -> 0 | T51: volume de 720 placas= | V51: =1548*V50 -> 5003.3571 | W51: m³
C53: VALOR p/ BASE de CÁLCULO | T53: amortiz/m³= | U53: =T38/V51 -> 501.47141
C54: de ICMS = | E54: =D48-E51 -> 0
C58: 7- IMPOSTOS
C60: FABRICAÇÃO | H60: MONTAGEM
C62: ICMS | D62: =FECHAMENTO!D62 -> 0.15275912 | E62: =(($D$48-E51)/(1-D62)-($D$48-E51)) -> 0 | H62: ISS | I62: =FECHAMENTO!I62 -> 0.05 | J62: =$I$48/(1-I62)-$I$48 -> 0
D63: =FECHAMENTO!D63 -> 0 | I63: =FECHAMENTO!I63 -> 0
C64: PIS | D64: =FECHAMENTO!D64 -> 0.0065 | E64: =(($D$48)/(1-D64)-($D$48)) -> 0 | H64: PIS | I64: =FECHAMENTO!I64 -> 0.0065 | J64: =$I$48/(1-I64)-$I$48 -> 0
D65: =FECHAMENTO!D65 -> 0 | I65: =FECHAMENTO!I65 -> 0
C66: CONFINS | D66: =FECHAMENTO!D66 -> 0.03 | E66: =(($D$48)/(1-D66)-($D$48)) -> 0 | H66: CONFINS | I66: =FECHAMENTO!I66 -> 0.03 | J66: =$I$48/(1-I66)-$I$48 -> 0
D67: =FECHAMENTO!D67 -> 0 | I67: =FECHAMENTO!I67 -> 0
C68: IR | D68: =FECHAMENTO!D68 -> 0.02 | E68: =(($D$48)/(1-D68)-($D$48)) -> 0 | H68: IR | I68: =FECHAMENTO!I68 -> 0.02 | J68: =$I$48/(1-I68)-$I$48 -> 0
D69: =FECHAMENTO!D69 -> 0 | I69: =FECHAMENTO!I69 -> 0
C70: CSLL | D70: =FECHAMENTO!D70 -> 0.0108 | E70: =(($D$48)/(1-D70)-($D$48)) -> 0 | H70: CSLL | I70: =FECHAMENTO!I70 -> 0.0108 | J70: =$I$48/(1-I70)-$I$48 -> 0
D71: =FECHAMENTO!D71 -> 0
C72: IPI | D72: =FECHAMENTO!D72 -> 0 | E72: =(($D$48-E65)/(1-D72)-($D$48-E65)) -> 0
C74: TOTAL IMPOSTOS NA FABRICAÇÃO = | H74: TOTAL IMPOSTOS NA MONTAGEM = | L74: IMPOSTOS ( FABRICAÇÃO + MONTAGEM )
D75: =SUM(E62:E72) -> 0 | I75: =SUM(J62:J72) -> 0 | M75: =D75+I75 -> 0
C77: % IMPOSTOS NA FABRICAÇÃO = | H77: % IMPOSTOS NA MONTAGEM =
D78: =IF(D75=0,0,D75/D48) -> 0 | I78: =IF(I75=0,0,I75/I48) -> 0
C82: 8- VENDA
C84: FABRICAÇÃO | H84: MONTAGEM | L84: FABRICAÇÃO + MONTAGEM
D85: =D48+D75 -> 0 | I85: =I48+I75 -> 0 | N85: =D85+I85 -> 0 | U85: OK
C87: PERCENTUAL PARA REPRESENTANTE DE VENDAS = | I87: =FECHAMENTO!I87 -> 0 | J87: % ---------------------- | L87: ----------- VALOR= | N87: =N85*I87/100 -> 0
D88: =IF(P88="OK",0,IF(ENTRADAS!D912="x","ESTE TANQUE CONTÉM COBERTURA ! =====================================================>>",0)) -> 0 | P88: OK
D89: =IF(P89="OK",0,"VERIFIQUE SEMPRE OS PREÇOS DE INSUMOS PENDENTES ! ===================================>>") -> 0 | P89: OK
E91: VALOR DE VENDA FINAL = | I91: =N85+N87 -> 0
C96: 9- PERCENTUAL DE VALORES SOBRE A VENDA
C98: CUSTO = | E98: =IF(N12=0,0,N12/I91) -> 0
C100: LUCRO = | E100: =IF(N20=0,0,N20/I91) -> 0
C102: ROYALTIES = | E102: =IF(N34=0,0,N34/I91) -> 0
C104: INVESTIMENTOS = | E104: =IF(N41=0,0,N41/I91) -> 0
C106: IMPOSTOS = | E106: =IF(M75=0,0,M75/I91) -> 0
C110: 9- ÍNDICES
C112: =IF(ENTRADAS!D912="x","PREÇO DE CUSTO / m² de COBERTURA SEM IMPOSTOS",0) -> 0 | L112: =IF((N12+N34+N41)=0,0,(N12+N34+N41)/(ENTRADAS!F22*LAJES!AK4)) -> 0
C114: =IF(ENTRADAS!D912="x","PREÇO DE CUSTO / m² de COBERTURA COM IMPOSTOS",0) -> 0 | L114: =IF((N12+N34+N41+M75)=0,0,(N12+N34+N41+M75)/(ENTRADAS!F22*LAJES!AK4)) -> 0
C116: =IF(ENTRADAS!D912="x","PREÇO DE CUSTO / m³ de COBERTURA SEM IMPOSTOS",0) -> 0 | L116: =IF((N12+N34+N41)=0,0,(N12+N34+N41)/(LAJES!C53+LAJES!C60+LAJES!C66+LAJES!C72)) -> 0
C118: =IF(ENTRADAS!D912="x","PREÇO DE CUSTO / m³ de COBERTURA COM IMPOSTOS",0) -> 0 | L118: =IF((N12+N34+N41+M75)=0,0,(N12+N34+N41+M75)/(LAJES!C53+LAJES!C60+LAJES!C66+LAJES!C72)) -> 0
C120: =IF(ENTRADAS!D912="x","PREÇO DE VENDA / m² de COBERTURA INCLUINDO IMPOSTOS",0) -> 0 | L120: =IF(I91=0,0,I91/(ENTRADAS!F22*LAJES!AK4)) -> 0
C122: =IF(ENTRADAS!D912="x","PREÇO DE VENDA / m³ de COBERTURA INCLUINDO IMPOSTOS",0) -> 0 | L122: =IF(I91=0,0,I91/(LAJES!C53+LAJES!C60+LAJES!C66+LAJES!C72)) -> 0

Sheet cronograma unit.
D2: DIGITE a DATA de INÍCIO: | J2: =IF(ENTRADAS!I15=0,0,IF(Q2=0,TODAY()+ENTRADAS!$Q$852,Q2)) -> 45914 | AL2: =IF(Q2=0,"SE VOCÊ NÃO DIGITAR UMA DATA ",0) -> SE VOCÊ NÃO DIGITAR UMA DATA | CV2: percentual de recuo no início da montagem das parede em relação
J3: =IF(ENTRADAS!I15=0,0,IF(Q2=0,TODAY()+2*ENTRADAS!$Q$852,Q2)) -> 45919 | AL3: =IF(Q2=0,"SERÁ CONSIDERADA A DATA DE HOJE",0) -> SERÁ CONSIDERADA A DATA DE HOJE | CV3: ao término da fabricaçao de paredes no caso do módulo 2: | GH3: 5 | GO3: %
D4: ="CLIENTE: "&ENTRADAS!F3 -> CLIENTE: Passarelli | BE4: ="LOCAL: "&FECHAMENTO!M5 -> LOCAL: São Paulo - Tatuapé - SP | CV4: módulo | DK4: 1 | DL4: 2 | DM4: 3 | DN4: 4
A5: =IF(B5=0,0,"XXX") -> 0 | D5: ="OBRA: "&ENTRADAS!F4 -> OBRA: 12 tqs Nereda | BE5: DATA: | BN5: =ENTRADAS!O1 -> 45638 | CV5: =IF(GUINDASTE!C123=1,2,IF(GUINDASTE!C125=1,1,2)) -> 2
H6: =IF(ENTRADAS!$Q$852>0,IF(ENTRADAS!$Q$852-H7>=0,1000,H7),H7) -> 1000 | I6: =IF(ENTRADAS!$Q$852>0,IF(ENTRADAS!$Q$852-I7>=0,1000,I7),I7) -> 1000 | J6: =IF(ENTRADAS!$Q$852>0,IF(ENTRADAS!$Q$852-J7>=0,1000,J7),J7) -> 1000 | K6: =IF(ENTRADAS!$Q$852>0,IF(ENTRADAS!$Q$852-K7>=0,1000,K7),K7) -> 1000 | L6: =IF(ENTRADAS!$Q$852>0,IF(ENTRADAS!$Q$852-L7>=0,1000,L7),L7) -> 1000 | M6: =IF(ENTRADAS!$Q$852>0,IF(ENTRADAS!$Q$852-M7>=0,1000,M7-ENTRADAS!$Q$852),M7) -> 1 | N6: =IF(ENTRADAS!$Q$852>0,IF(ENTRADAS!$Q$852-N7>=0,1000,N7-ENTRADAS!$Q$852),N7) -> 2 | O6: =IF(ENTRADAS!$Q$852>0,IF(ENTRADAS!$Q$852-O7>=0,1000,O7-ENTRADAS!$Q$852),O7) -> 3 | P6: =IF(ENTRADAS!$Q$852>0,IF(ENTRADAS!$Q$852-P7>=0,1000,P7-ENTRADAS!$Q$852),P7) -> 4 | Q6: =IF(ENTRADAS!$Q$852>0,IF(ENTRADAS!$Q$852-Q7>=0,1000,Q7-ENTRADAS!$Q$852),Q7) -> 5 | R6: =IF(ENTRADAS!$Q$852>0,IF(ENTRADAS!$Q$852-R7>=0,1000,R7-ENTRADAS!$Q$852),R7) -> 6 | S6: =IF(ENTRADAS!$Q$852>0,IF(ENTRADAS!$Q$852-S7>=0,1000,S7-ENTRADAS!$Q$852),S7) -> 7 | T6: =IF(ENTRADAS!$Q$852>0,IF(ENTRADAS!$Q$852-T7>=0,1000,T7-ENTRADAS!$Q$852),T7) -> 8 | ... IK6: =IF(ENTRADAS!$Q$852>0,IF(ENTRADAS!$Q$852-IK7>=0,1000,IK7-ENTRADAS!$Q$852),IK7) -> 233
H7: 1 | I7: 2 | J7: 3 | K7: 4 | L7: 5 | M7: 6 | N7: 7 | O7: 8 | P7: 9 | Q7: 10 | R7: 11 | S7: 12 | T7: 13 | U7: 14 | V7: 15 | W7: 16 | X7: 17 | Y7: 18 | Z7: 19 | AA7: 20 | AB7: 21 | AC7: 22 | AD7: 23 | AE7: 24 | AF7: 25 | AG7: 26 | AH7: 27 | AI7: 28 | AJ7: 29 | AK7: 30 | AL7: 31 | AM7: 32 | AN7: 33 | AO7: 34 | AP7: 35 | AQ7: 36 | AR7: 37 | AS7: 38 | AT7: 39 | AU7: 40 | AV7: 41 | AW7: 42 | AX7: 43 | AY7: 44 | AZ7: 45 | BA7: 46 | BB7: 47 | BC7: 48 | BD7: 49 | BE7: 50 | BF7: 51 | BG7: 52 | BH7: 53 | BI7: 54 | BJ7: 55 | BK7: 56 | BL7: 57 | BM7: 58 | BN7: 59 | BO7: 60 | BP7: 61 | BQ7: 62 | BR7: 63 | BS7: 64 | BT7: 65 | BU7: 66 | BV7: 67 | BW7: 68 | BX7: 69 | BY7: 70 | BZ7: 71 | CA7: 72 | CB7: 73 | CC7: 74 | CD7: 75 | CE7: 76 | CF7: 77 | CG7: 78 | CH7: 79 | CI7: 80 | CJ7: 81 | CK7: 82 | CL7: 83 | CM7: 84 | CN7: 85 | CO7: 86 | CP7: 87 | CQ7: 88 | CR7: 89 | CS7: 90 | CT7: 91 | CU7: 92 | CV7: 93 | CW7: 94 | CX7: 95 | CY7: 96 | CZ7: 97 | DA7: 98 | DB7: 99 | DC7: 100 | DD7: 101 | DE7: 102 | DF7: 103 | DG7: 104 | DH7: 105 | DI7: 106 | DJ7: 107 | DK7: 108 | DL7: 109 | DM7: 110 | DN7: 111 | DO7: 112 | DP7: 113 | DQ7: 114 | DR7: 115 | DS7: 116 | DT7: 117 | DU7: 118 | DV7: 119 | DW7: 120 | DX7: 121 | DY7: 122 | DZ7: 123 | EA7: 124 | EB7: 125 | EC7: 126 | ED7: 127 | EE7: 128 | EF7: 129 | EG7: 130 | EH7: 131 | EI7: 132 | EJ7: 133 | EK7: 134 | EL7: 135 | EM7: 136 | EN7: 137 | EO7: 138 | EP7: 139 | EQ7: 140 | ER7: 141 | ES7: 142 | ET7: 143 | EU7: 144 | EV7: 145 | EW7: 146 | EX7: 147 | EY7: 148 | EZ7: 149 | FA7: 150 | FB7: 151 | FC7: 152 | FD7: 153 | FE7: 154 | FF7: 155 | FG7: 156 | FH7: 157 | FI7: 158 | FJ7: 159 | FK7: 160 | FL7: 161 | FM7: 162 | FN7: 163 | FO7: 164 | FP7: 165 | FQ7: 166 | FR7: 167 | FS7: 168 | FT7: 169 | FU7: 170 | FV7: 171 | FW7: 172 | FX7: 173 | FY7: 174 | FZ7: 175 | GA7: 176 | GB7: 177 | GC7: 178 | GD7: 179 | GE7: 180 | GF7: 181 | GG7: 182 | GH7: 183 | GI7: 184 | GJ7: 185 | GK7: 186 | GL7: 187 | GM7: 188 | GN7: 189 | GO7: 190 | GP7: 191 | GQ7: 192 | GR7: 193 | GS7: 194 | GT7: 195 | GU7: 196 | GV7: 197 | GW7: 198 | GX7: 199 | GY7: 200 | GZ7: 201 | HA7: 202 | HB7: 203 | HC7: 204 | HD7: 205 | HE7: 206 | HF7: 207 | HG7: 208 | HH7: 209 | HI7: 210 | HJ7: 211 | HK7: 212 | HL7: 213 | HM7: 214 | HN7: 215 | HO7: 216 | HP7: 217 | HQ7: 218 | HR7: 219 | HS7: 220 | HT7: 221 | HU7: 222 | HV7: 223 | HW7: 224 | HX7: 225 | HY7: 226 | HZ7: 227 | IA7: 228 | IB7: 229 | IC7: 230 | ID7: 231 | IE7: 232 | IF7: 233 | IG7: 234 | IH7: 235 | II7: 236 | IJ7: 237 | IK7: 238
H9: =$J$2 -> 45914 | I9: =IF($J$2=0,0,H9+1) -> 45915 | J9: =IF($J$2=0,0,I9+1) -> 45916 | K9: =IF($J$2=0,0,J9+1) -> 45917 | L9: =IF($J$2=0,0,K9+1) -> 45918 | M9: =IF($J$2=0,0,L9+1) -> 45919 | N9: =IF($J$2=0,0,M9+1) -> 45920 | O9: =IF($J$2=0,0,N9+1) -> 45921 | P9: =IF($J$2=0,0,O9+1) -> 45922 | ... IK9: =IF($J$2=0,0,IJ9+1) -> 46151
B12: x | C12: =IF(F40<>0,F40,IF(F90<>0,F90,IF(F41<>0,F41,IF(F42<>0,F42,IF(F42<>0,F43,IF(F44<>0,F44,0)))))) -> 0 | H12: ="sem. "&N7/7 -> sem. 1 | O12: ="sem. "&U7/7 -> sem. 2 | V12: ="sem. "&AB7/7 -> sem. 3 | AC12: ="sem. "&AI7/7 -> sem. 4 | AJ12: ="sem. "&AP7/7 -> sem. 5 | AQ12: ="sem. "&AW7/7 -> sem. 6 | AX12: ="sem. "&BD7/7 -> sem. 7 | BE12: ="sem. "&BK7/7 -> sem. 8 | BL12: ="sem. "&BR7/7 -> sem. 9 | BS12: ="sem. "&BY7/7 -> sem. 10 | BZ12: ="sem. "&CF7/7 -> sem. 11 | CG12: ="sem. "&CM7/7 -> sem. 12 | CN12: ="sem. "&CT7/7 -> sem. 13 | CU12: ="sem. "&DA7/7 -> sem. 14 | DB12: ="sem. "&DH7/7 -> sem. 15 | DI12: ="sem. "&DO7/7 -> sem. 16 | DP12: ="sem. "&DV7/7 -> sem. 17 | DW12: ="sem. "&EC7/7 -> sem. 18 | ED12: ="sem. "&EJ7/7 -> sem. 19 | EK12: ="sem. "&EQ7/7 -> sem. 20 | ER12: ="sem. "&EX7/7 -> sem. 21 | EY12: ="sem. "&FE7/7 -> sem. 22 | FF12: ="sem. "&FL7/7 -> sem. 23 | FM12: ="sem. "&FS7/7 -> sem. 24 | FT12: ="sem. "&FZ7/7 -> sem. 25 | GA12: ="sem. "&GG7/7 -> sem. 26 | GH12: ="sem. "&GN7/7 -> sem. 27 | GO12: ="sem. "&GU7/7 -> sem. 28 | GV12: ="sem. "&HB7/7 -> sem. 29 | HC12: ="sem. "&HI7/7 -> sem. 30 | HJ12: ="sem. "&HP7/7 -> sem. 31 | HQ12: ="sem. "&HW7/7 -> sem. 32 | HX12: ="sem. "&ID7/7 -> sem. 33 | IE12: ="sem. "&IK7/7 -> sem. 34
A13: =IF($B$13=0,0,"XXX") -> XXX | B13: x | C13: ETAPAS DE SERVIÇOS | D13: DATAS | F13: PRAZO em dias corridos | H13: =H9 -> 45914 | K13: - | L13: =LARGE(H9:N11,1) -> 45920 | O13: =O9 -> 45921 | R13: - | S13: =LARGE(O9:U11,1) -> 45927 | V13: =V9 -> 45928 | Y13: - | Z13: =LARGE(V9:AB11,1) -> 45934 | AC13: =AC9 -> 45935 | AF13: - | AG13: =LARGE(AC9:AI11,1) -> 45941 | AJ13: =AJ9 -> 45942 | AM13: - | AN13: =LARGE(AJ9:AP11,1) -> 45948 | AQ13: =AQ9 -> 45949 | AT13: - | AU13: =LARGE(AQ9:AW11,1) -> 45955 | AX13: =AX9 -> 45956 | BA13: - | BB13: =LARGE(AX9:BD11,1) -> 45962 | BE13: =BE9 -> 45963 | BH13: - | BI13: =LARGE(BE9:BK11,1) -> 45969 | BL13: =BL9 -> 45970 | BO13: - | BP13: =LARGE(BL9:BR11,1) -> 45976 | BS13: =BS9 -> 45977 | BV13: - | BW13: =LARGE(BS9:BY11,1) -> 45983 | BZ13: =BZ9 -> 45984 | CC13: - | CD13: =LARGE(BZ9:CF11,1) -> 45990 | CG13: =CG9 -> 45991 | CJ13: - | CK13: =LARGE(CG9:CM11,1) -> 45997 | CN13: =CN9 -> 45998 | CQ13: - | CR13: =LARGE(CN9:CT11,1) -> 46004 | CU13: =CU9 -> 46005 | CX13: - | CY13: =LARGE(CU9:DA11,1) -> 46011 | DB13: =DB9 -> 46012 | DE13: - | DF13: =LARGE(DB9:DH11,1) -> 46018 | DI13: =DI9 -> 46019 | DL13: - | DM13: =LARGE(DI9:DO11,1) -> 46025 | DP13: =DP9 -> 46026 | DS13: - | DT13: =LARGE(DP9:DV11,1) -> 46032 | DW13: =DW9 -> 46033 | DZ13: - | EA13: =LARGE(DW9:EC11,1) -> 46039 | ED13: =ED9 -> 46040 | EG13: - | EH13: =LARGE(ED9:EJ11,1) -> 46046 | EK13: =EK9 -> 46047 | EN13: - | EO13: =LARGE(EK9:EQ11,1) -> 46053 | ER13: =ER9 -> 46054 | EU13: - | EV13: =LARGE(ER9:EX11,1) -> 46060 | EY13: =EY9 -> 46061 | FB13: - | FC13: =LARGE(EY9:FE11,1) -> 46067 | FF13: =FF9 -> 46068 | FI13: - | FJ13: =LARGE(FF9:FL11,1) -> 46074 | FM13: =FM9 -> 46075 | FP13: - | FQ13: =LARGE(FM9:FS11,1) -> 46081 | FT13: =FT9 -> 46082 | FW13: - | FX13: =LARGE(FT9:FZ11,1) -> 46088 | GA13: =GA9 -> 46089 | GD13: - | GE13: =LARGE(GA9:GG11,1) -> 46095 | GH13: =GH9 -> 46096 | GK13: - | GL13: =LARGE(GH9:GN11,1) -> 46102 | GO13: =GO9 -> 46103 | GR13: - | GS13: =LARGE(GO9:GU11,1) -> 46109 | GV13: =GV9 -> 46110 | GY13: - | GZ13: =LARGE(GV9:HB11,1) -> 46116 | HC13: =HC9 -> 46117 | HF13: - | HG13: =LARGE(HC9:HI11,1) -> 46123 | HJ13: =HJ9 -> 46124 | HM13: - | HN13: =LARGE(HJ9:HP11,1) -> 46130 | HQ13: =HQ9 -> 46131 | HT13: - | HU13: =LARGE(HQ9:HW11,1) -> 46137 | HX13: =HX9 -> 46138 | IA13: - | IB13: =LARGE(HX9:ID11,1) -> 46144 | IE13: =IE9 -> 46145 | IH13: - | II13: =LARGE(IE9:IK11,1) -> 46151
A14: =IF($B$13=0,0,"XXX") -> XXX | B14: ÍTEM
A15: =IF($B$13=0,0,"XXX") -> XXX
A16: =IF($B$13=0,0,"XXX") -> XXX
A17: =IF($B$17=0,0,"XXX") -> XXX | B17: =IF(ENTRADAS!$F$22=0,0,1) -> 1 | C17: =IF(ENTRADAS!$F$22=0,0,IF(ENTRADAS!$F$22=1,"PRAZO do TANQUE 01 ",IF(ENTRADAS!$F$22>=2,"PRAZO dos TANQUES de 1 a "&ENTRADAS!$F$22))) -> PRAZO dos TANQUES de 1 a 4 | D17: =IF(ENTRADAS!$F$22=0,0,"início:") -> início: | E17: =IF(ENTRADAS!$F$22=0,0,$J$2) -> 45914 | F17: =RELATÓRIO!W215 -> 139.7375 | G17: =IF(ENTRADAS!$F$22=0,0,"dias") -> dias | H17: =IF(OR(H7<$F$17,H21=1000,H105=1000,H189=1000,H273=1000,H20="x",H6=1000),"X",0) -> X | I17: =IF(OR(I7<$F$17,I21=1000,I105=1000,I189=1000,I273=1000,I20="x",I6=1000),"X",0) -> X | J17: =IF(OR(J7<$F$17,J21=1000,J105=1000,J189=1000,J273=1000,J20="x",J6=1000),"X",0) -> X | K17: =IF(OR(K7<$F$17,K21=1000,K105=1000,K189=1000,K273=1000,K20="x",K6=1000),"X",0) -> X | L17: =IF(OR(L7<$F$17,L21=1000,L105=1000,L189=1000,L273=1000,L20="x",L6=1000),"X",0) -> X | M17: =IF(OR(M7<$F$17,M21=1000,M105=1000,M189=1000,M273=1000,M20="x",M6=1000),"X",0) -> X | N17: =IF(OR(N7<$F$17,N21=1000,N105=1000,N189=1000,N273=1000,N20="x",N6=1000),"X",0) -> X | O17: =IF(OR(O7<$F$17,O21=1000,O105=1000,O189=1000,O273=1000,O20="x",O6=1000),"X",0) -> X | ... IK17: =IF(OR(IK7<$F$17,IK21=1000,IK105=1000,IK189=1000,IK273=1000,IK20="x",IK6=1000),"X",0) -> 0
A18: =IF($B$17=0,0,"XXX") -> XXX | D18: =IF(ENTRADAS!$F$22=0,0,"término:") -> término: | E18: =IF(ENTRADAS!$F$22=0,0,E17+F17) -> 46053.738
A19: =IF(B19=0,0,"XXX") -> XXX | B19: x | H19: =IF(H7<$F$17,H7,IF(OR(H21=1000,H105=1000,H189=1000,H273=1000),H7,0)) -> 1 | I19: =IF(I7<$F$17,I7,IF(OR(I21=1000,I105=1000,I189=1000,I273=1000),I7,0)) -> 2 | J19: =IF(J7<$F$17,J7,IF(OR(J21=1000,J105=1000,J189=1000,J273=1000),J7,0)) -> 3 | K19: =IF(K7<$F$17,K7,IF(OR(K21=1000,K105=1000,K189=1000,K273=1000),K7,0)) -> 4 | L19: =IF(L7<$F$17,L7,IF(OR(L21=1000,L105=1000,L189=1000,L273=1000),L7,0)) -> 5 | M19: =IF(M7<$F$17,M7,IF(OR(M21=1000,M105=1000,M189=1000,M273=1000),M7,0)) -> 6 | N19: =IF(N7<$F$17,N7,IF(OR(N21=1000,N105=1000,N189=1000,N273=1000),N7,0)) -> 7 | O19: =IF(O7<$F$17,O7,IF(OR(O21=1000,O105=1000,O189=1000,O273=1000),O7,0)) -> 8 | ... IK19: =IF(IK7<$F$17,IK7,IF(OR(IK21=1000,IK105=1000,IK189=1000,IK273=1000),IK7,0)) -> 0
H20: =IF(AND(H7>LARGE($H$19:$IK$19,1),H7<LARGE($H$19:$IK$19,1)+1),"x",0) -> 0 | I20: =IF(AND(I7>LARGE($H$19:$IK$19,1),I7<LARGE($H$19:$IK$19,1)+1),"x",0) -> 0 | J20: =IF(AND(J7>LARGE($H$19:$IK$19,1),J7<LARGE($H$19:$IK$19,1)+1),"x",0) -> 0 | K20: =IF(AND(K7>LARGE($H$19:$IK$19,1),K7<LARGE($H$19:$IK$19,1)+1),"x",0) -> 0 | L20: =IF(AND(L7>LARGE($H$19:$IK$19,1),L7<LARGE($H$19:$IK$19,1)+1),"x",0) -> 0 | M20: =IF(AND(M7>LARGE($H$19:$IK$19,1),M7<LARGE($H$19:$IK$19,1)+1),"x",0) -> 0 | N20: =IF(AND(N7>LARGE($H$19:$IK$19,1),N7<LARGE($H$19:$IK$19,1)+1),"x",0) -> 0 | O20: =IF(AND(O7>LARGE($H$19:$IK$19,1),O7<LARGE($H$19:$IK$19,1)+1),"x",0) -> 0 | ... IK20: =IF(AND(IK7>LARGE($H$19:$IK$19,1),IK7<LARGE($H$19:$IK$19,1)+1),"x",0) -> 0
A21: =IF(B21=0,0,"XXX") -> XXX | B21: =IF(ENTRADAS!$F$22=0,0,"1.1") -> 1.1 | C21: =IF(ENTRADAS!$F$22=0,0,"EXECUÇÃO DO TANQUE "&D43) -> EXECUÇÃO DO TANQUE 1 | D21: =IF(ENTRADAS!$F$22=0,0,"início:") -> início: | E21: =IF(ENTRADAS!$F$22=0,0,D45) -> 45919 | F21: =COUNTIF(H21:IK22,1000) -> 55 | G21: =IF(ENTRADAS!$F$22=0,0,"dias") -> dias | H21: =IF(OR(H33+H35+H37>=10,H88=1000),1000,0) -> 0 | I21: =IF(OR(I33+I35+I37>=10,I88=1000),1000,0) -> 0 | J21: =IF(OR(J33+J35+J37>=10,J88=1000),1000,0) -> 0 | K21: =IF(OR(K33+K35+K37>=10,K88=1000),1000,0) -> 0 | L21: =IF(OR(L33+L35+L37>=10,L88=1000),1000,0) -> 0 | M21: =IF(OR(M33+M35+M37>=10,M88=1000),1000,0) -> 1000 | N21: =IF(OR(N33+N35+N37>=10,N88=1000),1000,0) -> 1000 | O21: =IF(OR(O33+O35+O37>=10,O88=1000),1000,0) -> 1000 | ... IK21: =IF(OR(IK33+IK35+IK37>=10,IK88=1000),1000,0) -> 0
A22: =IF(B21=0,0,"XXX") -> XXX | D22: =IF(ENTRADAS!$F$22=0,0,"término:") -> término: | E22: =IF(ENTRADAS!$F$22=0,0,IF(ENTRADAS!$D$912<>0,E32,E30)) -> 45972.25
A23: =IF(B23=0,0,"XXX") -> XXX | B23: =IF(ENTRADAS!$F$22=0,0,"1.1.1") -> 1.1.1 | C23: =IF(ENTRADAS!$F$22=0,0,"CONFECÇÃO DE PAREDES") -> CONFECÇÃO DE PAREDES | D23: =IF(ENTRADAS!$F$22=0,0,"início:") -> início: | E23: =D49 -> 45919 | F23: =D48 -> 25.25 | G23: =IF(ENTRADAS!$F$22=0,0,"dias") -> dias | H23: =H48 -> 0 | I23: =I48 -> 0 | J23: =J48 -> 0 | K23: =K48 -> 0 | L23: =L48 -> 0 | M23: =M48 -> 10 | N23: =N48 -> 10 | O23: =O48 -> 10 | ... IK23: =IK48 -> 0
A24: =IF(B23=0,0,"XXX") -> XXX | D24: =IF(ENTRADAS!$F$22=0,0,"término:") -> término: | E24: =D50 -> 45943.25
A25: =IF(B25=0,0,"XXX") -> 0 | B25: =IF(F25=0,0,"1.1.2") -> 0 | C25: =IF(F25=0,0,"CONFECÇÃO DE COBERTURA") -> 0 | D25: =IF(F25=0,0,"início:") -> 0 | E25: =IF(F25=0,0,IF(D54<>0,D54,D55)) -> 0 | F25: =IF(ENTRADAS!D912=0,0,E56-E55-E54) -> 0 | G25: =IF(F25=0,0,"dias") -> 0 | H25: =H52 -> 0 | I25: =I52 -> 0 | J25: =J52 -> 0 | K25: =K52 -> 0 | L25: =L52 -> 0 | M25: =M52 -> 0 | N25: =N52 -> 0 | O25: =O52 -> 0 | ... IK25: =IK52 -> 0
A26: =IF(B25=0,0,"XXX") -> 0 | C26: =IF(F25=0,0,"COMPARTILHADA COM PAREDES") -> 0 | D26: =IF(F25=0,0,"término:") -> 0 | E26: =IF(F25=0,0,E25+F25-1) -> 0
A27: =IF(B27=0,0,"XXX") -> 0 | B27: =IF(AND(F25>=0,F27=0),0,IF(AND(F25=0,F27>0),"1.1.2",IF(F25+F27=0,0,"1.1.3"))) -> 0 | C27: =IF(F27=0,0,"CONFECÇÃO DE COBERTURA NÃO") -> 0 | D27: =IF(F27=0,0,"início:") -> 0 | E27: =IF(F27=0,0,D66+D62) -> 0 | F27: =IF(D61>0,D61,D64) -> 0 | G27: =IF(F27=0,0,"dias") -> 0 | H27: =IF(OR(H64=10,H61=10),10,0) -> 0 | I27: =IF(OR(I64=10,I61=10),10,0) -> 0 | J27: =IF(OR(J64=10,J61=10),10,0) -> 0 | K27: =IF(OR(K64=10,K61=10),10,0) -> 0 | L27: =IF(OR(L64=10,L61=10),10,0) -> 0 | M27: =IF(OR(M64=10,M61=10),10,0) -> 0 | N27: =IF(OR(N64=10,N61=10),10,0) -> 0 | O27: =IF(OR(O64=10,O61=10),10,0) -> 0 | ... IK27: =IF(OR(IK64=10,IK61=10),10,0) -> 0
A28: =IF(B27=0,0,"XXX") -> 0 | C28: =IF(F27=0,0,"COMPARTILHADA COM PAREDES") -> 0 | D28: =IF(F27=0,0,"término:") -> 0 | E28: =IF(F27=0,0,D67+D63) -> 0
A29: =IF(B29=0,0,"XXX") -> XXX | B29: =IF(ENTRADAS!$F$22=0,0,IF(AND(B25=0,B27=0),"1.1.2",IF(AND(B25>0,B27=0),"1.1.3",IF(B27="1.1.2","1.1.3",IF(B27="1.1.3","1.1.4","1.1.2"))))) -> 1.1.2 | C29: =IF(ENTRADAS!$F$22=0,0,"MONTAGEM DAS PAREDES") -> MONTAGEM DAS PAREDES | D29: =IF(ENTRADAS!$F$22=0,0,"início:") -> início: | E29: =D77 -> 45944.25 | F29: =D72 -> 29 | G29: =IF(ENTRADAS!$F$22=0,0,"dias") -> dias | H29: =H72 -> 0 | I29: =I72 -> 0 | J29: =J72 -> 0 | K29: =K72 -> 0 | L29: =L72 -> 0 | M29: =M72 -> 0 | N29: =N72 -> 0 | O29: =O72 -> 0 | ... IK29: =IK72 -> 0
A30: =IF(B29=0,0,"XXX") -> XXX | D30: =IF(ENTRADAS!$F$22=0,0,"término:") -> término: | E30: =D78 -> 45972.25
A31: =IF(B31=0,0,"XXX") -> 0 | B31: =IF(ENTRADAS!$D$912=0,0,IF(B29="1.1.2","1.3",IF(B29="1.1.3","1.1.4",IF(B29="1.1.4","1.1.5",0)))) -> 0 | C31: =IF(F31=0,0,"MONTAGEM DA COBERTURA") -> 0 | D31: =IF(F31=0,0,"início:") -> 0 | E31: =D88 -> 45969.35 | F31: =D83 -> 0 | G31: =IF(F31=0,0,"dias") -> 0 | H31: =H83 -> 0 | I31: =I83 -> 0 | J31: =J83 -> 0 | K31: =K83 -> 0 | L31: =L83 -> 0 | M31: =M83 -> 0 | N31: =N83 -> 0 | O31: =O83 -> 0 | ... IK31: =IK83 -> 0
A32: =IF(B31=0,0,"XXX") -> 0 | D32: =IF(F31=0,0,"término:") -> 0 | E32: =D89 -> 45968.35
